Workbook

Sheet Матрица с индикаторами
A1: Индекс | B1: Содержание | C1: Философия | D1: История (история России, всеобщая история) | E1: Иностранный язык | F1: Безопасность жизнедеятельности | G1: Физическая культура и спорт | H1: Информатика | I1: Цифровые технологии самообразования | J1: Религии мира | K1: Тренинг-практикум по самоорганизации и саморазвитию | L1: Физика | M1: Химия | N1: Математика | O1: Русский язык и деловые коммуникации | P1: Общий курс транспорта | Q1: Организация доступной среды | R1: Правовое обеспечение профессиональной деятельности | S1: Инженерная и компьютерная графика | T1: Экономика | U1: Экология | V1: Менеджмент | W1: Метрология, стандартизация и сертификация | X1: Транспортно-технологические системы | Y1: Системы искусственного интеллекта | Z1: Информационные технологии на транспорте. Цифровизация технологических процессов | AA1: Математическое моделирование транспортных процессов | AB1: Менеджмент качества и эффективность технических и технологических мероприятий в транспортных процессах | AC1: История России | AD1: Элективные курсы по физической культуре и спорту | AE1: Теория и практика логистики | AF1: Управление грузовой и коммерческой работой. Грузоведение | AG1: Транспортная логистика | AH1: Промышленный транспорт | AI1: Организация движения на железнодорожном транспорте | AJ1: Железнодорожная транспортная инфраструктура | AK1: Управление эксплуатационной работой | AL1: Организация логистики пассажирских перевозок | AM1: Обеспечение безопасности на транспорте | AN1: Хладотранспорт и основы теплотехники | AO1: Организация перевозок скоропортящихся грузов | AP1: Основы транспортного бизнеса | AQ1: Аутсорсинг на транспорте | AR1: Организация контейнерных и пакетных перевозок | AS1: Терминальные системы транспорта | AT1: Организация перевозок и тарифы в международных сообщениях | AU1: Организация мультимодальных перевозок | AV1: Организация работы экспедиторских фирм | AW1: Сервис на транспорте | AX1: Учебная практика (ознакомительная практика) | AY1: Производственная практика (технологическая (производственно-технологическая) практика) | AZ1: Производственная практика (эксплуатационная практика) | BA1: Производственная практика (преддипломная практика) | BB1: Итого без учета факультативов | BC1: История религиозной культуры | BD1: Построение бизнес-модели | BE1: Итого для факультативов | BF1: Итого
C2: Б1.О.01 | D2: Б1.О.02 | E2: Б1.О.03 | F2: Б1.О.04 | G2: Б1.О.05 | H2: Б1.О.06.01 | I2: Б1.О.06.02 | J2: Б1.О.07 | K2: Б1.О.08 | L2: Б1.О.09 | M2: Б1.О.10 | N2: Б1.О.11 | O2: Б1.О.12 | P2: Б1.О.13 | Q2: Б1.О.14 | R2: Б1.О.15 | S2: Б1.О.16 | T2: Б1.О.17 | U2: Б1.О.18 | V2: Б1.О.19 | W2: Б1.О.20 | X2: Б1.О.21 | Y2: Б1.О.22.01 | Z2: Б1.О.22.02 | AA2: Б1.О.23 | AB2: Б1.О.24 | AC2: Б1.О.25 | AD2: Б1.В.01.01 | AE2: Б1.В.02 | AF2: Б1.В.03 | AG2: Б1.В.04 | AH2: Б1.В.05 | AI2: Б1.В.06 | AJ2: Б1.В.07 | AK2: Б1.В.08 | AL2: Б1.В.09 | AM2: Б1.В.10 | AN2: Б1.В.ДВ.01.01 | AO2: Б1.В.ДВ.01.02 | AP2: Б1.В.ДВ.02.01 | AQ2: Б1.В.ДВ.02.02 | AR2: Б1.В.ДВ.03.01 | AS2: Б1.В.ДВ.03.02 | AT2: Б1.В.ДВ.04.01 | AU2: Б1.В.ДВ.04.02 | AV2: Б1.В.ДВ.05.01 | AW2: Б1.В.ДВ.05.02 | AX2: Б2.О.01(У) | AY2: Б2.В.01(П) | AZ2: Б2.В.02(П) | BA2: Б2.В.03(Пд) | BC2: ФТД.01 | BD2: ФТД.02
C3: УК-1.1; УК-1.2 | D3: УК-5.1; УК-5.2 | E3: УК-4.3; УК-4.4 | F3: УК-8.1; УК-8.2; УК-8.3 | G3: УК-7.1; УК-7.2 | H3: ОПК-4.1 | I3: ОПК-4.2 | J3: УК-5.3 | K3: УК-6.1; УК-6.2 | L3: ОПК-1.2; ОПК-1.3 | M3: ОПК-1.2; ОПК-1.3 | N3: ОПК-1.1 | O3: УК-4.1; УК-4.2 | P3: ОПК-5.3 | Q3: УК-9.1; УК-9.2 | R3: УК-2.1; УК-11.1; УК-11.2 | S3: ОПК-1.4 | T3: УК-10.1; УК-10.2; ОПК-2.2 | U3: ОПК-2.1 | V3: УК-2.2; УК-3.1; УК-3.2; ОПК-2.3 | W3: ОПК-3.1; ОПК-3.2; ОПК-6.2 | X3: ОПК-2.4; ОПК-5.2 | Y3: ОПК-4.4 | Z3: ОПК-4.2; ОПК-4.3 | AA3: ОПК-1.5; ПК-5.1 | AB3: ОПК-5.1; ОПК-6.1; ПК-5.3 | AC3: УК-2.1; УК-5.1; УК-5.2 | AD3: УК-7.3 | AE3: ПК-5.5 | AF3: ПК-1.1; ПК-1.2 | AG3: ПК-5.2 | AH3: ПК-4.2 | AI3: ПК-2.4 | AJ3: ПК-3.1; ПК-3.2 | AK3: ПК-2.1 | AL3: ПК-6.1; ПК-6.2 | AM3: ПК-2.2; ПК-2.3 | AN3: ПК-1.3 | AO3: ПК-1.3 | AP3: ПК-4.3; ПК-4.4 | AQ3: ПК-4.3; ПК-4.4 | AR3: ПК-5.4 | AS3: ПК-5.4 | AT3: ПК-1.4 | AU3: ПК-1.4 | AV3: ПК-4.1 | AW3: ПК-4.1 | AX3: ОПК-5.3; ПК-5.5 | AY3: ПК-1.2; ПК-2.1; ПК-3.1; ПК-3.2; ПК-5.2 | AZ3: ПК-1.1; ПК-1.3; ПК-2.4; ПК-4.1; ПК-4.4; ПК-5.4; ПК-5.5 | BA3: ПК-1.4; ПК-2.2; ПК-2.3; ПК-4.2; ПК-4.3; ПК-5.1; ПК-5.3; ПК-6.1; ПК-6.2 | BC3: УК-5.3 | BD3: УК-2.2
A4: УК-1 | B4: =VLOOKUP(A4,Лист1!B:C,2,0) -> Способен осуществлять поиск, критический анализ и синтез информации, применять системный подход для решения поставленных задач | C4: 18 | D4: =IFERROR(IF(SEARCH($A4,D$3)<>0,1,""),"") | E4: =IFERROR(IF(SEARCH($A4,E$3)<>0,1,""),"") | F4: =IFERROR(IF(SEARCH($A4,F$3)<>0,1,""),"") | G4: =IFERROR(IF(SEARCH($A4,G$3)<>0,1,""),"") | H4: =IFERROR(IF(SEARCH($A4,H$3)<>0,1,""),"") | I4: =IFERROR(IF(SEARCH($A4,I$3)<>0,1,""),"") | J4: =IFERROR(IF(SEARCH($A4,J$3)<>0,1,""),"") | K4: =IFERROR(IF(SEARCH($A4,K$3)<>0,1,""),"") | ... Q4: =IFERROR(IF(SEARCH($A4,Q$3)<>0,1,""),"") | S4: =IFERROR(IF(SEARCH($A4,S$3)<>0,1,""),"") | U4: =IFERROR(IF(SEARCH($A4,U$3)<>0,1,""),"") | V4: =IFERROR(IF(SEARCH($A4,V$3)<>0,1,""),"") | W4: =IFERROR(IF(SEARCH($A4,W$3)<>0,1,""),"") | X4: =IFERROR(IF(SEARCH($A4,X$3)<>0,1,""),"") | Y4: =IFERROR(IF(SEARCH($A4,Y$3)<>0,1,""),"") | Z4: =IFERROR(IF(SEARCH($A4,Z$3)<>0,1,""),"") | AA4: =IFERROR(IF(SEARCH($A4,AA$3)<>0,1,""),"") | AB4: =IFERROR(IF(SEARCH($A4,AB$3)<>0,1,""),"") | ... BA4: =IFERROR(IF(SEARCH($A4,BA$3)<>0,1,""),"") | BB4: =SUM(C4:BA4) -> 18 | BE4: =SUM(BC4:BD4) -> 0 | BF4: =BB4+BE4 -> 18
A5: УК-1.1 | B5: =VLOOKUP(A5,Лист1!B:C,2,0) -> Осуществляет поиск информации, критически оценивает надежность источников информации, работает с противоречивой информацией из разных источников | C5: 9 | D5: =IFERROR(SEARCH($A5,D$3),"") | E5: =IFERROR(SEARCH($A5,E$3),"") | F5: =IFERROR(SEARCH($A5,F$3),"") | G5: =IFERROR(SEARCH($A5,G$3),"") | H5: =IFERROR(SEARCH($A5,H$3),"") | I5: =IFERROR(SEARCH($A5,I$3),"") | J5: =IFERROR(SEARCH($A5,J$3),"") | K5: =IFERROR(SEARCH($A5,K$3),"") | ... BA5: =IFERROR(SEARCH($A5,BA$3),"") | BB5: =SUM(C5:BA5) -> 9 | BC5: =IFERROR(SEARCH($A5,BC$3),"") | BD5: =IFERROR(SEARCH($A5,BD$3),"") | BE5: =SUM(BC5:BD5) -> 0 | BF5: =BB5+BE5 -> 9
A6: УК-1.2 | B6: =VLOOKUP(A6,Лист1!B:C,2,0) -> Анализирует проблемную ситуацию, выявляет ее составляющие и связи между ними, формулирует и аргументирует выводы и суждения | C6: 9 | D6: =IFERROR(SEARCH($A6,D$3),"") | E6: =IFERROR(SEARCH($A6,E$3),"") | F6: =IFERROR(SEARCH($A6,F$3),"") | G6: =IFERROR(SEARCH($A6,G$3),"") | H6: =IFERROR(SEARCH($A6,H$3),"") | I6: =IFERROR(SEARCH($A6,I$3),"") | J6: =IFERROR(SEARCH($A6,J$3),"") | K6: =IFERROR(SEARCH($A6,K$3),"") | ... BA6: =IFERROR(SEARCH($A6,BA$3),"") | BB6: =SUM(C6:BA6) -> 9 | BC6: =IFERROR(SEARCH($A6,BC$3),"") | BD6: =IFERROR(SEARCH($A6,BD$3),"") | BE6: =SUM(BC6:BD6) -> 0 | BF6: =BB6+BE6 -> 9
A7: УК-2 | B7: =VLOOKUP(A7,Лист1!B:C,2,0) -> Способен определять круг задач в рамках поставленной цели и выбирать оптимальные способы их решения, исходя из действующих правовых норм, имеющихся ресурсов и ограничений | C7: =IFERROR(IF(SEARCH($A7,C$3)<>0,1,""),"") | D7: =IFERROR(IF(SEARCH($A7,D$3)<>0,1,""),"") | E7: =IFERROR(IF(SEARCH($A7,E$3)<>0,1,""),"") | F7: =IFERROR(IF(SEARCH($A7,F$3)<>0,1,""),"") | G7: =IFERROR(IF(SEARCH($A7,G$3)<>0,1,""),"") | H7: =IFERROR(IF(SEARCH($A7,H$3)<>0,1,""),"") | I7: =IFERROR(IF(SEARCH($A7,I$3)<>0,1,""),"") | J7: =IFERROR(IF(SEARCH($A7,J$3)<>0,1,""),"") | ... Q7: =IFERROR(IF(SEARCH($A7,Q$3)<>0,1,""),"") | R7: 2 | S7: =IFERROR(IF(SEARCH($A7,S$3)<>0,1,""),"") | T7: =IFERROR(IF(SEARCH($A7,T$3)<>0,1,""),"") | U7: =IFERROR(IF(SEARCH($A7,U$3)<>0,1,""),"") | V7: 2 | W7: =IFERROR(IF(SEARCH($A7,W$3)<>0,1,""),"") | X7: =IFERROR(IF(SEARCH($A7,X$3)<>0,1,""),"") | Y7: =IFERROR(IF(SEARCH($A7,Y$3)<>0,1,""),"") | Z7: =IFERROR(IF(SEARCH($A7,Z$3)<>0,1,""),"") | AA7: =IFERROR(IF(SEARCH($A7,AA$3)<>0,1,""),"") | AB7: =IFERROR(IF(SEARCH($A7,AB$3)<>0,1,""),"") | AC7: 14 | AD7: =IFERROR(IF(SEARCH($A7,AD$3)<>0,1,""),"") | AE7: =IFERROR(IF(SEARCH($A7,AE$3)<>0,1,""),"") | AF7: =IFERROR(IF(SEARCH($A7,AF$3)<>0,1,""),"") | AG7: =IFERROR(IF(SEARCH($A7,AG$3)<>0,1,""),"") | AH7: =IFERROR(IF(SEARCH($A7,AH$3)<>0,1,""),"") | AI7: =IFERROR(IF(SEARCH($A7,AI$3)<>0,1,""),"") | AJ7: =IFERROR(IF(SEARCH($A7,AJ$3)<>0,1,""),"") | AK7: =IFERROR(IF(SEARCH($A7,AK$3)<>0,1,""),"") | ... BA7: =IFERROR(IF(SEARCH($A7,BA$3)<>0,1,""),"") | BB7: =SUM(C7:BA7) -> 18 | BC7: =IFERROR(SEARCH(_xlfn.CONCAT(" ",$A7),#REF!),"") | BD7: 18 | BE7: =SUM(BC7:BD7) -> 18 | BF7: =BB7+BE7 -> 36
A8: УК-2.1 | B8: =VLOOKUP(A8,Лист1!B:C,2,0) -> Решает ситуационные задачи с учетом трудовых и социальных факторов в рамках нормативно-правового регулирования | C8: =IFERROR(SEARCH($A8,C$3),"") | D8: =IFERROR(SEARCH($A8,D$3),"") | E8: =IFERROR(SEARCH($A8,E$3),"") | F8: =IFERROR(SEARCH($A8,F$3),"") | G8: =IFERROR(SEARCH($A8,G$3),"") | H8: =IFERROR(SEARCH($A8,H$3),"") | I8: =IFERROR(SEARCH($A8,I$3),"") | J8: =IFERROR(SEARCH($A8,J$3),"") | ... Q8: =IFERROR(SEARCH($A8,Q$3),"") | R8: 2 | S8: =IFERROR(SEARCH($A8,S$3),"") | T8: =IFERROR(SEARCH($A8,T$3),"") | U8: =IFERROR(SEARCH($A8,U$3),"") | V8: =IFERROR(SEARCH($A8,V$3),"") | W8: =IFERROR(SEARCH($A8,W$3),"") | X8: =IFERROR(SEARCH($A8,X$3),"") | Y8: =IFERROR(SEARCH($A8,Y$3),"") | Z8: =IFERROR(SEARCH($A8,Z$3),"") | ... AB8: =IFERROR(SEARCH($A8,AB$3),"") | AC8: 14 | AD8: =IFERROR(SEARCH($A8,AD$3),"") | AE8: =IFERROR(SEARCH($A8,AE$3),"") | AF8: =IFERROR(SEARCH($A8,AF$3),"") | AG8: =IFERROR(SEARCH($A8,AG$3),"") | AH8: =IFERROR(SEARCH($A8,AH$3),"") | AI8: =IFERROR(SEARCH($A8,AI$3),"") | AJ8: =IFERROR(SEARCH($A8,AJ$3),"") | AK8: =IFERROR(SEARCH($A8,AK$3),"") | ... BA8: =IFERROR(SEARCH($A8,BA$3),"") | BB8: =SUM(C8:BA8) -> 16 | BC8: =IFERROR(SEARCH($A8,BC$3),"") | BD8: =IFERROR(SEARCH($A8,BD$3),"") | BE8: =SUM(BC8:BD8) -> 0 | BF8: =BB8+BE8 -> 16
A9: УК-2.2 | B9: =VLOOKUP(A9,Лист1!B:C,2,0) -> Формулирует проектную задачу, определяет способы ее решения средствами проектного управления | C9: =IFERROR(SEARCH($A9,C$3),"") | D9: =IFERROR(SEARCH($A9,D$3),"") | E9: =IFERROR(SEARCH($A9,E$3),"") | F9: =IFERROR(SEARCH($A9,F$3),"") | G9: =IFERROR(SEARCH($A9,G$3),"") | H9: =IFERROR(SEARCH($A9,H$3),"") | I9: =IFERROR(SEARCH($A9,I$3),"") | J9: =IFERROR(SEARCH($A9,J$3),"") | ... U9: =IFERROR(SEARCH($A9,U$3),"") | V9: 2 | W9: =IFERROR(SEARCH($A9,W$3),"") | X9: =IFERROR(SEARCH($A9,X$3),"") | Y9: =IFERROR(SEARCH($A9,Y$3),"") | Z9: =IFERROR(SEARCH($A9,Z$3),"") | AA9: =IFERROR(SEARCH($A9,AA$3),"") | AB9: =IFERROR(SEARCH($A9,AB$3),"") | AC9: =IFERROR(SEARCH($A9,AC$3),"") | AD9: =IFERROR(SEARCH($A9,AD$3),"") | ... BA9: =IFERROR(SEARCH($A9,BA$3),"") | BB9: =SUM(C9:BA9) -> 2 | BC9: =IFERROR(SEARCH($A9,BC$3),"") | BD9: 18 | BE9: =SUM(BC9:BD9) -> 18 | BF9: =BB9+BE9 -> 20
A10: УК-3 | B10: =VLOOKUP(A10,Лист1!B:C,2,0) -> Способен осуществлять социальное взаимодействие и реализовывать свою роль в команде | C10: =IFERROR(IF(SEARCH($A10,C$3)<>0,1,""),"") | D10: =IFERROR(IF(SEARCH($A10,D$3)<>0,1,""),"") | E10: =IFERROR(IF(SEARCH($A10,E$3)<>0,1,""),"") | F10: =IFERROR(IF(SEARCH($A10,F$3)<>0,1,""),"") | G10: =IFERROR(IF(SEARCH($A10,G$3)<>0,1,""),"") | H10: =IFERROR(IF(SEARCH($A10,H$3)<>0,1,""),"") | I10: =IFERROR(IF(SEARCH($A10,I$3)<>0,1,""),"") | J10: =IFERROR(IF(SEARCH($A10,J$3)<>0,1,""),"") | ... U10: =IFERROR(IF(SEARCH($A10,U$3)<>0,1,""),"") | V10: 18 | W10: =IFERROR(IF(SEARCH($A10,W$3)<>0,1,""),"") | X10: =IFERROR(IF(SEARCH($A10,X$3)<>0,1,""),"") | Y10: =IFERROR(IF(SEARCH($A10,Y$3)<>0,1,""),"") | Z10: =IFERROR(IF(SEARCH($A10,Z$3)<>0,1,""),"") | AA10: =IFERROR(IF(SEARCH($A10,AA$3)<>0,1,""),"") | AB10: =IFERROR(IF(SEARCH($A10,AB$3)<>0,1,""),"") | AC10: =IFERROR(IF(SEARCH($A10,AC$3)<>0,1,""),"") | AD10: =IFERROR(IF(SEARCH($A10,AD$3)<>0,1,""),"") | ... BA10: =IFERROR(IF(SEARCH($A10,BA$3)<>0,1,""),"") | BB10: =SUM(C10:BA10) -> 18 | BC10: =IFERROR(SEARCH(_xlfn.CONCAT(" ",$A10),#REF!),"") | BD10: =IFERROR(SEARCH(_xlfn.CONCAT(" ",$A10),#REF!),"") | BE10: =SUM(BC10:BD10) -> 0 | BF10: =BB10+BE10 -> 18
A11: УК-3.1 | B11: =VLOOKUP(A11,Лист1!B:C,2,0) -> Организует и координирует работу команды с учетом интересов, особенностей поведения и мнения её членов | C11: =IFERROR(SEARCH($A11,C$3),"") | D11: =IFERROR(SEARCH($A11,D$3),"") | E11: =IFERROR(SEARCH($A11,E$3),"") | F11: =IFERROR(SEARCH($A11,F$3),"") | G11: =IFERROR(SEARCH($A11,G$3),"") | H11: =IFERROR(SEARCH($A11,H$3),"") | I11: =IFERROR(SEARCH($A11,I$3),"") | J11: =IFERROR(SEARCH($A11,J$3),"") | ... BA11: =IFERROR(SEARCH($A11,BA$3),"") | BB11: =SUM(C11:BA11) -> 9 | BC11: =IFERROR(SEARCH($A11,BC$3),"") | BD11: =IFERROR(SEARCH($A11,BD$3),"") | BE11: =SUM(BC11:BD11) -> 0 | BF11: =BB11+BE11 -> 9
A12: УК-3.2 | B12: =VLOOKUP(A12,Лист1!B:C,2,0) -> Вырабатывает командную стратегию для достижения поставленной цели | C12: =IFERROR(SEARCH($A12,C$3),"") | D12: =IFERROR(SEARCH($A12,D$3),"") | E12: =IFERROR(SEARCH($A12,E$3),"") | F12: =IFERROR(SEARCH($A12,F$3),"") | G12: =IFERROR(SEARCH($A12,G$3),"") | H12: =IFERROR(SEARCH($A12,H$3),"") | I12: =IFERROR(SEARCH($A12,I$3),"") | J12: =IFERROR(SEARCH($A12,J$3),"") | ... U12: =IFERROR(SEARCH($A12,U$3),"") | V12: 9 | W12: =IFERROR(SEARCH($A12,W$3),"") | X12: =IFERROR(SEARCH($A12,X$3),"") | Y12: =IFERROR(SEARCH($A12,Y$3),"") | Z12: =IFERROR(SEARCH($A12,Z$3),"") | AA12: =IFERROR(SEARCH($A12,AA$3),"") | AB12: =IFERROR(SEARCH($A12,AB$3),"") | AC12: =IFERROR(SEARCH($A12,AC$3),"") | AD12: =IFERROR(SEARCH($A12,AD$3),"") | ... BA12: =IFERROR(SEARCH($A12,BA$3),"") | BB12: =SUM(C12:BA12) -> 9 | BC12: =IFERROR(SEARCH($A12,BC$3),"") | BD12: =IFERROR(SEARCH($A12,BD$3),"") | BE12: =SUM(BC12:BD12) -> 0 | BF12: =BB12+BE12 -> 9
A13: УК-4 | B13: =VLOOKUP(A13,Лист1!B:C,2,0) -> Способен осуществлять деловую коммуникацию в устной и письменной формах на государственном языке Российской Федерации и иностранном(ых) языке(ах) | C13: =IFERROR(IF(SEARCH($A13,C$3)<>0,1,""),"") | D13: =IFERROR(IF(SEARCH($A13,D$3)<>0,1,""),"") | E13: 18 | F13: =IFERROR(IF(SEARCH($A13,F$3)<>0,1,""),"") | G13: =IFERROR(IF(SEARCH($A13,G$3)<>0,1,""),"") | H13: =IFERROR(IF(SEARCH($A13,H$3)<>0,1,""),"") | I13: =IFERROR(IF(SEARCH($A13,I$3)<>0,1,""),"") | J13: =IFERROR(IF(SEARCH($A13,J$3)<>0,1,""),"") | K13: =IFERROR(IF(SEARCH($A13,K$3)<>0,1,""),"") | L13: =IFERROR(IF(SEARCH($A13,L$3)<>0,1,""),"") | M13: =IFERROR(IF(SEARCH($A13,M$3)<>0,1,""),"") | N13: =IFERROR(IF(SEARCH($A13,N$3)<>0,1,""),"") | O13: 18 | P13: =IFERROR(IF(SEARCH($A13,P$3)<>0,1,""),"") | Q13: =IFERROR(IF(SEARCH($A13,Q$3)<>0,1,""),"") | R13: =IFERROR(IF(SEARCH($A13,R$3)<>0,1,""),"") | S13: =IFERROR(IF(SEARCH($A13,S$3)<>0,1,""),"") | T13: =IFERROR(IF(SEARCH($A13,T$3)<>0,1,""),"") | U13: =IFERROR(IF(SEARCH($A13,U$3)<>0,1,""),"") | V13: =IFERROR(IF(SEARCH($A13,V$3)<>0,1,""),"") | W13: =IFERROR(IF(SEARCH($A13,W$3)<>0,1,""),"") | ... BA13: =IFERROR(IF(SEARCH($A13,BA$3)<>0,1,""),"") | BB13: =SUM(C13:BA13) -> 36 | BE13: =SUM(BC13:BD13) -> 0 | BF13: =BB13+BE13 -> 36
A14: УК-4.1 | B14: =VLOOKUP(A14,Лист1!B:C,2,0) -> Отбирает и использует средства русского языка в соответствии с языковыми нормами в целях построения эффективной академической и профессиональной коммуникации | C14: =IFERROR(SEARCH($A14,C$3),"") | D14: =IFERROR(SEARCH($A14,D$3),"") | E14: =IFERROR(SEARCH($A14,E$3),"") | F14: =IFERROR(SEARCH($A14,F$3),"") | G14: =IFERROR(SEARCH($A14,G$3),"") | H14: =IFERROR(SEARCH($A14,H$3),"") | I14: =IFERROR(SEARCH($A14,I$3),"") | J14: =IFERROR(SEARCH($A14,J$3),"") | ... N14: =IFERROR(SEARCH($A14,N$3),"") | O14: 9 | P14: =IFERROR(SEARCH($A14,P$3),"") | Q14: =IFERROR(SEARCH($A14,Q$3),"") | R14: =IFERROR(SEARCH($A14,R$3),"") | S14: =IFERROR(SEARCH($A14,S$3),"") | T14: =IFERROR(SEARCH($A14,T$3),"") | U14: =IFERROR(SEARCH($A14,U$3),"") | V14: =IFERROR(SEARCH($A14,V$3),"") | W14: =IFERROR(SEARCH($A14,W$3),"") | ... BA14: =IFERROR(SEARCH($A14,BA$3),"") | BB14: =SUM(C14:BA14) -> 9 | BC14: =IFERROR(SEARCH($A14,BC$3),"") | BD14: =IFERROR(SEARCH($A14,BD$3),"") | BE14: =SUM(BC14:BD14) -> 0 | BF14: =BB14+BE14 -> 9
A15: УК-4.2 | B15: =VLOOKUP(A15,Лист1!B:C,2,0) -> Осуществляет академическое и деловое взаимодействие в различных жанрах и формах с использованием современных коммуникативных технологий | C15: =IFERROR(SEARCH($A15,C$3),"") | D15: =IFERROR(SEARCH($A15,D$3),"") | E15: =IFERROR(SEARCH($A15,E$3),"") | F15: =IFERROR(SEARCH($A15,F$3),"") | G15: =IFERROR(SEARCH($A15,G$3),"") | H15: =IFERROR(SEARCH($A15,H$3),"") | I15: =IFERROR(SEARCH($A15,I$3),"") | J15: =IFERROR(SEARCH($A15,J$3),"") | ... BA15: =IFERROR(SEARCH($A15,BA$3),"") | BB15: =SUM(C15:BA15) -> 9 | BC15: =IFERROR(SEARCH($A15,BC$3),"") | BD15: =IFERROR(SEARCH($A15,BD$3),"") | BE15: =SUM(BC15:BD15) -> 0 | BF15: =BB15+BE15 -> 9
A16: УК-4.3 | B16: =VLOOKUP(A16,Лист1!B:C,2,0) -> Применяет современные коммуникативные технологии для академического взаимодействия на иностранном(ых) языке(ах) | C16: =IFERROR(SEARCH($A16,C$3),"") | D16: =IFERROR(SEARCH($A16,D$3),"") | E16: 9 | F16: =IFERROR(SEARCH($A16,F$3),"") | G16: =IFERROR(SEARCH($A16,G$3),"") | H16: =IFERROR(SEARCH($A16,H$3),"") | I16: =IFERROR(SEARCH($A16,I$3),"") | J16: =IFERROR(SEARCH($A16,J$3),"") | K16: =IFERROR(SEARCH($A16,K$3),"") | L16: =IFERROR(SEARCH($A16,L$3),"") | M16: =IFERROR(SEARCH($A16,M$3),"") | ... BA16: =IFERROR(SEARCH($A16,BA$3),"") | BB16: =SUM(C16:BA16) -> 9 | BC16: =IFERROR(SEARCH($A16,BC$3),"") | BD16: =IFERROR(SEARCH($A16,BD$3),"") | BE16: =SUM(BC16:BD16) -> 0 | BF16: =BB16+BE16 -> 9
A17: УК-4.4 | B17: =VLOOKUP(A17,Лист1!B:C,2,0) -> Применяет современные коммуникативные технологии для профессионального взаимодействия на иностранном(ых) языке(ах) | C17: =IFERROR(SEARCH($A17,C$3),"") | D17: =IFERROR(SEARCH($A17,D$3),"") | E17: 9 | F17: =IFERROR(SEARCH($A17,F$3),"") | G17: =IFERROR(SEARCH($A17,G$3),"") | H17: =IFERROR(SEARCH($A17,H$3),"") | I17: =IFERROR(SEARCH($A17,I$3),"") | J17: =IFERROR(SEARCH($A17,J$3),"") | K17: =IFERROR(SEARCH($A17,K$3),"") | L17: =IFERROR(SEARCH($A17,L$3),"") | M17: =IFERROR(SEARCH($A17,M$3),"") | ... BA17: =IFERROR(SEARCH($A17,BA$3),"") | BB17: =SUM(C17:BA17) -> 9 | BC17: =IFERROR(SEARCH($A17,BC$3),"") | BD17: =IFERROR(SEARCH($A17,BD$3),"") | BE17: =SUM(BC17:BD17) -> 0 | BF17: =BB17+BE17 -> 9
A18: УК-5 | B18: =VLOOKUP(A18,Лист1!B:C,2,0) -> Способен воспринимать межкультурное разнообразие общества в социально-историческом, этическом и философском контекстах | C18: =IFERROR(IF(SEARCH($A18,C$3)<>0,1,""),"") | D18: 18 | E18: =IFERROR(IF(SEARCH($A18,E$3)<>0,1,""),"") | F18: =IFERROR(IF(SEARCH($A18,F$3)<>0,1,""),"") | G18: =IFERROR(IF(SEARCH($A18,G$3)<>0,1,""),"") | H18: =IFERROR(IF(SEARCH($A18,H$3)<>0,1,""),"") | I18: =IFERROR(IF(SEARCH($A18,I$3)<>0,1,""),"") | J18: 18 | K18: =IFERROR(IF(SEARCH($A18,K$3)<>0,1,""),"") | L18: =IFERROR(IF(SEARCH($A18,L$3)<>0,1,""),"") | M18: =IFERROR(IF(SEARCH($A18,M$3)<>0,1,""),"") | N18: =IFERROR(IF(SEARCH($A18,N$3)<>0,1,""),"") | O18: =IFERROR(IF(SEARCH($A18,O$3)<>0,1,""),"") | P18: =IFERROR(IF(SEARCH($A18,P$3)<>0,1,""),"") | Q18: =IFERROR(IF(SEARCH($A18,Q$3)<>0,1,""),"") | R18: =IFERROR(IF(SEARCH($A18,R$3)<>0,1,""),"") | ... AB18: =IFERROR(IF(SEARCH($A18,AB$3)<>0,1,""),"") | AC18: 4 | AD18: =IFERROR(IF(SEARCH($A18,AD$3)<>0,1,""),"") | AE18: =IFERROR(IF(SEARCH($A18,AE$3)<>0,1,""),"") | AF18: =IFERROR(IF(SEARCH($A18,AF$3)<>0,1,""),"") | AG18: =IFERROR(IF(SEARCH($A18,AG$3)<>0,1,""),"") | AH18: =IFERROR(IF(SEARCH($A18,AH$3)<>0,1,""),"") | AI18: =IFERROR(IF(SEARCH($A18,AI$3)<>0,1,""),"") | AJ18: =IFERROR(IF(SEARCH($A18,AJ$3)<>0,1,""),"") | AK18: =IFERROR(IF(SEARCH($A18,AK$3)<>0,1,""),"") | ... BA18: =IFERROR(IF(SEARCH($A18,BA$3)<>0,1,""),"") | BB18: =SUM(C18:BA18) -> 40 | BC18: 18 | BD18: =IFERROR(SEARCH(_xlfn.CONCAT(" ",$A18),#REF!),"") | BE18: =SUM(BC18:BD18) -> 18 | BF18: =BB18+BE18 -> 58
A19: УК-5.1 | B19: =VLOOKUP(A19,Лист1!B:C,2,0) -> Анализирует идеологические и ценностные системы в контексте исторического развития общества, обосновывает актуальность их использования при социальном и профессиональном взаимодействии | C19: =IFERROR(SEARCH($A19,C$3),"") | D19: 9 | E19: =IFERROR(SEARCH($A19,E$3),"") | F19: =IFERROR(SEARCH($A19,F$3),"") | G19: =IFERROR(SEARCH($A19,G$3),"") | H19: =IFERROR(SEARCH($A19,H$3),"") | I19: =IFERROR(SEARCH($A19,I$3),"") | J19: =IFERROR(SEARCH($A19,J$3),"") | K19: =IFERROR(SEARCH($A19,K$3),"") | L19: =IFERROR(SEARCH($A19,L$3),"") | ... AB19: =IFERROR(SEARCH($A19,AB$3),"") | AC19: 2 | AD19: =IFERROR(SEARCH($A19,AD$3),"") | AE19: =IFERROR(SEARCH($A19,AE$3),"") | AF19: =IFERROR(SEARCH($A19,AF$3),"") | AG19: =IFERROR(SEARCH($A19,AG$3),"") | AH19: =IFERROR(SEARCH($A19,AH$3),"") | AI19: =IFERROR(SEARCH($A19,AI$3),"") | AJ19: =IFERROR(SEARCH($A19,AJ$3),"") | AK19: =IFERROR(SEARCH($A19,AK$3),"") | ... BA19: =IFERROR(SEARCH($A19,BA$3),"") | BB19: =SUM(C19:BA19) -> 11 | BC19: =IFERROR(SEARCH($A19,BC$3),"") | BD19: =IFERROR(SEARCH($A19,BD$3),"") | BE19: =SUM(BC19:BD19) -> 0 | BF19: =BB19+BE19 -> 11
A20: УК-5.2 | B20: =VLOOKUP(A20,Лист1!B:C,2,0) -> Выявляет современные тенденции исторического развития России с учетом геополитической обстановки | C20: =IFERROR(SEARCH($A20,C$3),"") | D20: =IFERROR(SEARCH($A20,D$3),"") -> 9 | E20: =IFERROR(SEARCH($A20,E$3),"") | F20: =IFERROR(SEARCH($A20,F$3),"") | G20: =IFERROR(SEARCH($A20,G$3),"") | H20: =IFERROR(SEARCH($A20,H$3),"") | I20: =IFERROR(SEARCH($A20,I$3),"") | J20: =IFERROR(SEARCH($A20,J$3),"") | ... AB20: =IFERROR(SEARCH($A20,AB$3),"") | AC20: 2 | AD20: =IFERROR(SEARCH($A20,AD$3),"") | AE20: =IFERROR(SEARCH($A20,AE$3),"") | AF20: =IFERROR(SEARCH($A20,AF$3),"") | AG20: =IFERROR(SEARCH($A20,AG$3),"") | AH20: =IFERROR(SEARCH($A20,AH$3),"") | AI20: =IFERROR(SEARCH($A20,AI$3),"") | AJ20: =IFERROR(SEARCH($A20,AJ$3),"") | AK20: =IFERROR(SEARCH($A20,AK$3),"") | ... BA20: =IFERROR(SEARCH($A20,BA$3),"") | BB20: =SUM(C20:BA20) -> 11 | BC20: =IFERROR(SEARCH($A20,BC$3),"") | BD20: =IFERROR(SEARCH($A20,BD$3),"") | BE20: =SUM(BC20:BD20) -> 0 | BF20: =BB20+BE20 -> 11
A21: УК-5.3 | B21: =VLOOKUP(A21,Лист1!B:C,2,0) -> Выстраивает социальное и профессиональное взаимодействие с учетом особенностей основных форм научного и религиозного сознания, деловой и общей культуры представителей различных социальных групп, этносов и конфессий | C21: =IFERROR(SEARCH($A21,C$3),"") | D21: =IFERROR(SEARCH($A21,D$3),"") | E21: =IFERROR(SEARCH($A21,E$3),"") | F21: =IFERROR(SEARCH($A21,F$3),"") | G21: =IFERROR(SEARCH($A21,G$3),"") | H21: =IFERROR(SEARCH($A21,H$3),"") | I21: =IFERROR(SEARCH($A21,I$3),"") | J21: 18 | K21: =IFERROR(SEARCH($A21,K$3),"") | L21: =IFERROR(SEARCH($A21,L$3),"") | M21: =IFERROR(SEARCH($A21,M$3),"") | N21: =IFERROR(SEARCH($A21,N$3),"") | O21: =IFERROR(SEARCH($A21,O$3),"") | P21: =IFERROR(SEARCH($A21,P$3),"") | Q21: =IFERROR(SEARCH($A21,Q$3),"") | R21: =IFERROR(SEARCH($A21,R$3),"") | ... BA21: =IFERROR(SEARCH($A21,BA$3),"") | BB21: =SUM(C21:BA21) -> 18 | BC21: 18 | BD21: =IFERROR(SEARCH($A21,BD$3),"") | BE21: =SUM(BC21:BD21) -> 18 | BF21: =BB21+BE21 -> 36
A22: УК-6 | B22: =VLOOKUP(A22,Лист1!B:C,2,0) -> Способен управлять своим временем, выстраивать и реализовывать траекторию саморазвития на основе принципов образования в течение всей жизни | C22: =IFERROR(IF(SEARCH($A22,C$3)<>0,1,""),"") | D22: =IFERROR(IF(SEARCH($A22,D$3)<>0,1,""),"") | E22: =IFERROR(IF(SEARCH($A22,E$3)<>0,1,""),"") | F22: =IFERROR(IF(SEARCH($A22,F$3)<>0,1,""),"") | G22: =IFERROR(IF(SEARCH($A22,G$3)<>0,1,""),"") | H22: =IFERROR(IF(SEARCH($A22,H$3)<>0,1,""),"") | I22: =IFERROR(IF(SEARCH($A22,I$3)<>0,1,""),"") | J22: =IFERROR(IF(SEARCH($A22,J$3)<>0,1,""),"") | K22: 18 | L22: =IFERROR(IF(SEARCH($A22,L$3)<>0,1,""),"") | M22: =IFERROR(IF(SEARCH($A22,M$3)<>0,1,""),"") | N22: =IFERROR(IF(SEARCH($A22,N$3)<>0,1,""),"") | O22: =IFERROR(IF(SEARCH($A22,O$3)<>0,1,""),"") | P22: =IFERROR(IF(SEARCH($A22,P$3)<>0,1,""),"") | Q22: =IFERROR(IF(SEARCH($A22,Q$3)<>0,1,""),"") | R22: =IFERROR(IF(SEARCH($A22,R$3)<>0,1,""),"") | S22: =IFERROR(IF(SEARCH($A22,S$3)<>0,1,""),"") | ... BA22: =IFERROR(IF(SEARCH($A22,BA$3)<>0,1,""),"") | BB22: =SUM(C22:BA22) -> 18 | BC22: =IFERROR(SEARCH(_xlfn.CONCAT(" ",$A22),#REF!),"") | BD22: =IFERROR(SEARCH(_xlfn.CONCAT(" ",$A22),#REF!),"") | BE22: =SUM(BC22:BD22) -> 0 | BF22: =BB22+BE22 -> 18
A23: УК-6.1 | B23: =VLOOKUP(A23,Лист1!B:C,2,0) -> Определяет цели и задачи саморазвития и профессионального роста на основе оценки временных и личностных ресурсов | C23: =IFERROR(SEARCH($A23,C$3),"") | D23: =IFERROR(SEARCH($A23,D$3),"") | E23: =IFERROR(SEARCH($A23,E$3),"") | F23: =IFERROR(SEARCH($A23,F$3),"") | G23: =IFERROR(SEARCH($A23,G$3),"") | H23: =IFERROR(SEARCH($A23,H$3),"") | I23: =IFERROR(SEARCH($A23,I$3),"") | J23: =IFERROR(SEARCH($A23,J$3),"") | K23: 9 | L23: =IFERROR(SEARCH($A23,L$3),"") | M23: =IFERROR(SEARCH($A23,M$3),"") | N23: =IFERROR(SEARCH($A23,N$3),"") | O23: =IFERROR(SEARCH($A23,O$3),"") | P23: =IFERROR(SEARCH($A23,P$3),"") | Q23: =IFERROR(SEARCH($A23,Q$3),"") | R23: =IFERROR(SEARCH($A23,R$3),"") | S23: =IFERROR(SEARCH($A23,S$3),"") | ... BA23: =IFERROR(SEARCH($A23,BA$3),"") | BB23: =SUM(C23:BA23) -> 9 | BC23: =IFERROR(SEARCH($A23,BC$3),"") | BD23: =IFERROR(SEARCH($A23,BD$3),"") | BE23: =SUM(BC23:BD23) -> 0 | BF23: =BB23+BE23 -> 9
A24: УК-6.2 | B24: =VLOOKUP(A24,Лист1!B:C,2,0) -> Использует основные возможности и инструменты непрерывного образования (образования в течение всей жизни) для реализации траектории саморазвития | C24: =IFERROR(SEARCH($A24,C$3),"") | D24: =IFERROR(SEARCH($A24,D$3),"") | E24: =IFERROR(SEARCH($A24,E$3),"") | F24: =IFERROR(SEARCH($A24,F$3),"") | G24: =IFERROR(SEARCH($A24,G$3),"") | H24: =IFERROR(SEARCH($A24,H$3),"") | I24: =IFERROR(SEARCH($A24,I$3),"") | J24: =IFERROR(SEARCH($A24,J$3),"") | ... BA24: =IFERROR(SEARCH($A24,BA$3),"") | BB24: =SUM(C24:BA24) -> 9 | BC24: =IFERROR(SEARCH($A24,BC$3),"") | BD24: =IFERROR(SEARCH($A24,BD$3),"") | BE24: =SUM(BC24:BD24) -> 0 | BF24: =BB24+BE24 -> 9
A25: УК-7 | B25: =VLOOKUP(A25,Лист1!B:C,2,0) -> Способен поддерживать должный уровень физической подготовленности для обеспечения полноценной социальной и профессиональной деятельности | C25: =IFERROR(IF(SEARCH($A25,C$3)<>0,1,""),"") | D25: =IFERROR(IF(SEARCH($A25,D$3)<>0,1,""),"") | E25: =IFERROR(IF(SEARCH($A25,E$3)<>0,1,""),"") | F25: =IFERROR(IF(SEARCH($A25,F$3)<>0,1,""),"") | G25: 18 | H25: =IFERROR(IF(SEARCH($A25,H$3)<>0,1,""),"") | I25: =IFERROR(IF(SEARCH($A25,I$3)<>0,1,""),"") | J25: =IFERROR(IF(SEARCH($A25,J$3)<>0,1,""),"") | K25: =IFERROR(IF(SEARCH($A25,K$3)<>0,1,""),"") | L25: =IFERROR(IF(SEARCH($A25,L$3)<>0,1,""),"") | M25: =IFERROR(IF(SEARCH($A25,M$3)<>0,1,""),"") | N25: =IFERROR(IF(SEARCH($A25,N$3)<>0,1,""),"") | O25: =IFERROR(IF(SEARCH($A25,O$3)<>0,1,""),"") | ... AC25: =IFERROR(IF(SEARCH($A25,AC$3)<>0,1,""),"") | AD25: 18 | AE25: =IFERROR(IF(SEARCH($A25,AE$3)<>0,1,""),"") | AF25: =IFERROR(IF(SEARCH($A25,AF$3)<>0,1,""),"") | AG25: =IFERROR(IF(SEARCH($A25,AG$3)<>0,1,""),"") | AH25: =IFERROR(IF(SEARCH($A25,AH$3)<>0,1,""),"") | AI25: =IFERROR(IF(SEARCH($A25,AI$3)<>0,1,""),"") | AJ25: =IFERROR(IF(SEARCH($A25,AJ$3)<>0,1,""),"") | AK25: =IFERROR(IF(SEARCH($A25,AK$3)<>0,1,""),"") | AL25: =IFERROR(IF(SEARCH($A25,AL$3)<>0,1,""),"") | ... BA25: =IFERROR(IF(SEARCH($A25,BA$3)<>0,1,""),"") | BB25: =SUM(C25:BA25) -> 36 | BE25: =SUM(BC25:BD25) -> 0 | BF25: =BB25+BE25 -> 36
A26: УК-7.1 | B26: =VLOOKUP(A26,Лист1!B:C,2,0) -> Идентифицирует и анализирует социально-биологические и методические основы физического воспитания, здорового образа жизни, профессионально-прикладной физической подготовки | C26: =IFERROR(SEARCH($A26,C$3),"") | D26: =IFERROR(SEARCH($A26,D$3),"") | E26: =IFERROR(SEARCH($A26,E$3),"") | F26: =IFERROR(SEARCH($A26,F$3),"") | G26: 9 | H26: =IFERROR(SEARCH($A26,H$3),"") | I26: =IFERROR(SEARCH($A26,I$3),"") | J26: =IFERROR(SEARCH($A26,J$3),"") | K26: =IFERROR(SEARCH($A26,K$3),"") | L26: =IFERROR(SEARCH($A26,L$3),"") | M26: =IFERROR(SEARCH($A26,M$3),"") | N26: =IFERROR(SEARCH($A26,N$3),"") | O26: =IFERROR(SEARCH($A26,O$3),"") | ... BA26: =IFERROR(SEARCH($A26,BA$3),"") | BB26: =SUM(C26:BA26) -> 9 | BC26: =IFERROR(SEARCH($A26,BC$3),"") | BD26: =IFERROR(SEARCH($A26,BD$3),"") | BE26: =SUM(BC26:BD26) -> 0 | BF26: =BB26+BE26 -> 9
A27: УК-7.2 | B27: =VLOOKUP(A27,Лист1!B:C,2,0) -> Выбирает способы оценки и контроля уровня физического развития, физической и профессионально-прикладной подготовленности, показателей работоспособности и здоровья, с учетом физиологических особенностей организма | C27: =IFERROR(SEARCH($A27,C$3),"") | D27: =IFERROR(SEARCH($A27,D$3),"") | E27: =IFERROR(SEARCH($A27,E$3),"") | F27: =IFERROR(SEARCH($A27,F$3),"") | G27: =IFERROR(SEARCH($A27,G$3),"") -> 9 | H27: =IFERROR(SEARCH($A27,H$3),"") | I27: =IFERROR(SEARCH($A27,I$3),"") | J27: =IFERROR(SEARCH($A27,J$3),"") | ... BA27: =IFERROR(SEARCH($A27,BA$3),"") | BB27: =SUM(C27:BA27) -> 9 | BC27: =IFERROR(SEARCH($A27,BC$3),"") | BD27: =IFERROR(SEARCH($A27,BD$3),"") | BE27: =SUM(BC27:BD27) -> 0 | BF27: =BB27+BE27 -> 9
A28: УК-7.3 | B28: =VLOOKUP(A28,Лист1!B:C,2,0) -> Соблюдает нормы здорового образа жизни, поддерживает должный уровень физической подготовленности для обеспечения полноценной социальной и профессиональной деятельности | C28: =IFERROR(SEARCH($A28,C$3),"") | D28: =IFERROR(SEARCH($A28,D$3),"") | E28: =IFERROR(SEARCH($A28,E$3),"") | F28: =IFERROR(SEARCH($A28,F$3),"") | G28: =IFERROR(SEARCH($A28,G$3),"") | H28: =IFERROR(SEARCH($A28,H$3),"") | I28: =IFERROR(SEARCH($A28,I$3),"") | J28: =IFERROR(SEARCH($A28,J$3),"") | ... AC28: =IFERROR(SEARCH($A28,AC$3),"") | AD28: 18 | AE28: =IFERROR(SEARCH($A28,AE$3),"") | AF28: =IFERROR(SEARCH($A28,AF$3),"") | AG28: =IFERROR(SEARCH($A28,AG$3),"") | AH28: =IFERROR(SEARCH($A28,AH$3),"") | AI28: =IFERROR(SEARCH($A28,AI$3),"") | AJ28: =IFERROR(SEARCH($A28,AJ$3),"") | AK28: =IFERROR(SEARCH($A28,AK$3),"") | AL28: =IFERROR(SEARCH($A28,AL$3),"") | ... BA28: =IFERROR(SEARCH($A28,BA$3),"") | BB28: =SUM(C28:BA28) -> 18 | BC28: =IFERROR(SEARCH($A28,BC$3),"") | BD28: =IFERROR(SEARCH($A28,BD$3),"") | BE28: =SUM(BC28:BD28) -> 0 | BF28: =BB28+BE28 -> 18
A29: УК-8 | B29: =VLOOKUP(A29,Лист1!B:C,2,0) -> Способен создавать и поддерживать в повседневной жизни и в профессиональной деятельности безопасные условия жизнедеятельности для сохранения природной среды, обеспечения устойчивого развития общества, в том числе при угрозе и возникновении чрезвычайных ситуаций и военных конфликтов | C29: =IFERROR(IF(SEARCH($A29,C$3)<>0,1,""),"") | D29: =IFERROR(IF(SEARCH($A29,D$3)<>0,1,""),"") | E29: =IFERROR(IF(SEARCH($A29,E$3)<>0,1,""),"") | F29: 18 | G29: =IFERROR(IF(SEARCH($A29,G$3)<>0,1,""),"") | H29: =IFERROR(IF(SEARCH($A29,H$3)<>0,1,""),"") | I29: =IFERROR(IF(SEARCH($A29,I$3)<>0,1,""),"") | J29: =IFERROR(IF(SEARCH($A29,J$3)<>0,1,""),"") | K29: =IFERROR(IF(SEARCH($A29,K$3)<>0,1,""),"") | L29: =IFERROR(IF(SEARCH($A29,L$3)<>0,1,""),"") | M29: =IFERROR(IF(SEARCH($A29,M$3)<>0,1,""),"") | N29: =IFERROR(IF(SEARCH($A29,N$3)<>0,1,""),"") | ... BA29: =IFERROR(IF(SEARCH($A29,BA$3)<>0,1,""),"") | BB29: =SUM(C29:BA29) -> 18 | BC29: =IFERROR(SEARCH(_xlfn.CONCAT(" ",$A29),#REF!),"") | BD29: =IFERROR(SEARCH(_xlfn.CONCAT(" ",$A29),#REF!),"") | BE29: =SUM(BC29:BD29) -> 0 | BF29: =BB29+BE29 -> 18
A30: УК-8.1 | B30: =VLOOKUP(A30,Лист1!B:C,2,0) -> Идентифицирует и анализирует факторы вредного влияния элементов среды обитания (технических средств, технологических процессов, материалов, зданий и сооружений, природных и социальных явлений) | C30: =IFERROR(SEARCH($A30,C$3),"") | D30: =IFERROR(SEARCH($A30,D$3),"") | E30: =IFERROR(SEARCH($A30,E$3),"") | F30: 6 | G30: =IFERROR(SEARCH($A30,G$3),"") | H30: =IFERROR(SEARCH($A30,H$3),"") | I30: =IFERROR(SEARCH($A30,I$3),"") | J30: =IFERROR(SEARCH($A30,J$3),"") | K30: =IFERROR(SEARCH($A30,K$3),"") | L30: =IFERROR(SEARCH($A30,L$3),"") | M30: =IFERROR(SEARCH($A30,M$3),"") | N30: =IFERROR(SEARCH($A30,N$3),"") | ... BA30: =IFERROR(SEARCH($A30,BA$3),"") | BB30: =SUM(C30:BA30) -> 6 | BC30: =IFERROR(SEARCH($A30,BC$3),"") | BD30: =IFERROR(SEARCH($A30,BD$3),"") | BE30: =SUM(BC30:BD30) -> 0 | BF30: =BB30+BE30 -> 6
A31: УК-8.2 | B31: =VLOOKUP(A31,Лист1!B:C,2,0) -> Определяет алгоритм действий по обеспечению безопасных условий жизнедеятельности при угрозе и возникновении чрезвычайных ситуаций и военных конфликтов | C31: =IFERROR(SEARCH($A31,C$3),"") | D31: =IFERROR(SEARCH($A31,D$3),"") | E31: =IFERROR(SEARCH($A31,E$3),"") | F31: 6 | G31: =IFERROR(SEARCH($A31,G$3),"") | H31: =IFERROR(SEARCH($A31,H$3),"") | I31: =IFERROR(SEARCH($A31,I$3),"") | J31: =IFERROR(SEARCH($A31,J$3),"") | K31: =IFERROR(SEARCH($A31,K$3),"") | L31: =IFERROR(SEARCH($A31,L$3),"") | M31: =IFERROR(SEARCH($A31,M$3),"") | N31: =IFERROR(SEARCH($A31,N$3),"") | ... BA31: =IFERROR(SEARCH($A31,BA$3),"") | BB31: =SUM(C31:BA31) -> 6 | BC31: =IFERROR(SEARCH($A31,BC$3),"") | BD31: =IFERROR(SEARCH($A31,BD$3),"") | BE31: =SUM(BC31:BD31) -> 0 | BF31: =BB31+BE31 -> 6
A32: УК-8.3 | B32: =VLOOKUP(A32,Лист1!B:C,2,0) -> Планирует мероприятия по организации безопасных условий труда на предприятии | C32: =IFERROR(SEARCH($A32,C$3),"") | D32: =IFERROR(SEARCH($A32,D$3),"") | E32: =IFERROR(SEARCH($A32,E$3),"") | F32: 6 | G32: =IFERROR(SEARCH($A32,G$3),"") | H32: =IFERROR(SEARCH($A32,H$3),"") | I32: =IFERROR(SEARCH($A32,I$3),"") | J32: =IFERROR(SEARCH($A32,J$3),"") | K32: =IFERROR(SEARCH($A32,K$3),"") | L32: =IFERROR(SEARCH($A32,L$3),"") | M32: =IFERROR(SEARCH($A32,M$3),"") | N32: =IFERROR(SEARCH($A32,N$3),"") | ... BA32: =IFERROR(SEARCH($A32,BA$3),"") | BB32: =SUM(C32:BA32) -> 6 | BC32: =IFERROR(SEARCH($A32,BC$3),"") | BD32: =IFERROR(SEARCH($A32,BD$3),"") | BE32: =SUM(BC32:BD32) -> 0 | BF32: =BB32+BE32 -> 6
A33: УК-9 | B33: =VLOOKUP(A33,Лист1!B:C,2,0) -> Способен использовать базовые дефектологические знания в социальной и профессиональной сферах | C33: =IFERROR(IF(SEARCH($A33,C$3)<>0,1,""),"") | D33: =IFERROR(IF(SEARCH($A33,D$3)<>0,1,""),"") | E33: =IFERROR(IF(SEARCH($A33,E$3)<>0,1,""),"") | F33: =IFERROR(IF(SEARCH($A33,F$3)<>0,1,""),"") | G33: =IFERROR(IF(SEARCH($A33,G$3)<>0,1,""),"") | H33: =IFERROR(IF(SEARCH($A33,H$3)<>0,1,""),"") | I33: =IFERROR(IF(SEARCH($A33,I$3)<>0,1,""),"") | J33: =IFERROR(IF(SEARCH($A33,J$3)<>0,1,""),"") | ... P33: =IFERROR(IF(SEARCH($A33,P$3)<>0,1,""),"") | Q33: 18 | R33: =IFERROR(IF(SEARCH($A33,R$3)<>0,1,""),"") | S33: =IFERROR(IF(SEARCH($A33,S$3)<>0,1,""),"") | T33: =IFERROR(IF(SEARCH($A33,T$3)<>0,1,""),"") | U33: =IFERROR(IF(SEARCH($A33,U$3)<>0,1,""),"") | V33: =IFERROR(IF(SEARCH($A33,V$3)<>0,1,""),"") | W33: =IFERROR(IF(SEARCH($A33,W$3)<>0,1,""),"") | X33: =IFERROR(IF(SEARCH($A33,X$3)<>0,1,""),"") | Y33: =IFERROR(IF(SEARCH($A33,Y$3)<>0,1,""),"") | ... BA33: =IFERROR(IF(SEARCH($A33,BA$3)<>0,1,""),"") | BB33: =SUM(C33:BA33) -> 18 | BC33: =IFERROR(SEARCH(_xlfn.CONCAT(" ",$A33),#REF!),"") | BD33: =IFERROR(SEARCH(_xlfn.CONCAT(" ",$A33),#REF!),"") | BE33: =SUM(BC33:BD33) -> 0 | BF33: =BB33+BE33 -> 18
A34: УК-9.1 | B34: =VLOOKUP(A34,Лист1!B:C,2,0) -> Осуществляет взаимодействие в социальной и профессиональной сферах с лицами с ограниченными возможностями здоровья и инвалидами | C34: =IFERROR(SEARCH($A34,C$3),"") | D34: =IFERROR(SEARCH($A34,D$3),"") | E34: =IFERROR(SEARCH($A34,E$3),"") | F34: =IFERROR(SEARCH($A34,F$3),"") | G34: =IFERROR(SEARCH($A34,G$3),"") | H34: =IFERROR(SEARCH($A34,H$3),"") | I34: =IFERROR(SEARCH($A34,I$3),"") | J34: =IFERROR(SEARCH($A34,J$3),"") | ... P34: =IFERROR(SEARCH($A34,P$3),"") | Q34: 9 | R34: =IFERROR(SEARCH($A34,R$3),"") | S34: =IFERROR(SEARCH($A34,S$3),"") | T34: =IFERROR(SEARCH($A34,T$3),"") | U34: =IFERROR(SEARCH($A34,U$3),"") | V34: =IFERROR(SEARCH($A34,V$3),"") | W34: =IFERROR(SEARCH($A34,W$3),"") | X34: =IFERROR(SEARCH($A34,X$3),"") | Y34: =IFERROR(SEARCH($A34,Y$3),"") | ... BA34: =IFERROR(SEARCH($A34,BA$3),"") | BB34: =SUM(C34:BA34) -> 9 | BC34: =IFERROR(SEARCH($A34,BC$3),"") | BD34: =IFERROR(SEARCH($A34,BD$3),"") | BE34: =SUM(BC34:BD34) -> 0 | BF34: =BB34+BE34 -> 9
A35: УК-9.2 | B35: =VLOOKUP(A35,Лист1!B:C,2,0) -> Планирует мероприятия по организации доступной среды на объектах транспорта для безбарьерного обслуживания пассажиров из числа инвалидов и лиц с ограниченными возможностями здоровья | C35: =IFERROR(SEARCH($A35,C$3),"") | D35: =IFERROR(SEARCH($A35,D$3),"") | E35: =IFERROR(SEARCH($A35,E$3),"") | F35: =IFERROR(SEARCH($A35,F$3),"") | G35: =IFERROR(SEARCH($A35,G$3),"") | H35: =IFERROR(SEARCH($A35,H$3),"") | I35: =IFERROR(SEARCH($A35,I$3),"") | J35: =IFERROR(SEARCH($A35,J$3),"") | ... BA35: =IFERROR(SEARCH($A35,BA$3),"") | BB35: =SUM(C35:BA35) -> 9 | BC35: =IFERROR(SEARCH($A35,BC$3),"") | BD35: =IFERROR(SEARCH($A35,BD$3),"") | BE35: =SUM(BC35:BD35) -> 0 | BF35: =BB35+BE35 -> 9
A36: УК-10 | B36: =VLOOKUP(A36,Лист1!B:C,2,0) -> Способен принимать обоснованные экономические решения в различных областях жизнедеятельности | C36: =IFERROR(IF(SEARCH($A36,C$3)<>0,1,""),"") | D36: =IFERROR(IF(SEARCH($A36,D$3)<>0,1,""),"") | E36: =IFERROR(IF(SEARCH($A36,E$3)<>0,1,""),"") | F36: =IFERROR(IF(SEARCH($A36,F$3)<>0,1,""),"") | G36: =IFERROR(IF(SEARCH($A36,G$3)<>0,1,""),"") | H36: =IFERROR(IF(SEARCH($A36,H$3)<>0,1,""),"") | I36: =IFERROR(IF(SEARCH($A36,I$3)<>0,1,""),"") | J36: =IFERROR(IF(SEARCH($A36,J$3)<>0,1,""),"") | ... S36: =IFERROR(IF(SEARCH($A36,S$3)<>0,1,""),"") | T36: 18 | U36: =IFERROR(IF(SEARCH($A36,U$3)<>0,1,""),"") | V36: =IFERROR(IF(SEARCH($A36,V$3)<>0,1,""),"") | W36: =IFERROR(IF(SEARCH($A36,W$3)<>0,1,""),"") | X36: =IFERROR(IF(SEARCH($A36,X$3)<>0,1,""),"") | Y36: =IFERROR(IF(SEARCH($A36,Y$3)<>0,1,""),"") | Z36: =IFERROR(IF(SEARCH($A36,Z$3)<>0,1,""),"") | AA36: =IFERROR(IF(SEARCH($A36,AA$3)<>0,1,""),"") | AB36: =IFERROR(IF(SEARCH($A36,AB$3)<>0,1,""),"") | ... BA36: =IFERROR(IF(SEARCH($A36,BA$3)<>0,1,""),"") | BB36: =SUM(C36:BA36) -> 18 | BE36: =SUM(BC36:BD36) -> 0 | BF36: =BB36+BE36 -> 18
A37: УК-10.1 | B37: =VLOOKUP(A37,Лист1!B:C,2,0) -> Анализирует и критически оценивает информацию, необходимую для принятия обоснованных экономических решений | C37: =IFERROR(SEARCH($A37,C$3),"") | D37: =IFERROR(SEARCH($A37,D$3),"") | E37: =IFERROR(SEARCH($A37,E$3),"") | F37: =IFERROR(SEARCH($A37,F$3),"") | G37: =IFERROR(SEARCH($A37,G$3),"") | H37: =IFERROR(SEARCH($A37,H$3),"") | I37: =IFERROR(SEARCH($A37,I$3),"") | J37: =IFERROR(SEARCH($A37,J$3),"") | ... S37: =IFERROR(SEARCH($A37,S$3),"") | T37: 9 | U37: =IFERROR(SEARCH($A37,U$3),"") | V37: =IFERROR(SEARCH($A37,V$3),"") | W37: =IFERROR(SEARCH($A37,W$3),"") | X37: =IFERROR(SEARCH($A37,X$3),"") | Y37: =IFERROR(SEARCH($A37,Y$3),"") | Z37: =IFERROR(SEARCH($A37,Z$3),"") | AA37: =IFERROR(SEARCH($A37,AA$3),"") | AB37: =IFERROR(SEARCH($A37,AB$3),"") | ... BA37: =IFERROR(SEARCH($A37,BA$3),"") | BB37: =SUM(C37:BA37) -> 9 | BC37: =IFERROR(SEARCH($A37,BC$3),"") | BD37: =IFERROR(SEARCH($A37,BD$3),"") | BE37: =SUM(BC37:BD37) -> 0 | BF37: =BB37+BE37 -> 9
A38: УК-10.2 | B38: =VLOOKUP(A38,Лист1!B:C,2,0) -> Применяет методы личного экономического и финансового планирования для достижения текущих и долгосрочных финансовых целей, использует финансовые инструменты для управления личными финансами (личным бюджетом), контролирует собственные экономические и финансовые риски | C38: =IFERROR(SEARCH($A38,C$3),"") | D38: =IFERROR(SEARCH($A38,D$3),"") | E38: =IFERROR(SEARCH($A38,E$3),"") | F38: =IFERROR(SEARCH($A38,F$3),"") | G38: =IFERROR(SEARCH($A38,G$3),"") | H38: =IFERROR(SEARCH($A38,H$3),"") | I38: =IFERROR(SEARCH($A38,I$3),"") | J38: =IFERROR(SEARCH($A38,J$3),"") | ... S38: =IFERROR(SEARCH($A38,S$3),"") | T38: 9 | U38: =IFERROR(SEARCH($A38,U$3),"") | V38: =IFERROR(SEARCH($A38,V$3),"") | W38: =IFERROR(SEARCH($A38,W$3),"") | X38: =IFERROR(SEARCH($A38,X$3),"") | Y38: =IFERROR(SEARCH($A38,Y$3),"") | Z38: =IFERROR(SEARCH($A38,Z$3),"") | AA38: =IFERROR(SEARCH($A38,AA$3),"") | AB38: =IFERROR(SEARCH($A38,AB$3),"") | ... BA38: =IFERROR(SEARCH($A38,BA$3),"") | BB38: =SUM(C38:BA38) -> 9 | BC38: =IFERROR(SEARCH($A38,BC$3),"") | BD38: =IFERROR(SEARCH($A38,BD$3),"") | BE38: =SUM(BC38:BD38) -> 0 | BF38: =BB38+BE38 -> 9
A39: УК-11 | B39: =VLOOKUP(A39,Лист1!B:C,2,0) -> Способен формировать нетерпимое отношение к проявлениям экстремизма, терроризма, коррупционному поведению и противодействовать им в профессиональной деятельности | C39: =IFERROR(IF(SEARCH($A39,C$3)<>0,1,""),"") | D39: =IFERROR(IF(SEARCH($A39,D$3)<>0,1,""),"") | E39: =IFERROR(IF(SEARCH($A39,E$3)<>0,1,""),"") | F39: =IFERROR(IF(SEARCH($A39,F$3)<>0,1,""),"") | G39: =IFERROR(IF(SEARCH($A39,G$3)<>0,1,""),"") | H39: =IFERROR(IF(SEARCH($A39,H$3)<>0,1,""),"") | I39: =IFERROR(IF(SEARCH($A39,I$3)<>0,1,""),"") | J39: =IFERROR(IF(SEARCH($A39,J$3)<>0,1,""),"") | ... Q39: =IFERROR(IF(SEARCH($A39,Q$3)<>0,1,""),"") | R39: 18 | S39: =IFERROR(IF(SEARCH($A39,S$3)<>0,1,""),"") | T39: =IFERROR(IF(SEARCH($A39,T$3)<>0,1,""),"") | U39: =IFERROR(IF(SEARCH($A39,U$3)<>0,1,""),"") | V39: =IFERROR(IF(SEARCH($A39,V$3)<>0,1,""),"") | W39: =IFERROR(IF(SEARCH($A39,W$3)<>0,1,""),"") | X39: =IFERROR(IF(SEARCH($A39,X$3)<>0,1,""),"") | Y39: =IFERROR(IF(SEARCH($A39,Y$3)<>0,1,""),"") | Z39: =IFERROR(IF(SEARCH($A39,Z$3)<>0,1,""),"") | ... BA39: =IFERROR(IF(SEARCH($A39,BA$3)<>0,1,""),"") | BB39: =SUM(C39:BA39) -> 18 | BC39: =IFERROR(SEARCH(_xlfn.CONCAT(" ",$A39),#REF!),"") | BD39: =IFERROR(SEARCH(_xlfn.CONCAT(" ",$A39),#REF!),"") | BE39: =SUM(BC39:BD39) -> 0 | BF39: =BB39+BE39 -> 18
A40: УК-11.1 | B40: =VLOOKUP(A40,Лист1!B:C,2,0) -> Раскрывает механизм проявления коррупционного поведения и определяет способы противодействия ему в профессиональной деятельности | C40: =IFERROR(SEARCH($A40,C$3),"") | D40: =IFERROR(SEARCH($A40,D$3),"") | E40: =IFERROR(SEARCH($A40,E$3),"") | F40: =IFERROR(SEARCH($A40,F$3),"") | G40: =IFERROR(SEARCH($A40,G$3),"") | H40: =IFERROR(SEARCH($A40,H$3),"") | I40: =IFERROR(SEARCH($A40,I$3),"") | J40: =IFERROR(SEARCH($A40,J$3),"") | ... BA40: =IFERROR(SEARCH($A40,BA$3),"") | BB40: =SUM(C40:BA40) -> 9 | BC40: =IFERROR(SEARCH($A40,BC$3),"") | BD40: =IFERROR(SEARCH($A40,BD$3),"") | BE40: =SUM(BC40:BD40) -> 0 | BF40: =BB40+BE40 -> 9
A41: УК-11.2 | B41: =VLOOKUP(A41,Лист1!B:C,2,0) -> Обосновывает правовыми средствами свою гражданскую позицию в отношении терроризма и экстремизма и применяет способы противодействия им в профессиональной сфере | C41: =IFERROR(SEARCH($A41,C$3),"") | D41: =IFERROR(SEARCH($A41,D$3),"") | E41: =IFERROR(SEARCH($A41,E$3),"") | F41: =IFERROR(SEARCH($A41,F$3),"") | G41: =IFERROR(SEARCH($A41,G$3),"") | H41: =IFERROR(SEARCH($A41,H$3),"") | I41: =IFERROR(SEARCH($A41,I$3),"") | J41: =IFERROR(SEARCH($A41,J$3),"") | ... Q41: =IFERROR(SEARCH($A41,Q$3),"") | R41: 9 | S41: =IFERROR(SEARCH($A41,S$3),"") | T41: =IFERROR(SEARCH($A41,T$3),"") | U41: =IFERROR(SEARCH($A41,U$3),"") | V41: =IFERROR(SEARCH($A41,V$3),"") | W41: =IFERROR(SEARCH($A41,W$3),"") | X41: =IFERROR(SEARCH($A41,X$3),"") | Y41: =IFERROR(SEARCH($A41,Y$3),"") | Z41: =IFERROR(SEARCH($A41,Z$3),"") | ... BA41: =IFERROR(SEARCH($A41,BA$3),"") | BB41: =SUM(C41:BA41) -> 9 | BC41: =IFERROR(SEARCH($A41,BC$3),"") | BD41: =IFERROR(SEARCH($A41,BD$3),"") | BE41: =SUM(BC41:BD41) -> 0 | BF41: =BB41+BE41 -> 9
A42: ОПК-1 | B42: =VLOOKUP(A42,Лист1!B:C,2,0) -> Способен применять естественнонаучные и общеинженерные знания, методы математического анализа и моделирования в профессиональной деятельности | C42: =IFERROR(IF(SEARCH($A42,C$3)<>0,1,""),"") | D42: =IFERROR(IF(SEARCH($A42,D$3)<>0,1,""),"") | E42: =IFERROR(IF(SEARCH($A42,E$3)<>0,1,""),"") | F42: =IFERROR(IF(SEARCH($A42,F$3)<>0,1,""),"") | G42: =IFERROR(IF(SEARCH($A42,G$3)<>0,1,""),"") | H42: =IFERROR(IF(SEARCH($A42,H$3)<>0,1,""),"") | I42: =IFERROR(IF(SEARCH($A42,I$3)<>0,1,""),"") | J42: =IFERROR(IF(SEARCH($A42,J$3)<>0,1,""),"") | K42: =IFERROR(IF(SEARCH($A42,K$3)<>0,1,""),"") | L42: 18 | M42: 18 | N42: 18 | O42: =IFERROR(IF(SEARCH($A42,O$3)<>0,1,""),"") | P42: =IFERROR(IF(SEARCH($A42,P$3)<>0,1,""),"") | Q42: =IFERROR(IF(SEARCH($A42,Q$3)<>0,1,""),"") | R42: =IFERROR(IF(SEARCH($A42,R$3)<>0,1,""),"") | S42: 18 | T42: =IFERROR(IF(SEARCH($A42,T$3)<>0,1,""),"") | U42: =IFERROR(IF(SEARCH($A42,U$3)<>0,1,""),"") | V42: =IFERROR(IF(SEARCH($A42,V$3)<>0,1,""),"") | W42: =IFERROR(IF(SEARCH($A42,W$3)<>0,1,""),"") | X42: =IFERROR(IF(SEARCH($A42,X$3)<>0,1,""),"") | Y42: =IFERROR(IF(SEARCH($A42,Y$3)<>0,1,""),"") | Z42: =IFERROR(IF(SEARCH($A42,Z$3)<>0,1,""),"") | AA42: 9 | AB42: =IFERROR(IF(SEARCH($A42,AB$3)<>0,1,""),"") | AC42: =IFERROR(IF(SEARCH($A42,AC$3)<>0,1,""),"") | AD42: =IFERROR(IF(SEARCH($A42,AD$3)<>0,1,""),"") | AE42: =IFERROR(IF(SEARCH($A42,AE$3)<>0,1,""),"") | AF42: =IFERROR(IF(SEARCH($A42,AF$3)<>0,1,""),"") | AG42: =IFERROR(IF(SEARCH($A42,AG$3)<>0,1,""),"") | AH42: =IFERROR(IF(SEARCH($A42,AH$3)<>0,1,""),"") | AI42: =IFERROR(IF(SEARCH($A42,AI$3)<>0,1,""),"") | ... BA42: =IFERROR(IF(SEARCH($A42,BA$3)<>0,1,""),"") | BB42: =SUM(C42:BA42) -> 81 | BC42: =IFERROR(SEARCH(_xlfn.CONCAT(" ",$A42),#REF!),"") | BD42: =IFERROR(SEARCH(_xlfn.CONCAT(" ",$A42),#REF!),"") | BE42: =SUM(BC42:BD42) -> 0 | BF42: =BB42+BE42 -> 81
A43: ОПК-1.1 | B43: =VLOOKUP(A43,Лист1!B:C,2,0) -> Применяет методы высшей математики для решения задач профессиональной деятельности | C43: =IFERROR(SEARCH($A43,C$3),"") | D43: =IFERROR(SEARCH($A43,D$3),"") | E43: =IFERROR(SEARCH($A43,E$3),"") | F43: =IFERROR(SEARCH($A43,F$3),"") | G43: =IFERROR(SEARCH($A43,G$3),"") | H43: =IFERROR(SEARCH($A43,H$3),"") | I43: =IFERROR(SEARCH($A43,I$3),"") | J43: =IFERROR(SEARCH($A43,J$3),"") | ... M43: =IFERROR(SEARCH($A43,M$3),"") | N43: 18 | O43: =IFERROR(SEARCH($A43,O$3),"") | P43: =IFERROR(SEARCH($A43,P$3),"") | Q43: =IFERROR(SEARCH($A43,Q$3),"") | R43: =IFERROR(SEARCH($A43,R$3),"") | S43: =IFERROR(SEARCH($A43,S$3),"") | T43: =IFERROR(SEARCH($A43,T$3),"") | U43: =IFERROR(SEARCH($A43,U$3),"") | V43: =IFERROR(SEARCH($A43,V$3),"") | ... BA43: =IFERROR(SEARCH($A43,BA$3),"") | BB43: =SUM(C43:BA43) -> 18 | BC43: =IFERROR(SEARCH($A43,BC$3),"") | BD43: =IFERROR(SEARCH($A43,BD$3),"") | BE43: =SUM(BC43:BD43) -> 0 | BF43: =BB43+BE43 -> 18
A44: ОПК-1.2 | B44: =VLOOKUP(A44,Лист1!B:C,2,0) -> Применяет основные понятия и законы естественных наук для решения предметно-профильных задач | C44: =IFERROR(SEARCH($A44,C$3),"") | D44: =IFERROR(SEARCH($A44,D$3),"") | E44: =IFERROR(SEARCH($A44,E$3),"") | F44: =IFERROR(SEARCH($A44,F$3),"") | G44: =IFERROR(SEARCH($A44,G$3),"") | H44: =IFERROR(SEARCH($A44,H$3),"") | I44: =IFERROR(SEARCH($A44,I$3),"") | J44: =IFERROR(SEARCH($A44,J$3),"") | K44: =IFERROR(SEARCH($A44,K$3),"") | L44: 9 | M44: 9 | N44: =IFERROR(SEARCH($A44,N$3),"") | O44: =IFERROR(SEARCH($A44,O$3),"") | P44: =IFERROR(SEARCH($A44,P$3),"") | Q44: =IFERROR(SEARCH($A44,Q$3),"") | R44: =IFERROR(SEARCH($A44,R$3),"") | S44: =IFERROR(SEARCH($A44,S$3),"") | T44: =IFERROR(SEARCH($A44,T$3),"") | U44: =IFERROR(SEARCH($A44,U$3),"") | ... BA44: =IFERROR(SEARCH($A44,BA$3),"") | BB44: =SUM(C44:BA44) -> 18 | BC44: =IFERROR(SEARCH($A44,BC$3),"") | BD44: =IFERROR(SEARCH($A44,BD$3),"") | BE44: =SUM(BC44:BD44) -> 0 | BF44: =BB44+BE44 -> 18
A45: ОПК-1.3 | B45: =VLOOKUP(A45,Лист1!B:C,2,0) -> Применяет естественнонаучные методы теоретического и экспериментального исследования объектов, процессов, явлений, проводит эксперименты по заданной методике и анализирует результаты | C45: =IFERROR(SEARCH($A45,C$3),"") | D45: =IFERROR(SEARCH($A45,D$3),"") | E45: =IFERROR(SEARCH($A45,E$3),"") | F45: =IFERROR(SEARCH($A45,F$3),"") | G45: =IFERROR(SEARCH($A45,G$3),"") | H45: =IFERROR(SEARCH($A45,H$3),"") | I45: =IFERROR(SEARCH($A45,I$3),"") | J45: =IFERROR(SEARCH($A45,J$3),"") | K45: =IFERROR(SEARCH($A45,K$3),"") | L45: 9 | M45: 9 | N45: =IFERROR(SEARCH($A45,N$3),"") | O45: =IFERROR(SEARCH($A45,O$3),"") | P45: =IFERROR(SEARCH($A45,P$3),"") | Q45: =IFERROR(SEARCH($A45,Q$3),"") | R45: =IFERROR(SEARCH($A45,R$3),"") | S45: =IFERROR(SEARCH($A45,S$3),"") | T45: =IFERROR(SEARCH($A45,T$3),"") | U45: =IFERROR(SEARCH($A45,U$3),"") | ... BA45: =IFERROR(SEARCH($A45,BA$3),"") | BB45: =SUM(C45:BA45) -> 18 | BC45: =IFERROR(SEARCH($A45,BC$3),"") | BD45: =IFERROR(SEARCH($A45,BD$3),"") | BE45: =SUM(BC45:BD45) -> 0 | BF45: =BB45+BE45 -> 18
A46: ОПК-1.4 | B46: =VLOOKUP(A46,Лист1!B:C,2,0) -> Разрабатывает графическую техническую документацию в соответствии с требованиями ЕСКД, в том числе с использованием пакетов прикладных программ для автоматизированного построения модели деталей техники | C46: =IFERROR(SEARCH($A46,C$3),"") | D46: =IFERROR(SEARCH($A46,D$3),"") | E46: =IFERROR(SEARCH($A46,E$3),"") | F46: =IFERROR(SEARCH($A46,F$3),"") | G46: =IFERROR(SEARCH($A46,G$3),"") | H46: =IFERROR(SEARCH($A46,H$3),"") | I46: =IFERROR(SEARCH($A46,I$3),"") | J46: =IFERROR(SEARCH($A46,J$3),"") | ... R46: =IFERROR(SEARCH($A46,R$3),"") | S46: 18 | T46: =IFERROR(SEARCH($A46,T$3),"") | U46: =IFERROR(SEARCH($A46,U$3),"") | V46: =IFERROR(SEARCH($A46,V$3),"") | W46: =IFERROR(SEARCH($A46,W$3),"") | X46: =IFERROR(SEARCH($A46,X$3),"") | Y46: =IFERROR(SEARCH($A46,Y$3),"") | Z46: =IFERROR(SEARCH($A46,Z$3),"") | AA46: =IFERROR(SEARCH($A46,AA$3),"") | ... BA46: =IFERROR(SEARCH($A46,BA$3),"") | BB46: =SUM(C46:BA46) -> 18 | BC46: =IFERROR(SEARCH($A46,BC$3),"") | BD46: =IFERROR(SEARCH($A46,BD$3),"") | BE46: =SUM(BC46:BD46) -> 0 | BF46: =BB46+BE46 -> 18
A47: ОПК-1.5 | B47: =VLOOKUP(A47,Лист1!B:C,2,0) -> Применяет методы математического анализа и моделирования для решения прикладных задач | C47: =IFERROR(SEARCH($A47,C$3),"") | D47: =IFERROR(SEARCH($A47,D$3),"") | E47: =IFERROR(SEARCH($A47,E$3),"") | F47: =IFERROR(SEARCH($A47,F$3),"") | G47: =IFERROR(SEARCH($A47,G$3),"") | H47: =IFERROR(SEARCH($A47,H$3),"") | I47: =IFERROR(SEARCH($A47,I$3),"") | J47: =IFERROR(SEARCH($A47,J$3),"") | ... Z47: =IFERROR(SEARCH($A47,Z$3),"") | AA47: 9 | AB47: =IFERROR(SEARCH($A47,AB$3),"") | AC47: =IFERROR(SEARCH($A47,AC$3),"") | AD47: =IFERROR(SEARCH($A47,AD$3),"") | AE47: =IFERROR(SEARCH($A47,AE$3),"") | AF47: =IFERROR(SEARCH($A47,AF$3),"") | AG47: =IFERROR(SEARCH($A47,AG$3),"") | AH47: =IFERROR(SEARCH($A47,AH$3),"") | AI47: =IFERROR(SEARCH($A47,AI$3),"") | ... BA47: =IFERROR(SEARCH($A47,BA$3),"") | BB47: =SUM(C47:BA47) -> 9 | BC47: =IFERROR(SEARCH($A47,BC$3),"") | BD47: =IFERROR(SEARCH($A47,BD$3),"") | BE47: =SUM(BC47:BD47) -> 0 | BF47: =BB47+BE47 -> 9
A48: ОПК-2 | B48: =VLOOKUP(A48,Лист1!B:C,2,0) -> Способен осуществлять профессиональную деятельность с учетом экономических, экологических и социальных ограничений на всех этапах жизненного цикла транспортно-технологических машин и комплексов | C48: =IFERROR(IF(SEARCH($A48,C$3)<>0,1,""),"") | D48: =IFERROR(IF(SEARCH($A48,D$3)<>0,1,""),"") | E48: =IFERROR(IF(SEARCH($A48,E$3)<>0,1,""),"") | F48: =IFERROR(IF(SEARCH($A48,F$3)<>0,1,""),"") | G48: =IFERROR(IF(SEARCH($A48,G$3)<>0,1,""),"") | H48: =IFERROR(IF(SEARCH($A48,H$3)<>0,1,""),"") | I48: =IFERROR(IF(SEARCH($A48,I$3)<>0,1,""),"") | J48: =IFERROR(IF(SEARCH($A48,J$3)<>0,1,""),"") | ... S48: =IFERROR(IF(SEARCH($A48,S$3)<>0,1,""),"") | T48: 2 | U48: 18 | V48: 2 | W48: =IFERROR(IF(SEARCH($A48,W$3)<>0,1,""),"") | X48: 9 | Y48: =IFERROR(IF(SEARCH($A48,Y$3)<>0,1,""),"") | Z48: =IFERROR(IF(SEARCH($A48,Z$3)<>0,1,""),"") | AA48: =IFERROR(IF(SEARCH($A48,AA$3)<>0,1,""),"") | AB48: =IFERROR(IF(SEARCH($A48,AB$3)<>0,1,""),"") | AC48: =IFERROR(IF(SEARCH($A48,AC$3)<>0,1,""),"") | AD48: =IFERROR(IF(SEARCH($A48,AD$3)<>0,1,""),"") | AE48: =IFERROR(IF(SEARCH($A48,AE$3)<>0,1,""),"") | AF48: =IFERROR(IF(SEARCH($A48,AF$3)<>0,1,""),"") | ... BA48: =IFERROR(IF(SEARCH($A48,BA$3)<>0,1,""),"") | BB48: =SUM(C48:BA48) -> 31 | BE48: =SUM(BC48:BD48) -> 0 | BF48: =BB48+BE48 -> 31
A49: ОПК-2.1 | B49: =VLOOKUP(A49,Лист1!B:C,2,0) -> Осуществляет мониторинг, прогнозирование и оценку экологической безопасности действующих, вновь строящихся и реконструируемых объектов | C49: =IFERROR(SEARCH($A49,C$3),"") | D49: =IFERROR(SEARCH($A49,D$3),"") | E49: =IFERROR(SEARCH($A49,E$3),"") | F49: =IFERROR(SEARCH($A49,F$3),"") | G49: =IFERROR(SEARCH($A49,G$3),"") | H49: =IFERROR(SEARCH($A49,H$3),"") | I49: =IFERROR(SEARCH($A49,I$3),"") | J49: =IFERROR(SEARCH($A49,J$3),"") | ... T49: =IFERROR(SEARCH($A49,T$3),"") | U49: 18 | V49: =IFERROR(SEARCH($A49,V$3),"") | W49: =IFERROR(SEARCH($A49,W$3),"") | X49: =IFERROR(SEARCH($A49,X$3),"") | Y49: =IFERROR(SEARCH($A49,Y$3),"") | Z49: =IFERROR(SEARCH($A49,Z$3),"") | AA49: =IFERROR(SEARCH($A49,AA$3),"") | AB49: =IFERROR(SEARCH($A49,AB$3),"") | AC49: =IFERROR(SEARCH($A49,AC$3),"") | ... BA49: =IFERROR(SEARCH($A49,BA$3),"") | BB49: =SUM(C49:BA49) -> 18 | BC49: =IFERROR(SEARCH($A49,BC$3),"") | BD49: =IFERROR(SEARCH($A49,BD$3),"") | BE49: =SUM(BC49:BD49) -> 0 | BF49: =BB49+BE49 -> 18
A50: ОПК-2.2 | B50: =VLOOKUP(A50,Лист1!B:C,2,0) -> Решает задачи профессиональной деятельности с учетом экономических ограничений на всех этапах жизненного цикла транспортно-технологических машин и комплексов | C50: =IFERROR(SEARCH($A50,C$3),"") | D50: =IFERROR(SEARCH($A50,D$3),"") | E50: =IFERROR(SEARCH($A50,E$3),"") | F50: =IFERROR(SEARCH($A50,F$3),"") | G50: =IFERROR(SEARCH($A50,G$3),"") | H50: =IFERROR(SEARCH($A50,H$3),"") | I50: =IFERROR(SEARCH($A50,I$3),"") | J50: =IFERROR(SEARCH($A50,J$3),"") | ... S50: =IFERROR(SEARCH($A50,S$3),"") | T50: 2 | U50: =IFERROR(SEARCH($A50,U$3),"") | V50: =IFERROR(SEARCH($A50,V$3),"") | W50: =IFERROR(SEARCH($A50,W$3),"") | X50: =IFERROR(SEARCH($A50,X$3),"") | Y50: =IFERROR(SEARCH($A50,Y$3),"") | Z50: =IFERROR(SEARCH($A50,Z$3),"") | AA50: =IFERROR(SEARCH($A50,AA$3),"") | AB50: =IFERROR(SEARCH($A50,AB$3),"") | ... BA50: =IFERROR(SEARCH($A50,BA$3),"") | BB50: =SUM(C50:BA50) -> 2 | BC50: =IFERROR(SEARCH($A50,BC$3),"") | BD50: =IFERROR(SEARCH($A50,BD$3),"") | BE50: =SUM(BC50:BD50) -> 0 | BF50: =BB50+BE50 -> 2
A51: ОПК-2.3 | B51: =VLOOKUP(A51,Лист1!B:C,2,0) -> Применяет теоретические основы менеджмента при решении профессиональных задач | C51: =IFERROR(SEARCH($A51,C$3),"") | D51: =IFERROR(SEARCH($A51,D$3),"") | E51: =IFERROR(SEARCH($A51,E$3),"") | F51: =IFERROR(SEARCH($A51,F$3),"") | G51: =IFERROR(SEARCH($A51,G$3),"") | H51: =IFERROR(SEARCH($A51,H$3),"") | I51: =IFERROR(SEARCH($A51,I$3),"") | J51: =IFERROR(SEARCH($A51,J$3),"") | ... U51: =IFERROR(SEARCH($A51,U$3),"") | V51: 2 | W51: =IFERROR(SEARCH($A51,W$3),"") | X51: =IFERROR(SEARCH($A51,X$3),"") | Y51: =IFERROR(SEARCH($A51,Y$3),"") | Z51: =IFERROR(SEARCH($A51,Z$3),"") | AA51: =IFERROR(SEARCH($A51,AA$3),"") | AB51: =IFERROR(SEARCH($A51,AB$3),"") | AC51: =IFERROR(SEARCH($A51,AC$3),"") | AD51: =IFERROR(SEARCH($A51,AD$3),"") | ... BA51: =IFERROR(SEARCH($A51,BA$3),"") | BB51: =SUM(C51:BA51) -> 2 | BC51: =IFERROR(SEARCH($A51,BC$3),"") | BD51: =IFERROR(SEARCH($A51,BD$3),"") | BE51: =SUM(BC51:BD51) -> 0 | BF51: =BB51+BE51 -> 2
A52: ОПК-2.4 | B52: =VLOOKUP(A52,Лист1!B:C,2,0) -> Предлагает решение проблем, связанных с формированием или развитием транспортно-технологических систем (в том числе машин и комплексов) | C52: =IFERROR(SEARCH($A52,C$3),"") | D52: =IFERROR(SEARCH($A52,D$3),"") | E52: =IFERROR(SEARCH($A52,E$3),"") | F52: =IFERROR(SEARCH($A52,F$3),"") | G52: =IFERROR(SEARCH($A52,G$3),"") | H52: =IFERROR(SEARCH($A52,H$3),"") | I52: =IFERROR(SEARCH($A52,I$3),"") | J52: =IFERROR(SEARCH($A52,J$3),"") | ... W52: =IFERROR(SEARCH($A52,W$3),"") | X52: 9 | Y52: =IFERROR(SEARCH($A52,Y$3),"") | Z52: =IFERROR(SEARCH($A52,Z$3),"") | AA52: =IFERROR(SEARCH($A52,AA$3),"") | AB52: =IFERROR(SEARCH($A52,AB$3),"") | AC52: =IFERROR(SEARCH($A52,AC$3),"") | AD52: =IFERROR(SEARCH($A52,AD$3),"") | AE52: =IFERROR(SEARCH($A52,AE$3),"") | AF52: =IFERROR(SEARCH($A52,AF$3),"") | ... BA52: =IFERROR(SEARCH($A52,BA$3),"") | BB52: =SUM(C52:BA52) -> 9 | BC52: =IFERROR(SEARCH($A52,BC$3),"") | BD52: =IFERROR(SEARCH($A52,BD$3),"") | BE52: =SUM(BC52:BD52) -> 0 | BF52: =BB52+BE52 -> 9
A53: ОПК-3 | B53: =VLOOKUP(A53,Лист1!B:C,2,0) -> Способен в сфере своей профессиональной деятельности проводить измерения и наблюдения, обрабатывать и представлять экспериментальные данные и результаты испытаний | C53: =IFERROR(IF(SEARCH($A53,C$3)<>0,1,""),"") | D53: =IFERROR(IF(SEARCH($A53,D$3)<>0,1,""),"") | E53: =IFERROR(IF(SEARCH($A53,E$3)<>0,1,""),"") | F53: =IFERROR(IF(SEARCH($A53,F$3)<>0,1,""),"") | G53: =IFERROR(IF(SEARCH($A53,G$3)<>0,1,""),"") | H53: =IFERROR(IF(SEARCH($A53,H$3)<>0,1,""),"") | I53: =IFERROR(IF(SEARCH($A53,I$3)<>0,1,""),"") | J53: =IFERROR(IF(SEARCH($A53,J$3)<>0,1,""),"") | ... V53: =IFERROR(IF(SEARCH($A53,V$3)<>0,1,""),"") | W53: 16 | X53: =IFERROR(IF(SEARCH($A53,X$3)<>0,1,""),"") | Y53: =IFERROR(IF(SEARCH($A53,Y$3)<>0,1,""),"") | Z53: =IFERROR(IF(SEARCH($A53,Z$3)<>0,1,""),"") | AA53: =IFERROR(IF(SEARCH($A53,AA$3)<>0,1,""),"") | AB53: =IFERROR(IF(SEARCH($A53,AB$3)<>0,1,""),"") | AC53: =IFERROR(IF(SEARCH($A53,AC$3)<>0,1,""),"") | AD53: =IFERROR(IF(SEARCH($A53,AD$3)<>0,1,""),"") | AE53: =IFERROR(IF(SEARCH($A53,AE$3)<>0,1,""),"") | ... BA53: =IFERROR(IF(SEARCH($A53,BA$3)<>0,1,""),"") | BB53: =SUM(C53:BA53) -> 16 | BC53: =IFERROR(SEARCH(_xlfn.CONCAT(" ",$A53),#REF!),"") | BE53: =SUM(BC53:BD53) -> 0 | BF53: =BB53+BE53 -> 16
A54: ОПК-3.1 | B54: =VLOOKUP(A54,Лист1!B:C,2,0) -> Проводит измерения и наблюдения с использованием технических средств с учетом правовых норм метрологии | C54: =IFERROR(SEARCH($A54,C$3),"") | D54: =IFERROR(SEARCH($A54,D$3),"") | E54: =IFERROR(SEARCH($A54,E$3),"") | F54: =IFERROR(SEARCH($A54,F$3),"") | G54: =IFERROR(SEARCH($A54,G$3),"") | H54: =IFERROR(SEARCH($A54,H$3),"") | I54: =IFERROR(SEARCH($A54,I$3),"") | J54: =IFERROR(SEARCH($A54,J$3),"") | ... V54: =IFERROR(SEARCH($A54,V$3),"") | W54: 8 | X54: =IFERROR(SEARCH($A54,X$3),"") | Y54: =IFERROR(SEARCH($A54,Y$3),"") | Z54: =IFERROR(SEARCH($A54,Z$3),"") | AA54: =IFERROR(SEARCH($A54,AA$3),"") | AB54: =IFERROR(SEARCH($A54,AB$3),"") | AC54: =IFERROR(SEARCH($A54,AC$3),"") | AD54: =IFERROR(SEARCH($A54,AD$3),"") | AE54: =IFERROR(SEARCH($A54,AE$3),"") | ... BA54: =IFERROR(SEARCH($A54,BA$3),"") | BB54: =SUM(C54:BA54) -> 8 | BC54: =IFERROR(SEARCH($A54,BC$3),"") | BD54: =IFERROR(SEARCH($A54,BD$3),"") | BE54: =SUM(BC54:BD54) -> 0 | BF54: =BB54+BE54 -> 8
A55: ОПК-3.2 | B55: =VLOOKUP(A55,Лист1!B:C,2,0) -> Обрабатывает и представляет результаты измерений в ходе выполнения экспериментальных испытаний в соответствии с требованиями действующих стандартов | C55: =IFERROR(SEARCH($A55,C$3),"") | D55: =IFERROR(SEARCH($A55,D$3),"") | E55: =IFERROR(SEARCH($A55,E$3),"") | F55: =IFERROR(SEARCH($A55,F$3),"") | G55: =IFERROR(SEARCH($A55,G$3),"") | H55: =IFERROR(SEARCH($A55,H$3),"") | I55: =IFERROR(SEARCH($A55,I$3),"") | J55: =IFERROR(SEARCH($A55,J$3),"") | ... V55: =IFERROR(SEARCH($A55,V$3),"") | W55: 8 | X55: =IFERROR(SEARCH($A55,X$3),"") | Y55: =IFERROR(SEARCH($A55,Y$3),"") | Z55: =IFERROR(SEARCH($A55,Z$3),"") | AA55: =IFERROR(SEARCH($A55,AA$3),"") | AB55: =IFERROR(SEARCH($A55,AB$3),"") | AC55: =IFERROR(SEARCH($A55,AC$3),"") | AD55: =IFERROR(SEARCH($A55,AD$3),"") | AE55: =IFERROR(SEARCH($A55,AE$3),"") | ... BA55: =IFERROR(SEARCH($A55,BA$3),"") | BB55: =SUM(C55:BA55) -> 8 | BC55: =IFERROR(SEARCH($A55,BC$3),"") | BD55: =IFERROR(SEARCH($A55,BD$3),"") | BE55: =SUM(BC55:BD55) -> 0 | BF55: =BB55+BE55 -> 8
A56: ОПК-4 | B56: =VLOOKUP(A56,Лист1!B:C,2,0) -> Способен понимать принципы работы современных информационных технологий и использовать их для решения задач профессиональной деятельности | C56: =IFERROR(IF(SEARCH($A56,C$3)<>0,1,""),"") | D56: =IFERROR(IF(SEARCH($A56,D$3)<>0,1,""),"") | E56: =IFERROR(IF(SEARCH($A56,E$3)<>0,1,""),"") | F56: =IFERROR(IF(SEARCH($A56,F$3)<>0,1,""),"") | G56: =IFERROR(IF(SEARCH($A56,G$3)<>0,1,""),"") | H56: 18 | I56: 18 | J56: =IFERROR(IF(SEARCH($A56,J$3)<>0,1,""),"") | K56: =IFERROR(IF(SEARCH($A56,K$3)<>0,1,""),"") | L56: =IFERROR(IF(SEARCH($A56,L$3)<>0,1,""),"") | M56: =IFERROR(IF(SEARCH($A56,M$3)<>0,1,""),"") | N56: =IFERROR(IF(SEARCH($A56,N$3)<>0,1,""),"") | O56: =IFERROR(IF(SEARCH($A56,O$3)<>0,1,""),"") | P56: =IFERROR(IF(SEARCH($A56,P$3)<>0,1,""),"") | Q56: =IFERROR(IF(SEARCH($A56,Q$3)<>0,1,""),"") | ... X56: =IFERROR(IF(SEARCH($A56,X$3)<>0,1,""),"") | Y56: 18 | Z56: 18 | AA56: =IFERROR(IF(SEARCH($A56,AA$3)<>0,1,""),"") | AB56: =IFERROR(IF(SEARCH($A56,AB$3)<>0,1,""),"") | AC56: =IFERROR(IF(SEARCH($A56,AC$3)<>0,1,""),"") | AD56: =IFERROR(IF(SEARCH($A56,AD$3)<>0,1,""),"") | AE56: =IFERROR(IF(SEARCH($A56,AE$3)<>0,1,""),"") | AF56: =IFERROR(IF(SEARCH($A56,AF$3)<>0,1,""),"") | AG56: =IFERROR(IF(SEARCH($A56,AG$3)<>0,1,""),"") | AH56: =IFERROR(IF(SEARCH($A56,AH$3)<>0,1,""),"") | ... BA56: =IFERROR(IF(SEARCH($A56,BA$3)<>0,1,""),"") | BB56: =SUM(C56:BA56) -> 72 | BC56: =IFERROR(SEARCH(_xlfn.CONCAT(" ",$A56),#REF!),"") | BD56: =IFERROR(SEARCH(_xlfn.CONCAT(" ",$A56),#REF!),"") | BE56: =SUM(BC56:BD56) -> 0 | BF56: =BB56+BE56 -> 72
A57: ОПК-4.1 | B57: =VLOOKUP(A57,Лист1!B:C,2,0) -> Применяет основные методы представления информации и алгоритмы обработки данных в профессиональной деятельности | C57: =IFERROR(SEARCH($A57,C$3),"") | D57: =IFERROR(SEARCH($A57,D$3),"") | E57: =IFERROR(SEARCH($A57,E$3),"") | F57: =IFERROR(SEARCH($A57,F$3),"") | G57: =IFERROR(SEARCH($A57,G$3),"") | H57: 18 | I57: =IFERROR(SEARCH($A57,I$3),"") | J57: =IFERROR(SEARCH($A57,J$3),"") | K57: =IFERROR(SEARCH($A57,K$3),"") | L57: =IFERROR(SEARCH($A57,L$3),"") | M57: =IFERROR(SEARCH($A57,M$3),"") | N57: =IFERROR(SEARCH($A57,N$3),"") | O57: =IFERROR(SEARCH($A57,O$3),"") | P57: =IFERROR(SEARCH($A57,P$3),"") | ... BA57: =IFERROR(SEARCH($A57,BA$3),"") | BB57: =SUM(C57:BA57) -> 18 | BC57: =IFERROR(SEARCH($A57,BC$3),"") | BD57: =IFERROR(SEARCH($A57,BD$3),"") | BE57: =SUM(BC57:BD57) -> 0 | BF57: =BB57+BE57 -> 18
A58: ОПК-4.2 | B58: =VLOOKUP(A58,Лист1!B:C,2,0) -> Использует ресурсы электронной образовательной среды в рамках своей образовательной деятельности | C58: =IFERROR(SEARCH($A58,C$3),"") | D58: =IFERROR(SEARCH($A58,D$3),"") | E58: =IFERROR(SEARCH($A58,E$3),"") | F58: =IFERROR(SEARCH($A58,F$3),"") | G58: =IFERROR(SEARCH($A58,G$3),"") | H58: =IFERROR(SEARCH($A58,H$3),"") | I58: 18 | J58: =IFERROR(SEARCH($A58,J$3),"") | K58: =IFERROR(SEARCH($A58,K$3),"") | L58: =IFERROR(SEARCH($A58,L$3),"") | M58: =IFERROR(SEARCH($A58,M$3),"") | N58: =IFERROR(SEARCH($A58,N$3),"") | O58: =IFERROR(SEARCH($A58,O$3),"") | P58: =IFERROR(SEARCH($A58,P$3),"") | Q58: =IFERROR(SEARCH($A58,Q$3),"") | ... Y58: =IFERROR(SEARCH($A58,Y$3),"") | Z58: 9 | AA58: =IFERROR(SEARCH($A58,AA$3),"") | AB58: =IFERROR(SEARCH($A58,AB$3),"") | AC58: =IFERROR(SEARCH($A58,AC$3),"") | AD58: =IFERROR(SEARCH($A58,AD$3),"") | AE58: =IFERROR(SEARCH($A58,AE$3),"") | AF58: =IFERROR(SEARCH($A58,AF$3),"") | AG58: =IFERROR(SEARCH($A58,AG$3),"") | AH58: =IFERROR(SEARCH($A58,AH$3),"") | ... BA58: =IFERROR(SEARCH($A58,BA$3),"") | BB58: =SUM(C58:BA58) -> 27 | BC58: =IFERROR(SEARCH($A58,BC$3),"") | BD58: =IFERROR(SEARCH($A58,BD$3),"") | BE58: =SUM(BC58:BD58) -> 0 | BF58: =BB58+BE58 -> 27
A59: ОПК-4.3 | B59: =VLOOKUP(A59,Лист1!B:C,2,0) -> Использует в своей профессиональной деятельности автоматизированные информационно-управляющие и аналитические системы, применяемые на транспорте | C59: =IFERROR(SEARCH($A59,C$3),"") | D59: =IFERROR(SEARCH($A59,D$3),"") | E59: =IFERROR(SEARCH($A59,E$3),"") | F59: =IFERROR(SEARCH($A59,F$3),"") | G59: =IFERROR(SEARCH($A59,G$3),"") | H59: =IFERROR(SEARCH($A59,H$3),"") | I59: =IFERROR(SEARCH($A59,I$3),"") | J59: =IFERROR(SEARCH($A59,J$3),"") | ... Y59: =IFERROR(SEARCH($A59,Y$3),"") | Z59: 9 | AA59: =IFERROR(SEARCH($A59,AA$3),"") | AB59: =IFERROR(SEARCH($A59,AB$3),"") | AC59: =IFERROR(SEARCH($A59,AC$3),"") | AD59: =IFERROR(SEARCH($A59,AD$3),"") | AE59: =IFERROR(SEARCH($A59,AE$3),"") | AF59: =IFERROR(SEARCH($A59,AF$3),"") | AG59: =IFERROR(SEARCH($A59,AG$3),"") | AH59: =IFERROR(SEARCH($A59,AH$3),"") | ... BA59: =IFERROR(SEARCH($A59,BA$3),"") | BB59: =SUM(C59:BA59) -> 9 | BC59: =IFERROR(SEARCH($A59,BC$3),"") | BD59: =IFERROR(SEARCH($A59,BD$3),"") | BE59: =SUM(BC59:BD59) -> 0 | BF59: =BB59+BE59 -> 9
A60: ОПК-4.4 | B60: =VLOOKUP(A60,Лист1!B:C,2,0) -> Использует методы искусственного интеллекта (машинного обучения) и анализа больших данных для решения прикладных задач | C60: =IFERROR(SEARCH($A60,C$3),"") | D60: =IFERROR(SEARCH($A60,D$3),"") | E60: =IFERROR(SEARCH($A60,E$3),"") | F60: =IFERROR(SEARCH($A60,F$3),"") | G60: =IFERROR(SEARCH($A60,G$3),"") | H60: =IFERROR(SEARCH($A60,H$3),"") | I60: =IFERROR(SEARCH($A60,I$3),"") | J60: =IFERROR(SEARCH($A60,J$3),"") | ... X60: =IFERROR(SEARCH($A60,X$3),"") | Y60: 18 | Z60: =IFERROR(SEARCH($A60,Z$3),"") | AA60: =IFERROR(SEARCH($A60,AA$3),"") | AB60: =IFERROR(SEARCH($A60,AB$3),"") | AC60: =IFERROR(SEARCH($A60,AC$3),"") | AD60: =IFERROR(SEARCH($A60,AD$3),"") | AE60: =IFERROR(SEARCH($A60,AE$3),"") | AF60: =IFERROR(SEARCH($A60,AF$3),"") | AG60: =IFERROR(SEARCH($A60,AG$3),"") | ... BA60: =IFERROR(SEARCH($A60,BA$3),"") | BB60: =SUM(C60:BA60) -> 18 | BC60: =IFERROR(SEARCH($A60,BC$3),"") | BD60: =IFERROR(SEARCH($A60,BD$3),"") | BE60: =SUM(BC60:BD60) -> 0 | BF60: =BB60+BE60 -> 18
A61: ОПК-5 | B61: =VLOOKUP(A61,Лист1!B:C,2,0) -> Способен принимать обоснованные технические решения, выбирать эффективные и безопасные технические средства и технологии при решении задач профессиональной деятельности | C61: =IFERROR(IF(SEARCH($A61,C$3)<>0,1,""),"") | D61: =IFERROR(IF(SEARCH($A61,D$3)<>0,1,""),"") | E61: =IFERROR(IF(SEARCH($A61,E$3)<>0,1,""),"") | F61: =IFERROR(IF(SEARCH($A61,F$3)<>0,1,""),"") | G61: =IFERROR(IF(SEARCH($A61,G$3)<>0,1,""),"") | H61: =IFERROR(IF(SEARCH($A61,H$3)<>0,1,""),"") | I61: =IFERROR(IF(SEARCH($A61,I$3)<>0,1,""),"") | J61: =IFERROR(IF(SEARCH($A61,J$3)<>0,1,""),"") | ... O61: =IFERROR(IF(SEARCH($A61,O$3)<>0,1,""),"") | P61: 18 | Q61: =IFERROR(IF(SEARCH($A61,Q$3)<>0,1,""),"") | R61: =IFERROR(IF(SEARCH($A61,R$3)<>0,1,""),"") | S61: =IFERROR(IF(SEARCH($A61,S$3)<>0,1,""),"") | T61: =IFERROR(IF(SEARCH($A61,T$3)<>0,1,""),"") | U61: =IFERROR(IF(SEARCH($A61,U$3)<>0,1,""),"") | V61: =IFERROR(IF(SEARCH($A61,V$3)<>0,1,""),"") | W61: =IFERROR(IF(SEARCH($A61,W$3)<>0,1,""),"") | X61: 9 | Y61: =IFERROR(IF(SEARCH($A61,Y$3)<>0,1,""),"") | Z61: =IFERROR(IF(SEARCH($A61,Z$3)<>0,1,""),"") | AA61: =IFERROR(IF(SEARCH($A61,AA$3)<>0,1,""),"") | AB61: 6 | AC61: =IFERROR(IF(SEARCH($A61,AC$3)<>0,1,""),"") | AD61: =IFERROR(IF(SEARCH($A61,AD$3)<>0,1,""),"") | AE61: =IFERROR(IF(SEARCH($A61,AE$3)<>0,1,""),"") | AF61: =IFERROR(IF(SEARCH($A61,AF$3)<>0,1,""),"") | AG61: =IFERROR(IF(SEARCH($A61,AG$3)<>0,1,""),"") | AH61: =IFERROR(IF(SEARCH($A61,AH$3)<>0,1,""),"") | AI61: =IFERROR(IF(SEARCH($A61,AI$3)<>0,1,""),"") | AJ61: =IFERROR(IF(SEARCH($A61,AJ$3)<>0,1,""),"") | ... AW61: =IFERROR(IF(SEARCH($A61,AW$3)<>0,1,""),"") | AX61: 2 | AY61: =IFERROR(IF(SEARCH($A61,AY$3)<>0,1,""),"") | AZ61: =IFERROR(IF(SEARCH($A61,AZ$3)<>0,1,""),"") | BA61: =IFERROR(IF(SEARCH($A61,BA$3)<>0,1,""),"") | BB61: =SUM(C61:BA61) -> 35 | BE61: =SUM(BC61:BD61) -> 0 | BF61: =BB61+BE61 -> 35
A62: ОПК-5.1 | B62: =VLOOKUP(A62,Лист1!B:C,2,0) -> Обосновывает технические решения, выбирает эффективные и безопасные технические средства и технологии при решении задач профессиональной деятельности | C62: =IFERROR(SEARCH($A62,C$3),"") | D62: =IFERROR(SEARCH($A62,D$3),"") | E62: =IFERROR(SEARCH($A62,E$3),"") | F62: =IFERROR(SEARCH($A62,F$3),"") | G62: =IFERROR(SEARCH($A62,G$3),"") | H62: =IFERROR(SEARCH($A62,H$3),"") | I62: =IFERROR(SEARCH($A62,I$3),"") | J62: =IFERROR(SEARCH($A62,J$3),"") | ... AA62: =IFERROR(SEARCH($A62,AA$3),"") | AB62: 6 | AC62: =IFERROR(SEARCH($A62,AC$3),"") | AD62: =IFERROR(SEARCH($A62,AD$3),"") | AE62: =IFERROR(SEARCH($A62,AE$3),"") | AF62: =IFERROR(SEARCH($A62,AF$3),"") | AG62: =IFERROR(SEARCH($A62,AG$3),"") | AH62: =IFERROR(SEARCH($A62,AH$3),"") | AI62: =IFERROR(SEARCH($A62,AI$3),"") | AJ62: =IFERROR(SEARCH($A62,AJ$3),"") | ... BA62: =IFERROR(SEARCH($A62,BA$3),"") | BB62: =SUM(C62:BA62) -> 6 | BC62: =IFERROR(SEARCH($A62,BC$3),"") | BD62: =IFERROR(SEARCH($A62,BD$3),"") | BE62: =SUM(BC62:BD62) -> 0 | BF62: =BB62+BE62 -> 6
A63: ОПК-5.2 | B63: =VLOOKUP(A63,Лист1!B:C,2,0) -> Выбирает эффективные и безопасные технические средства и технологии погрузочно-разгрузочных работ | C63: =IFERROR(SEARCH($A63,C$3),"") | D63: =IFERROR(SEARCH($A63,D$3),"") | E63: =IFERROR(SEARCH($A63,E$3),"") | F63: =IFERROR(SEARCH($A63,F$3),"") | G63: =IFERROR(SEARCH($A63,G$3),"") | H63: =IFERROR(SEARCH($A63,H$3),"") | I63: =IFERROR(SEARCH($A63,I$3),"") | J63: =IFERROR(SEARCH($A63,J$3),"") | ... W63: =IFERROR(SEARCH($A63,W$3),"") | X63: 9 | Y63: =IFERROR(SEARCH($A63,Y$3),"") | Z63: =IFERROR(SEARCH($A63,Z$3),"") | AA63: =IFERROR(SEARCH($A63,AA$3),"") | AB63: =IFERROR(SEARCH($A63,AB$3),"") | AC63: =IFERROR(SEARCH($A63,AC$3),"") | AD63: =IFERROR(SEARCH($A63,AD$3),"") | AE63: =IFERROR(SEARCH($A63,AE$3),"") | AF63: =IFERROR(SEARCH($A63,AF$3),"") | ... BA63: =IFERROR(SEARCH($A63,BA$3),"") | BB63: =SUM(C63:BA63) -> 9 | BC63: =IFERROR(SEARCH($A63,BC$3),"") | BD63: =IFERROR(SEARCH($A63,BD$3),"") | BE63: =SUM(BC63:BD63) -> 0 | BF63: =BB63+BE63 -> 9
A64: ОПК-5.3 | B64: =VLOOKUP(A64,Лист1!B:C,2,0) -> Обосновывает выбор эффективных и безопасных технических средств и технологий при решении задач профессиональной деятельности | C64: =IFERROR(SEARCH($A64,C$3),"") | D64: =IFERROR(SEARCH($A64,D$3),"") | E64: =IFERROR(SEARCH($A64,E$3),"") | F64: =IFERROR(SEARCH($A64,F$3),"") | G64: =IFERROR(SEARCH($A64,G$3),"") | H64: =IFERROR(SEARCH($A64,H$3),"") | I64: =IFERROR(SEARCH($A64,I$3),"") | J64: =IFERROR(SEARCH($A64,J$3),"") | ... O64: =IFERROR(SEARCH($A64,O$3),"") | P64: 18 | Q64: =IFERROR(SEARCH($A64,Q$3),"") | R64: =IFERROR(SEARCH($A64,R$3),"") | S64: =IFERROR(SEARCH($A64,S$3),"") | T64: =IFERROR(SEARCH($A64,T$3),"") | U64: =IFERROR(SEARCH($A64,U$3),"") | V64: =IFERROR(SEARCH($A64,V$3),"") | W64: =IFERROR(SEARCH($A64,W$3),"") | X64: =IFERROR(SEARCH($A64,X$3),"") | ... AW64: =IFERROR(SEARCH($A64,AW$3),"") | AX64: 2 | AY64: =IFERROR(SEARCH($A64,AY$3),"") | AZ64: =IFERROR(SEARCH($A64,AZ$3),"") | BA64: =IFERROR(SEARCH($A64,BA$3),"") | BB64: =SUM(C64:BA64) -> 20 | BC64: =IFERROR(SEARCH($A64,BC$3),"") | BD64: =IFERROR(SEARCH($A64,BD$3),"") | BE64: =SUM(BC64:BD64) -> 0 | BF64: =BB64+BE64 -> 20
A65: ОПК-6 | B65: =VLOOKUP(A65,Лист1!B:C,2,0) -> Способен участвовать в разработке технической документации с использованием стандартов, норм и правил, связанных с профессиональной деятельностью | C65: =IFERROR(IF(SEARCH($A65,C$3)<>0,1,""),"") | D65: =IFERROR(IF(SEARCH($A65,D$3)<>0,1,""),"") | E65: =IFERROR(IF(SEARCH($A65,E$3)<>0,1,""),"") | F65: =IFERROR(IF(SEARCH($A65,F$3)<>0,1,""),"") | G65: =IFERROR(IF(SEARCH($A65,G$3)<>0,1,""),"") | H65: =IFERROR(IF(SEARCH($A65,H$3)<>0,1,""),"") | I65: =IFERROR(IF(SEARCH($A65,I$3)<>0,1,""),"") | J65: =IFERROR(IF(SEARCH($A65,J$3)<>0,1,""),"") | ... V65: =IFERROR(IF(SEARCH($A65,V$3)<>0,1,""),"") | W65: 16 | X65: =IFERROR(IF(SEARCH($A65,X$3)<>0,1,""),"") | Y65: =IFERROR(IF(SEARCH($A65,Y$3)<>0,1,""),"") | Z65: =IFERROR(IF(SEARCH($A65,Z$3)<>0,1,""),"") | AA65: =IFERROR(IF(SEARCH($A65,AA$3)<>0,1,""),"") | AB65: 6 | AC65: =IFERROR(IF(SEARCH($A65,AC$3)<>0,1,""),"") | AD65: =IFERROR(IF(SEARCH($A65,AD$3)<>0,1,""),"") | AE65: =IFERROR(IF(SEARCH($A65,AE$3)<>0,1,""),"") | AF65: =IFERROR(IF(SEARCH($A65,AF$3)<>0,1,""),"") | AG65: =IFERROR(IF(SEARCH($A65,AG$3)<>0,1,""),"") | AH65: =IFERROR(IF(SEARCH($A65,AH$3)<>0,1,""),"") | AI65: =IFERROR(IF(SEARCH($A65,AI$3)<>0,1,""),"") | AJ65: =IFERROR(IF(SEARCH($A65,AJ$3)<>0,1,""),"") | ... BA65: =IFERROR(IF(SEARCH($A65,BA$3)<>0,1,""),"") | BB65: =SUM(C65:BA65) -> 22 | BC65: =IFERROR(SEARCH(_xlfn.CONCAT(" ",$A65),#REF!),"") | BD65: =IFERROR(SEARCH(_xlfn.CONCAT(" ",$A65),#REF!),"") | BE65: =SUM(BC65:BD65) -> 0 | BF65: =BB65+BE65 -> 22
A66: ОПК-6.1 | B66: =VLOOKUP(A66,Лист1!B:C,2,0) -> Использует стандарты, нормы и правила, связанные с профессиональной деятельностью, при разработке технических и технологических мероприятий в организации перевозочного процесса и оказании логистических услуг | C66: =IFERROR(SEARCH($A66,C$3),"") | D66: =IFERROR(SEARCH($A66,D$3),"") | E66: =IFERROR(SEARCH($A66,E$3),"") | F66: =IFERROR(SEARCH($A66,F$3),"") | G66: =IFERROR(SEARCH($A66,G$3),"") | H66: =IFERROR(SEARCH($A66,H$3),"") | I66: =IFERROR(SEARCH($A66,I$3),"") | J66: =IFERROR(SEARCH($A66,J$3),"") | ... AA66: =IFERROR(SEARCH($A66,AA$3),"") | AB66: 6 | AC66: =IFERROR(SEARCH($A66,AC$3),"") | AD66: =IFERROR(SEARCH($A66,AD$3),"") | AE66: =IFERROR(SEARCH($A66,AE$3),"") | AF66: =IFERROR(SEARCH($A66,AF$3),"") | AG66: =IFERROR(SEARCH($A66,AG$3),"") | AH66: =IFERROR(SEARCH($A66,AH$3),"") | AI66: =IFERROR(SEARCH($A66,AI$3),"") | AJ66: =IFERROR(SEARCH($A66,AJ$3),"") | ... BA66: =IFERROR(SEARCH($A66,BA$3),"") | BB66: =SUM(C66:BA66) -> 6 | BC66: =IFERROR(SEARCH($A66,BC$3),"") | BD66: =IFERROR(SEARCH($A66,BD$3),"") | BE66: =SUM(BC66:BD66) -> 0 | BF66: =BB66+BE66 -> 6
A67: ОПК-6.2 | B67: =VLOOKUP(A67,Лист1!B:C,2,0) -> Разрабатывает технические и технологические мероприятия производственной деятельности с учетом действующих международных, российских, отраслевых стандартов, норм и правил | C67: =IFERROR(SEARCH($A67,C$3),"") | D67: =IFERROR(SEARCH($A67,D$3),"") | E67: =IFERROR(SEARCH($A67,E$3),"") | F67: =IFERROR(SEARCH($A67,F$3),"") | G67: =IFERROR(SEARCH($A67,G$3),"") | H67: =IFERROR(SEARCH($A67,H$3),"") | I67: =IFERROR(SEARCH($A67,I$3),"") | J67: =IFERROR(SEARCH($A67,J$3),"") | ... V67: =IFERROR(SEARCH($A67,V$3),"") | W67: 16 | X67: =IFERROR(SEARCH($A67,X$3),"") | Y67: =IFERROR(SEARCH($A67,Y$3),"") | Z67: =IFERROR(SEARCH($A67,Z$3),"") | AA67: =IFERROR(SEARCH($A67,AA$3),"") | AB67: =IFERROR(SEARCH($A67,AB$3),"") | AC67: =IFERROR(SEARCH($A67,AC$3),"") | AD67: =IFERROR(SEARCH($A67,AD$3),"") | AE67: =IFERROR(SEARCH($A67,AE$3),"") | ... BA67: =IFERROR(SEARCH($A67,BA$3),"") | BB67: =SUM(C67:BA67) -> 16 | BC67: =IFERROR(SEARCH($A67,BC$3),"") | BD67: =IFERROR(SEARCH($A67,BD$3),"") | BE67: =SUM(BC67:BD67) -> 0 | BF67: =BB67+BE67 -> 16
A68: ПК-1 | B68: =VLOOKUP(A68,Лист1!B:C,2,0) -> Способен выполнять комплекс услуг по транспортному обслуживанию грузоотправителей и грузополучателей при перевозке грузов, в том числе скоропортящихся, на основе принципов логистики с учетом эффективного и рационального взаимодействия видов транспорта, составляющих единую транспортную систему | C68: =IFERROR(IF(SEARCH($A68,C$3)<>0,1,""),"") | D68: =IFERROR(IF(SEARCH($A68,D$3)<>0,1,""),"") | E68: =IFERROR(IF(SEARCH($A68,E$3)<>0,1,""),"") | F68: =IFERROR(IF(SEARCH($A68,F$3)<>0,1,""),"") | G68: =IFERROR(IF(SEARCH($A68,G$3)<>0,1,""),"") | H68: =IFERROR(IF(SEARCH($A68,H$3)<>0,1,""),"") | I68: =IFERROR(IF(SEARCH($A68,I$3)<>0,1,""),"") | J68: =IFERROR(IF(SEARCH($A68,J$3)<>0,1,""),"") | K68: =IFERROR(IF(SEARCH($A68,K$3)<>0,1,""),"") | O68: =IFERROR(IF(SEARCH($A68,O$3)<>0,1,""),"") | P68: =IFERROR(IF(SEARCH($A68,P$3)<>0,1,""),"") | Q68: =IFERROR(IF(SEARCH($A68,Q$3)<>0,1,""),"") | R68: =IFERROR(IF(SEARCH($A68,R$3)<>0,1,""),"") | T68: =IFERROR(IF(SEARCH($A68,T$3)<>0,1,""),"") | U68: =IFERROR(IF(SEARCH($A68,U$3)<>0,1,""),"") | V68: =IFERROR(IF(SEARCH($A68,V$3)<>0,1,""),"") | W68: =IFERROR(IF(SEARCH($A68,W$3)<>0,1,""),"") | X68: =IFERROR(IF(SEARCH($A68,X$3)<>0,1,""),"") | Y68: =IFERROR(IF(SEARCH($A68,Y$3)<>0,1,""),"") | Z68: =IFERROR(IF(SEARCH($A68,Z$3)<>0,1,""),"") | AB68: =IFERROR(IF(SEARCH($A68,AB$3)<>0,1,""),"") | AC68: =IFERROR(IF(SEARCH($A68,AC$3)<>0,1,""),"") | AD68: =IFERROR(IF(SEARCH($A68,AD$3)<>0,1,""),"") | AE68: =IFERROR(IF(SEARCH($A68,AE$3)<>0,1,""),"") | AF68: 18 | AG68: =IFERROR(IF(SEARCH($A68,AG$3)<>0,1,""),"") | AH68: =IFERROR(IF(SEARCH($A68,AH$3)<>0,1,""),"") | AI68: =IFERROR(IF(SEARCH($A68,AI$3)<>0,1,""),"") | AJ68: =IFERROR(IF(SEARCH($A68,AJ$3)<>0,1,""),"") | AK68: =IFERROR(IF(SEARCH($A68,AK$3)<>0,1,""),"") | AL68: =IFERROR(IF(SEARCH($A68,AL$3)<>0,1,""),"") | AM68: =IFERROR(IF(SEARCH($A68,AM$3)<>0,1,""),"") | AN68: 18 | AO68: 18 | AP68: =IFERROR(IF(SEARCH($A68,AP$3)<>0,1,""),"") | AQ68: =IFERROR(IF(SEARCH($A68,AQ$3)<>0,1,""),"") | AR68: =IFERROR(IF(SEARCH($A68,AR$3)<>0,1,""),"") | AS68: =IFERROR(IF(SEARCH($A68,AS$3)<>0,1,""),"") | AT68: 18 | AU68: 18 | AV68: =IFERROR(IF(SEARCH($A68,AV$3)<>0,1,""),"") | AW68: =IFERROR(IF(SEARCH($A68,AW$3)<>0,1,""),"") | AX68: =IFERROR(IF(SEARCH($A68,AX$3)<>0,1,""),"") | AY68: 2 | AZ68: 2 | BA68: 2 | BB68: =SUM(C68:BA68) -> 96 | BC68: =IFERROR(SEARCH(_xlfn.CONCAT(" ",$A68),#REF!),"") | BD68: =IFERROR(SEARCH(_xlfn.CONCAT(" ",$A68),#REF!),"") | BE68: =SUM(BC68:BD68) -> 0 | BF68: =BB68+BE68 -> 96
A69: ПК-1.1 | B69: =VLOOKUP(A69,Лист1!B:C,2,0) -> Планирует работу предприятия транспортной отрасли по оказанию комплекса услуг грузовладельцам | C69: =IFERROR(SEARCH($A69,C$3),"") | D69: =IFERROR(SEARCH($A69,D$3),"") | E69: =IFERROR(SEARCH($A69,E$3),"") | F69: =IFERROR(SEARCH($A69,F$3),"") | G69: =IFERROR(SEARCH($A69,G$3),"") | H69: =IFERROR(SEARCH($A69,H$3),"") | I69: =IFERROR(SEARCH($A69,I$3),"") | J69: =IFERROR(SEARCH($A69,J$3),"") | K69: =IFERROR(SEARCH($A69,K$3),"") | O69: =IFERROR(SEARCH($A69,O$3),"") | P69: =IFERROR(SEARCH($A69,P$3),"") | Q69: =IFERROR(SEARCH($A69,Q$3),"") | R69: =IFERROR(SEARCH($A69,R$3),"") | S69: =IFERROR(SEARCH($A69,S$3),"") | T69: =IFERROR(SEARCH($A69,T$3),"") | U69: =IFERROR(SEARCH($A69,U$3),"") | V69: =IFERROR(SEARCH($A69,V$3),"") | ... AE69: =IFERROR(SEARCH($A69,AE$3),"") | AF69: 9 | AG69: =IFERROR(SEARCH($A69,AG$3),"") | AH69: =IFERROR(SEARCH($A69,AH$3),"") | AI69: =IFERROR(SEARCH($A69,AI$3),"") | AJ69: =IFERROR(SEARCH($A69,AJ$3),"") | AK69: =IFERROR(SEARCH($A69,AK$3),"") | AL69: =IFERROR(SEARCH($A69,AL$3),"") | AM69: =IFERROR(SEARCH($A69,AM$3),"") | AN69: =IFERROR(SEARCH($A69,AN$3),"") | ... BA69: =IFERROR(SEARCH($A69,BA$3),"") | BB69: =SUM(C69:BA69) -> 10 | BC69: =IFERROR(SEARCH($A69,BC$3),"") | BD69: =IFERROR(SEARCH($A69,BD$3),"") | BE69: =SUM(BC69:BD69) -> 0 | BF69: =BB69+BE69 -> 10
A70: ПК-1.2 | B70: =VLOOKUP(A70,Лист1!B:C,2,0) -> Идентифицирует и анализирует свойства грузов, характеристики подвижного состава, требования к размещению и креплению грузов в вагонах и контейнерах | C70: =IFERROR(SEARCH($A70,C$3),"") | D70: =IFERROR(SEARCH($A70,D$3),"") | E70: =IFERROR(SEARCH($A70,E$3),"") | F70: =IFERROR(SEARCH($A70,F$3),"") | G70: =IFERROR(SEARCH($A70,G$3),"") | H70: =IFERROR(SEARCH($A70,H$3),"") | I70: =IFERROR(SEARCH($A70,I$3),"") | J70: =IFERROR(SEARCH($A70,J$3),"") | K70: =IFERROR(SEARCH($A70,K$3),"") | O70: =IFERROR(SEARCH($A70,O$3),"") | P70: =IFERROR(SEARCH($A70,P$3),"") | Q70: =IFERROR(SEARCH($A70,Q$3),"") | R70: =IFERROR(SEARCH($A70,R$3),"") | S70: =IFERROR(SEARCH($A70,S$3),"") | T70: =IFERROR(SEARCH($A70,T$3),"") | U70: =IFERROR(SEARCH($A70,U$3),"") | V70: =IFERROR(SEARCH($A70,V$3),"") | ... AX70: =IFERROR(SEARCH($A70,AX$3),"") | AY70: 2 | AZ70: =IFERROR(SEARCH($A70,AZ$3),"") | BA70: =IFERROR(SEARCH($A70,BA$3),"") | BB70: =SUM(C70:BA70) -> 11 | BC70: =IFERROR(SEARCH($A70,BC$3),"") | BD70: =IFERROR(SEARCH($A70,BD$3),"") | BE70: =SUM(BC70:BD70) -> 0 | BF70: =BB70+BE70 -> 11
A71: ПК-1.3 | B71: =VLOOKUP(A71,Лист1!B:C,2,0) -> Определяет перечень транспортных услуг, связанных с перевозкой скоропортящихся грузов | C71: =IFERROR(SEARCH($A71,C$3),"") | D71: =IFERROR(SEARCH($A71,D$3),"") | E71: =IFERROR(SEARCH($A71,E$3),"") | F71: =IFERROR(SEARCH($A71,F$3),"") | G71: =IFERROR(SEARCH($A71,G$3),"") | H71: =IFERROR(SEARCH($A71,H$3),"") | I71: =IFERROR(SEARCH($A71,I$3),"") | J71: =IFERROR(SEARCH($A71,J$3),"") | K71: =IFERROR(SEARCH($A71,K$3),"") | O71: =IFERROR(SEARCH($A71,O$3),"") | P71: =IFERROR(SEARCH($A71,P$3),"") | Q71: =IFERROR(SEARCH($A71,Q$3),"") | R71: =IFERROR(SEARCH($A71,R$3),"") | S71: =IFERROR(SEARCH($A71,S$3),"") | T71: =IFERROR(SEARCH($A71,T$3),"") | U71: =IFERROR(SEARCH($A71,U$3),"") | V71: =IFERROR(SEARCH($A71,V$3),"") | ... AM71: =IFERROR(SEARCH($A71,AM$3),"") | AN71: 18 | AO71: 18 | AP71: =IFERROR(SEARCH($A71,AP$3),"") | AQ71: =IFERROR(SEARCH($A71,AQ$3),"") | AR71: =IFERROR(SEARCH($A71,AR$3),"") | AS71: =IFERROR(SEARCH($A71,AS$3),"") | AT71: =IFERROR(SEARCH($A71,AT$3),"") | AU71: =IFERROR(SEARCH($A71,AU$3),"") | AV71: =IFERROR(SEARCH($A71,AV$3),"") | AW71: =IFERROR(SEARCH($A71,AW$3),"") | ... AY71: =IFERROR(SEARCH($A71,AY$3),"") | AZ71: 1 | BA71: =IFERROR(SEARCH($A71,BA$3),"") | BB71: =SUM(C71:BA71) -> 37 | BC71: =IFERROR(SEARCH($A71,BC$3),"") | BD71: =IFERROR(SEARCH($A71,BD$3),"") | BE71: =SUM(BC71:BD71) -> 0 | BF71: =BB71+BE71 -> 37
A72: ПК-1.4 | B72: =VLOOKUP(A72,Лист1!B:C,2,0) -> Разрабатывает комплекс услуг по транспортно-логистическому обслуживанию для эффективной мультимодальной перевозки грузов | C72: =IFERROR(SEARCH($A72,C$3),"") | D72: =IFERROR(SEARCH($A72,D$3),"") | E72: =IFERROR(SEARCH($A72,E$3),"") | F72: =IFERROR(SEARCH($A72,F$3),"") | G72: =IFERROR(SEARCH($A72,G$3),"") | H72: =IFERROR(SEARCH($A72,H$3),"") | I72: =IFERROR(SEARCH($A72,I$3),"") | J72: =IFERROR(SEARCH($A72,J$3),"") | ... R72: =IFERROR(SEARCH($A72,R$3),"") | T72: =IFERROR(SEARCH($A72,T$3),"") | U72: =IFERROR(SEARCH($A72,U$3),"") | V72: =IFERROR(SEARCH($A72,V$3),"") | W72: =IFERROR(SEARCH($A72,W$3),"") | X72: =IFERROR(SEARCH($A72,X$3),"") | Y72: =IFERROR(SEARCH($A72,Y$3),"") | Z72: =IFERROR(SEARCH($A72,Z$3),"") | AA72: =IFERROR(SEARCH($A72,AA$3),"") | ... AS72: =IFERROR(SEARCH($A72,AS$3),"") | AT72: 18 | AU72: 18 | AV72: =IFERROR(SEARCH($A72,AV$3),"") | AW72: =IFERROR(SEARCH($A72,AW$3),"") | AX72: =IFERROR(SEARCH($A72,AX$3),"") | AY72: =IFERROR(SEARCH($A72,AY$3),"") | AZ72: =IFERROR(SEARCH($A72,AZ$3),"") | BA72: 2 | BB72: =SUM(C72:BA72) -> 38 | BC72: =IFERROR(SEARCH($A72,BC$3),"") | BD72: =IFERROR(SEARCH($A72,BD$3),"") | BE72: =SUM(BC72:BD72) -> 0 | BF72: =BB72+BE72 -> 38
A73: ПК-2 | B73: =VLOOKUP(A73,Лист1!B:C,2,0) -> Способен осуществлять контроль и управление перевозочным процессом, оперативное планирование и управление эксплуатационной работой с учетом технического состояния, контроль безопасности движения и эксплуатации на железнодорожном транспорте | C73: =IFERROR(IF(SEARCH($A73,C$3)<>0,1,""),"") | D73: =IFERROR(IF(SEARCH($A73,D$3)<>0,1,""),"") | E73: =IFERROR(IF(SEARCH($A73,E$3)<>0,1,""),"") | F73: =IFERROR(IF(SEARCH($A73,F$3)<>0,1,""),"") | G73: =IFERROR(IF(SEARCH($A73,G$3)<>0,1,""),"") | H73: =IFERROR(IF(SEARCH($A73,H$3)<>0,1,""),"") | I73: =IFERROR(IF(SEARCH($A73,I$3)<>0,1,""),"") | J73: =IFERROR(IF(SEARCH($A73,J$3)<>0,1,""),"") | ... S73: =IFERROR(IF(SEARCH($A73,S$3)<>0,1,""),"") | W73: =IFERROR(IF(SEARCH($A73,W$3)<>0,1,""),"") | Y73: =IFERROR(IF(SEARCH($A73,Y$3)<>0,1,""),"") | Z73: =IFERROR(IF(SEARCH($A73,Z$3)<>0,1,""),"") | AA73: =IFERROR(IF(SEARCH($A73,AA$3)<>0,1,""),"") | AB73: =IFERROR(IF(SEARCH($A73,AB$3)<>0,1,""),"") | AC73: =IFERROR(IF(SEARCH($A73,AC$3)<>0,1,""),"") | AD73: =IFERROR(IF(SEARCH($A73,AD$3)<>0,1,""),"") | AE73: =IFERROR(IF(SEARCH($A73,AE$3)<>0,1,""),"") | AF73: =IFERROR(IF(SEARCH($A73,AF$3)<>0,1,""),"") | ... AH73: =IFERROR(IF(SEARCH($A73,AH$3)<>0,1,""),"") | AI73: 18 | AJ73: =IFERROR(IF(SEARCH($A73,AJ$3)<>0,1,""),"") | AK73: 18 | AL73: =IFERROR(IF(SEARCH($A73,AL$3)<>0,1,""),"") | AM73: 18 | AN73: =IFERROR(IF(SEARCH($A73,AN$3)<>0,1,""),"") | AO73: =IFERROR(IF(SEARCH($A73,AO$3)<>0,1,""),"") | AP73: =IFERROR(IF(SEARCH($A73,AP$3)<>0,1,""),"") | AQ73: =IFERROR(IF(SEARCH($A73,AQ$3)<>0,1,""),"") | AR73: =IFERROR(IF(SEARCH($A73,AR$3)<>0,1,""),"") | AS73: =IFERROR(IF(SEARCH($A73,AS$3)<>0,1,""),"") | AT73: =IFERROR(IF(SEARCH($A73,AT$3)<>0,1,""),"") | AU73: =IFERROR(IF(SEARCH($A73,AU$3)<>0,1,""),"") | ... AX73: =IFERROR(IF(SEARCH($A73,AX$3)<>0,1,""),"") | AY73: 2 | AZ73: 2 | BA73: 2 | BB73: =SUM(C73:BA73) -> 60 | BE73: =SUM(BC73:BD73) -> 0 | BF73: =BB73+BE73 -> 60
A74: ПК-2.1 | B74: =VLOOKUP(A74,Лист1!B:C,2,0) -> Осуществляет оперативное планирование, управление, контроль перевозочного процесса с учетом технического состояния и безопасности | C74: =IFERROR(SEARCH($A74,C$3),"") | D74: =IFERROR(SEARCH($A74,D$3),"") | E74: =IFERROR(SEARCH($A74,E$3),"") | F74: =IFERROR(SEARCH($A74,F$3),"") | G74: =IFERROR(SEARCH($A74,G$3),"") | H74: =IFERROR(SEARCH($A74,H$3),"") | I74: =IFERROR(SEARCH($A74,I$3),"") | J74: =IFERROR(SEARCH($A74,J$3),"") | ... S74: =IFERROR(SEARCH($A74,S$3),"") | AI74: =IFERROR(SEARCH($A74,AI$3),"") | AJ74: =IFERROR(SEARCH($A74,AJ$3),"") | AK74: 18 | AL74: =IFERROR(SEARCH($A74,AL$3),"") | AM74: =IFERROR(SEARCH($A74,AM$3),"") | AN74: =IFERROR(SEARCH($A74,AN$3),"") | AO74: =IFERROR(SEARCH($A74,AO$3),"") | AP74: =IFERROR(SEARCH($A74,AP$3),"") | AQ74: =IFERROR(SEARCH($A74,AQ$3),"") | AR74: =IFERROR(SEARCH($A74,AR$3),"") | AS74: =IFERROR(SEARCH($A74,AS$3),"") | ... AX74: =IFERROR(SEARCH($A74,AX$3),"") | AY74: 2 | AZ74: =IFERROR(SEARCH($A74,AZ$3),"") | BA74: =IFERROR(SEARCH($A74,BA$3),"") | BB74: =SUM(C74:BA74) -> 20 | BC74: =IFERROR(SEARCH($A74,BC$3),"") | BD74: =IFERROR(SEARCH($A74,BD$3),"") | BE74: =SUM(BC74:BD74) -> 0 | BF74: =BB74+BE74 -> 20
A75: ПК-2.2 | B75: =VLOOKUP(A75,Лист1!B:C,2,0) -> Использует технические средства для обеспечения безопасности на железнодорожном транспорте | C75: =IFERROR(SEARCH($A75,C$3),"") | D75: =IFERROR(SEARCH($A75,D$3),"") | E75: =IFERROR(SEARCH($A75,E$3),"") | F75: =IFERROR(SEARCH($A75,F$3),"") | G75: =IFERROR(SEARCH($A75,G$3),"") | H75: =IFERROR(SEARCH($A75,H$3),"") | I75: =IFERROR(SEARCH($A75,I$3),"") | J75: =IFERROR(SEARCH($A75,J$3),"") | ... S75: =IFERROR(SEARCH($A75,S$3),"") | AI75: =IFERROR(SEARCH($A75,AI$3),"") | AJ75: =IFERROR(SEARCH($A75,AJ$3),"") | AK75: =IFERROR(SEARCH($A75,AK$3),"") | AL75: =IFERROR(SEARCH($A75,AL$3),"") | AM75: 9 | AN75: =IFERROR(SEARCH($A75,AN$3),"") | AO75: =IFERROR(SEARCH($A75,AO$3),"") | AP75: =IFERROR(SEARCH($A75,AP$3),"") | AQ75: =IFERROR(SEARCH($A75,AQ$3),"") | AR75: =IFERROR(SEARCH($A75,AR$3),"") | AS75: =IFERROR(SEARCH($A75,AS$3),"") | AT75: =IFERROR(SEARCH($A75,AT$3),"") | AU75: =IFERROR(SEARCH($A75,AU$3),"") | ... AZ75: =IFERROR(SEARCH($A75,AZ$3),"") | BA75: 1 | BB75: =SUM(C75:BA75) -> 10 | BC75: =IFERROR(SEARCH($A75,BC$3),"") | BD75: =IFERROR(SEARCH($A75,BD$3),"") | BE75: =SUM(BC75:BD75) -> 0 | BF75: =BB75+BE75 -> 10
A76: ПК-2.3 | B76: =VLOOKUP(A76,Лист1!B:C,2,0) -> Определяет последовательность действий в соответствии с правилами технической эксплуатации и требованиями техники безопасности при организации и проведении работ | C76: =IFERROR(SEARCH($A76,C$3),"") | D76: =IFERROR(SEARCH($A76,D$3),"") | E76: =IFERROR(SEARCH($A76,E$3),"") | F76: =IFERROR(SEARCH($A76,F$3),"") | G76: =IFERROR(SEARCH($A76,G$3),"") | H76: =IFERROR(SEARCH($A76,H$3),"") | I76: =IFERROR(SEARCH($A76,I$3),"") | J76: =IFERROR(SEARCH($A76,J$3),"") | ... S76: =IFERROR(SEARCH($A76,S$3),"") | AI76: =IFERROR(SEARCH($A76,AI$3),"") | AJ76: =IFERROR(SEARCH($A76,AJ$3),"") | AK76: =IFERROR(SEARCH($A76,AK$3),"") | AL76: =IFERROR(SEARCH($A76,AL$3),"") | AM76: =IFERROR(SEARCH($A76,AM$3),"") -> 9 | AN76: =IFERROR(SEARCH($A76,AN$3),"") | AO76: =IFERROR(SEARCH($A76,AO$3),"") | AP76: =IFERROR(SEARCH($A76,AP$3),"") | ... AZ76: =IFERROR(SEARCH($A76,AZ$3),"") | BA76: 1 | BB76: =SUM(C76:BA76) -> 10 | BC76: =IFERROR(SEARCH($A76,BC$3),"") | BD76: =IFERROR(SEARCH($A76,BD$3),"") | BE76: =SUM(BC76:BD76) -> 0 | BF76: =BB76+BE76 -> 10
A77: ПК-2.4 | B77: =VLOOKUP(A77,Лист1!B:C,2,0) -> Осуществляет контроль и управление движением поездов, принимает решения по организации движения поездов по участку в изменяющейся поездной обстановке | C77: =IFERROR(SEARCH($A77,C$3),"") | D77: =IFERROR(SEARCH($A77,D$3),"") | E77: =IFERROR(SEARCH($A77,E$3),"") | F77: =IFERROR(SEARCH($A77,F$3),"") | G77: =IFERROR(SEARCH($A77,G$3),"") | H77: =IFERROR(SEARCH($A77,H$3),"") | I77: =IFERROR(SEARCH($A77,I$3),"") | J77: =IFERROR(SEARCH($A77,J$3),"") | ... S77: =IFERROR(SEARCH($A77,S$3),"") | AI77: 18 | AJ77: =IFERROR(SEARCH($A77,AJ$3),"") | AK77: =IFERROR(SEARCH($A77,AK$3),"") | AL77: =IFERROR(SEARCH($A77,AL$3),"") | AM77: =IFERROR(SEARCH($A77,AM$3),"") | AN77: =IFERROR(SEARCH($A77,AN$3),"") | AO77: =IFERROR(SEARCH($A77,AO$3),"") | AP77: =IFERROR(SEARCH($A77,AP$3),"") | AQ77: =IFERROR(SEARCH($A77,AQ$3),"") | ... AY77: =IFERROR(SEARCH($A77,AY$3),"") | AZ77: 2 | BA77: =IFERROR(SEARCH($A77,BA$3),"") | BB77: =SUM(C77:BA77) -> 20 | BC77: =IFERROR(SEARCH($A77,BC$3),"") | BD77: =IFERROR(SEARCH($A77,BD$3),"") | BE77: =SUM(BC77:BD77) -> 0 | BF77: =BB77+BE77 -> 20
A78: ПК-3 | B78: =VLOOKUP(A78,Лист1!B:C,2,0) -> Способен проектировать железнодорожные линии, станции и узлы, разрабатывать и корректировать нормативную технологическую документацию с учетом технического оснащения и перспективного развития объектов железнодорожной инфраструктуры | C78: =IFERROR(IF(SEARCH($A78,C$3)<>0,1,""),"") | D78: =IFERROR(IF(SEARCH($A78,D$3)<>0,1,""),"") | E78: =IFERROR(IF(SEARCH($A78,E$3)<>0,1,""),"") | F78: =IFERROR(IF(SEARCH($A78,F$3)<>0,1,""),"") | G78: =IFERROR(IF(SEARCH($A78,G$3)<>0,1,""),"") | H78: =IFERROR(IF(SEARCH($A78,H$3)<>0,1,""),"") | I78: =IFERROR(IF(SEARCH($A78,I$3)<>0,1,""),"") | J78: =IFERROR(IF(SEARCH($A78,J$3)<>0,1,""),"") | ... V78: =IFERROR(IF(SEARCH($A78,V$3)<>0,1,""),"") | X78: =IFERROR(IF(SEARCH($A78,X$3)<>0,1,""),"") | Y78: =IFERROR(IF(SEARCH($A78,Y$3)<>0,1,""),"") | Z78: =IFERROR(IF(SEARCH($A78,Z$3)<>0,1,""),"") | AA78: =IFERROR(IF(SEARCH($A78,AA$3)<>0,1,""),"") | AB78: =IFERROR(IF(SEARCH($A78,AB$3)<>0,1,""),"") | AC78: =IFERROR(IF(SEARCH($A78,AC$3)<>0,1,""),"") | AD78: =IFERROR(IF(SEARCH($A78,AD$3)<>0,1,""),"") | AE78: =IFERROR(IF(SEARCH($A78,AE$3)<>0,1,""),"") | ... AI78: =IFERROR(IF(SEARCH($A78,AI$3)<>0,1,""),"") | AJ78: 18 | AK78: =IFERROR(IF(SEARCH($A78,AK$3)<>0,1,""),"") | AL78: =IFERROR(IF(SEARCH($A78,AL$3)<>0,1,""),"") | AM78: =IFERROR(IF(SEARCH($A78,AM$3)<>0,1,""),"") | AN78: =IFERROR(IF(SEARCH($A78,AN$3)<>0,1,""),"") | AO78: =IFERROR(IF(SEARCH($A78,AO$3)<>0,1,""),"") | AP78: =IFERROR(IF(SEARCH($A78,AP$3)<>0,1,""),"") | AQ78: =IFERROR(IF(SEARCH($A78,AQ$3)<>0,1,""),"") | AR78: =IFERROR(IF(SEARCH($A78,AR$3)<>0,1,""),"") | ... AX78: =IFERROR(IF(SEARCH($A78,AX$3)<>0,1,""),"") | AY78: 2 | AZ78: =IFERROR(IF(SEARCH($A78,AZ$3)<>0,1,""),"") | BA78: =IFERROR(IF(SEARCH($A78,BA$3)<>0,1,""),"") | BB78: =SUM(C78:BA78) -> 20 | BC78: =IFERROR(SEARCH(_xlfn.CONCAT(" ",$A78),#REF!),"") | BD78: =IFERROR(SEARCH(_xlfn.CONCAT(" ",$A78),#REF!),"") | BE78: =SUM(BC78:BD78) -> 0 | BF78: =BB78+BE78 -> 20
A79: ПК-3.1 | B79: =VLOOKUP(A79,Лист1!B:C,2,0) -> Использует техническую и нормативную документацию по проектированию объектов транспортной инфраструктуры, устройств и технического оснащения раздельных пунктов и транспортных узлов; методы расчета основных элементов; способы увязки проектных решений с передовой технологией работы станций и железнодорожных узлов; методы выполнения технико-экономических расчетов по выбору наиболее эффективных решений | C79: =IFERROR(SEARCH($A79,C$3),"") | D79: =IFERROR(SEARCH($A79,D$3),"") | E79: =IFERROR(SEARCH($A79,E$3),"") | F79: =IFERROR(SEARCH($A79,F$3),"") | G79: =IFERROR(SEARCH($A79,G$3),"") | H79: =IFERROR(SEARCH($A79,H$3),"") | I79: =IFERROR(SEARCH($A79,I$3),"") | J79: =IFERROR(SEARCH($A79,J$3),"") | ... V79: =IFERROR(SEARCH($A79,V$3),"") | X79: =IFERROR(SEARCH($A79,X$3),"") | Y79: =IFERROR(SEARCH($A79,Y$3),"") | Z79: =IFERROR(SEARCH($A79,Z$3),"") | AA79: =IFERROR(SEARCH($A79,AA$3),"") | AB79: =IFERROR(SEARCH($A79,AB$3),"") | AC79: =IFERROR(SEARCH($A79,AC$3),"") | AD79: =IFERROR(SEARCH($A79,AD$3),"") | AE79: =IFERROR(SEARCH($A79,AE$3),"") | ... AI79: =IFERROR(SEARCH($A79,AI$3),"") | AJ79: 9 | AK79: =IFERROR(SEARCH($A79,AK$3),"") | AL79: =IFERROR(SEARCH($A79,AL$3),"") | AM79: =IFERROR(SEARCH($A79,AM$3),"") | AN79: =IFERROR(SEARCH($A79,AN$3),"") | AO79: =IFERROR(SEARCH($A79,AO$3),"") | AP79: =IFERROR(SEARCH($A79,AP$3),"") | AQ79: =IFERROR(SEARCH($A79,AQ$3),"") | AR79: =IFERROR(SEARCH($A79,AR$3),"") | ... AX79: =IFERROR(SEARCH($A79,AX$3),"") | AY79: 1 | AZ79: =IFERROR(SEARCH($A79,AZ$3),"") | BA79: =IFERROR(SEARCH($A79,BA$3),"") | BB79: =SUM(C79:BA79) -> 10 | BC79: =IFERROR(SEARCH($A79,BC$3),"") | BD79: =IFERROR(SEARCH($A79,BD$3),"") | BE79: =SUM(BC79:BD79) -> 0 | BF79: =BB79+BE79 -> 10
A80: ПК-3.2 | B80: =VLOOKUP(A80,Лист1!B:C,2,0) -> Использует методы технико-экономического обоснования при принятии решения о необходимости развития железнодорожной станции и узла; проектирования и расчетов, включая применение автоматизированного проектирования | C80: =IFERROR(SEARCH($A80,C$3),"") | D80: =IFERROR(SEARCH($A80,D$3),"") | E80: =IFERROR(SEARCH($A80,E$3),"") | F80: =IFERROR(SEARCH($A80,F$3),"") | G80: =IFERROR(SEARCH($A80,G$3),"") | H80: =IFERROR(SEARCH($A80,H$3),"") | I80: =IFERROR(SEARCH($A80,I$3),"") | J80: =IFERROR(SEARCH($A80,J$3),"") | ... V80: =IFERROR(SEARCH($A80,V$3),"") | X80: =IFERROR(SEARCH($A80,X$3),"") | Y80: =IFERROR(SEARCH($A80,Y$3),"") | Z80: =IFERROR(SEARCH($A80,Z$3),"") | AA80: =IFERROR(SEARCH($A80,AA$3),"") | AB80: =IFERROR(SEARCH($A80,AB$3),"") | AC80: =IFERROR(SEARCH($A80,AC$3),"") | AD80: =IFERROR(SEARCH($A80,AD$3),"") | AE80: =IFERROR(SEARCH($A80,AE$3),"") | ... AX80: =IFERROR(SEARCH($A80,AX$3),"") | AY80: 1 | AZ80: =IFERROR(SEARCH($A80,AZ$3),"") | BA80: =IFERROR(SEARCH($A80,BA$3),"") | BB80: =SUM(C80:BA80) -> 10 | BC80: =IFERROR(SEARCH($A80,BC$3),"") | BD80: =IFERROR(SEARCH($A80,BD$3),"") | BE80: =SUM(BC80:BD80) -> 0 | BF80: =BB80+BE80 -> 10
A81: ПК-4 | B81: =VLOOKUP(A81,Лист1!B:C,2,0) -> Способен осуществлять организацию работы с подрядчиками на рынке транспортных услуг | C81: =IFERROR(IF(SEARCH($A81,C$3)<>0,1,""),"") | D81: =IFERROR(IF(SEARCH($A81,D$3)<>0,1,""),"") | E81: =IFERROR(IF(SEARCH($A81,E$3)<>0,1,""),"") | F81: =IFERROR(IF(SEARCH($A81,F$3)<>0,1,""),"") | G81: =IFERROR(IF(SEARCH($A81,G$3)<>0,1,""),"") | J81: =IFERROR(IF(SEARCH($A81,J$3)<>0,1,""),"") | K81: =IFERROR(IF(SEARCH($A81,K$3)<>0,1,""),"") | L81: =IFERROR(IF(SEARCH($A81,L$3)<>0,1,""),"") | M81: =IFERROR(IF(SEARCH($A81,M$3)<>0,1,""),"") | N81: =IFERROR(IF(SEARCH($A81,N$3)<>0,1,""),"") | O81: =IFERROR(IF(SEARCH($A81,O$3)<>0,1,""),"") | Q81: =IFERROR(IF(SEARCH($A81,Q$3)<>0,1,""),"") | R81: =IFERROR(IF(SEARCH($A81,R$3)<>0,1,""),"") | S81: =IFERROR(IF(SEARCH($A81,S$3)<>0,1,""),"") | T81: =IFERROR(IF(SEARCH($A81,T$3)<>0,1,""),"") | U81: =IFERROR(IF(SEARCH($A81,U$3)<>0,1,""),"") | V81: =IFERROR(IF(SEARCH($A81,V$3)<>0,1,""),"") | W81: =IFERROR(IF(SEARCH($A81,W$3)<>0,1,""),"") | X81: =IFERROR(IF(SEARCH($A81,X$3)<>0,1,""),"") | AA81: =IFERROR(IF(SEARCH($A81,AA$3)<>0,1,""),"") | AB81: =IFERROR(IF(SEARCH($A81,AB$3)<>0,1,""),"") | AC81: =IFERROR(IF(SEARCH($A81,AC$3)<>0,1,""),"") | AD81: =IFERROR(IF(SEARCH($A81,AD$3)<>0,1,""),"") | AE81: =IFERROR(IF(SEARCH($A81,AE$3)<>0,1,""),"") | AF81: =IFERROR(IF(SEARCH($A81,AF$3)<>0,1,""),"") | AG81: =IFERROR(IF(SEARCH($A81,AG$3)<>0,1,""),"") | AH81: 18 | AI81: =IFERROR(IF(SEARCH($A81,AI$3)<>0,1,""),"") | AJ81: =IFERROR(IF(SEARCH($A81,AJ$3)<>0,1,""),"") | AK81: =IFERROR(IF(SEARCH($A81,AK$3)<>0,1,""),"") | AL81: =IFERROR(IF(SEARCH($A81,AL$3)<>0,1,""),"") | AM81: =IFERROR(IF(SEARCH($A81,AM$3)<>0,1,""),"") | AN81: =IFERROR(IF(SEARCH($A81,AN$3)<>0,1,""),"") | AO81: =IFERROR(IF(SEARCH($A81,AO$3)<>0,1,""),"") | AP81: 18 | AQ81: 18 | AR81: =IFERROR(IF(SEARCH($A81,AR$3)<>0,1,""),"") | AS81: =IFERROR(IF(SEARCH($A81,AS$3)<>0,1,""),"") | AT81: =IFERROR(IF(SEARCH($A81,AT$3)<>0,1,""),"") | AU81: =IFERROR(IF(SEARCH($A81,AU$3)<>0,1,""),"") | AV81: 18 | AW81: 18 | AX81: =IFERROR(IF(SEARCH($A81,AX$3)<>0,1,""),"") | AY81: =IFERROR(IF(SEARCH($A81,AY$3)<>0,1,""),"") | AZ81: 2 | BA81: 2 | BB81: =SUM(C81:BA81) -> 94 | BC81: =IFERROR(SEARCH(_xlfn.CONCAT(" ",$A81),#REF!),"") | BD81: =IFERROR(SEARCH(_xlfn.CONCAT(" ",$A81),#REF!),"") | BE81: =SUM(BC81:BD81) -> 0 | BF81: =BB81+BE81 -> 94
A82: ПК-4.1 | B82: =VLOOKUP(A82,Лист1!B:C,2,0) -> Решает задачи по организации работы экспедиторских фирм, оформляет необходимые документы для заключения договоров с юридическими и физическими лицами на транспортно-экспедиционное обслуживание грузовладельцев | C82: =IFERROR(SEARCH($A82,C$3),"") | D82: =IFERROR(SEARCH($A82,D$3),"") | E82: =IFERROR(SEARCH($A82,E$3),"") | F82: =IFERROR(SEARCH($A82,F$3),"") | G82: =IFERROR(SEARCH($A82,G$3),"") | J82: =IFERROR(SEARCH($A82,J$3),"") | K82: =IFERROR(SEARCH($A82,K$3),"") | L82: =IFERROR(SEARCH($A82,L$3),"") | M82: =IFERROR(SEARCH($A82,M$3),"") | N82: =IFERROR(SEARCH($A82,N$3),"") | O82: =IFERROR(SEARCH($A82,O$3),"") | P82: =IFERROR(SEARCH($A82,P$3),"") | Q82: =IFERROR(SEARCH($A82,Q$3),"") | ... X82: =IFERROR(SEARCH($A82,X$3),"") | AA82: =IFERROR(SEARCH($A82,AA$3),"") | AB82: =IFERROR(SEARCH($A82,AB$3),"") | AC82: =IFERROR(SEARCH($A82,AC$3),"") | AD82: =IFERROR(SEARCH($A82,AD$3),"") | AE82: =IFERROR(SEARCH($A82,AE$3),"") | AF82: =IFERROR(SEARCH($A82,AF$3),"") | AG82: =IFERROR(SEARCH($A82,AG$3),"") | AH82: =IFERROR(SEARCH($A82,AH$3),"") | ... AU82: =IFERROR(SEARCH($A82,AU$3),"") | AV82: 18 | AW82: 18 | AX82: =IFERROR(SEARCH($A82,AX$3),"") | AY82: =IFERROR(SEARCH($A82,AY$3),"") | AZ82: 1 | BA82: =IFERROR(SEARCH($A82,BA$3),"") | BB82: =SUM(C82:BA82) -> 37 | BC82: =IFERROR(SEARCH($A82,BC$3),"") | BD82: =IFERROR(SEARCH($A82,BD$3),"") | BE82: =SUM(BC82:BD82) -> 0 | BF82: =BB82+BE82 -> 37
A83: ПК-4.2 | B83: =VLOOKUP(A83,Лист1!B:C,2,0) -> Разрабатывает эффективные схемы взаимоотношения промышленного и магистрального транспорта в процессе оказания логистической услуги перевозки груза в цепи поставок | C83: =IFERROR(SEARCH($A83,C$3),"") | D83: =IFERROR(SEARCH($A83,D$3),"") | E83: =IFERROR(SEARCH($A83,E$3),"") | F83: =IFERROR(SEARCH($A83,F$3),"") | G83: =IFERROR(SEARCH($A83,G$3),"") | J83: =IFERROR(SEARCH($A83,J$3),"") | K83: =IFERROR(SEARCH($A83,K$3),"") | L83: =IFERROR(SEARCH($A83,L$3),"") | M83: =IFERROR(SEARCH($A83,M$3),"") | N83: =IFERROR(SEARCH($A83,N$3),"") | O83: =IFERROR(SEARCH($A83,O$3),"") | P83: =IFERROR(SEARCH($A83,P$3),"") | Q83: =IFERROR(SEARCH($A83,Q$3),"") | ... X83: =IFERROR(SEARCH($A83,X$3),"") | AA83: =IFERROR(SEARCH($A83,AA$3),"") | AB83: =IFERROR(SEARCH($A83,AB$3),"") | AC83: =IFERROR(SEARCH($A83,AC$3),"") | AD83: =IFERROR(SEARCH($A83,AD$3),"") | AE83: =IFERROR(SEARCH($A83,AE$3),"") | AF83: =IFERROR(SEARCH($A83,AF$3),"") | AG83: =IFERROR(SEARCH($A83,AG$3),"") | AH83: 18 | AI83: =IFERROR(SEARCH($A83,AI$3),"") | AJ83: =IFERROR(SEARCH($A83,AJ$3),"") | AK83: =IFERROR(SEARCH($A83,AK$3),"") | AL83: =IFERROR(SEARCH($A83,AL$3),"") | AM83: =IFERROR(SEARCH($A83,AM$3),"") | AN83: =IFERROR(SEARCH($A83,AN$3),"") | AO83: =IFERROR(SEARCH($A83,AO$3),"") | AP83: =IFERROR(SEARCH($A83,AP$3),"") | ... AZ83: =IFERROR(SEARCH($A83,AZ$3),"") | BA83: 1 | BB83: =SUM(C83:BA83) -> 19 | BC83: =IFERROR(SEARCH($A83,BC$3),"") | BD83: =IFERROR(SEARCH($A83,BD$3),"") | BE83: =SUM(BC83:BD83) -> 0 | BF83: =BB83+BE83 -> 19
A84: ПК-4.3 | B84: =VLOOKUP(A84,Лист1!B:C,2,0) -> Анализирует информацию о планируемых мероприятиях, разрабатывает эффективные схемы взаимоотношений в процессе оказания логистической услуги перевозки груза, организует планирование услуг, этапов, сроков доставки | C84: =IFERROR(SEARCH($A84,C$3),"") | D84: =IFERROR(SEARCH($A84,D$3),"") | E84: =IFERROR(SEARCH($A84,E$3),"") | F84: =IFERROR(SEARCH($A84,F$3),"") | G84: =IFERROR(SEARCH($A84,G$3),"") | H84: =IFERROR(SEARCH($A84,H$3),"") | I84: =IFERROR(SEARCH($A84,I$3),"") | J84: =IFERROR(SEARCH($A84,J$3),"") | ... X84: =IFERROR(SEARCH($A84,X$3),"") | AA84: =IFERROR(SEARCH($A84,AA$3),"") | AB84: =IFERROR(SEARCH($A84,AB$3),"") | AC84: =IFERROR(SEARCH($A84,AC$3),"") | AD84: =IFERROR(SEARCH($A84,AD$3),"") | AE84: =IFERROR(SEARCH($A84,AE$3),"") | AF84: =IFERROR(SEARCH($A84,AF$3),"") | AG84: =IFERROR(SEARCH($A84,AG$3),"") | AH84: =IFERROR(SEARCH($A84,AH$3),"") | ... AO84: =IFERROR(SEARCH($A84,AO$3),"") | AP84: 9 | AQ84: 9 | AR84: =IFERROR(SEARCH($A84,AR$3),"") | AS84: =IFERROR(SEARCH($A84,AS$3),"") | AT84: =IFERROR(SEARCH($A84,AT$3),"") | AU84: =IFERROR(SEARCH($A84,AU$3),"") | AV84: =IFERROR(SEARCH($A84,AV$3),"") | AW84: =IFERROR(SEARCH($A84,AW$3),"") | AX84: =IFERROR(SEARCH($A84,AX$3),"") | AY84: =IFERROR(SEARCH($A84,AY$3),"") | AZ84: =IFERROR(SEARCH($A84,AZ$3),"") | BA84: 1 | BB84: =SUM(C84:BA84) -> 19 | BC84: =IFERROR(SEARCH($A84,BC$3),"") | BD84: =IFERROR(SEARCH($A84,BD$3),"") | BE84: =SUM(BC84:BD84) -> 0 | BF84: =BB84+BE84 -> 19
A85: ПК-4.4 | B85: =VLOOKUP(A85,Лист1!B:C,2,0) -> Определяет перечень необходимых услуг на транспортном рынке, выбирает подрядчика на основе критериального анализа, проверяет договор на содержание, полноту и соответствие услуг, организует работу с подрядчиками на рынке транспортных услуг | C85: =IFERROR(SEARCH($A85,C$3),"") | D85: =IFERROR(SEARCH($A85,D$3),"") | E85: =IFERROR(SEARCH($A85,E$3),"") | F85: =IFERROR(SEARCH($A85,F$3),"") | G85: =IFERROR(SEARCH($A85,G$3),"") | H85: =IFERROR(SEARCH($A85,H$3),"") | I85: =IFERROR(SEARCH($A85,I$3),"") | J85: =IFERROR(SEARCH($A85,J$3),"") | ... X85: =IFERROR(SEARCH($A85,X$3),"") | AA85: =IFERROR(SEARCH($A85,AA$3),"") | AB85: =IFERROR(SEARCH($A85,AB$3),"") | AC85: =IFERROR(SEARCH($A85,AC$3),"") | AD85: =IFERROR(SEARCH($A85,AD$3),"") | AE85: =IFERROR(SEARCH($A85,AE$3),"") | AF85: =IFERROR(SEARCH($A85,AF$3),"") | AG85: =IFERROR(SEARCH($A85,AG$3),"") | AH85: =IFERROR(SEARCH($A85,AH$3),"") | ... AY85: =IFERROR(SEARCH($A85,AY$3),"") | AZ85: 1 | BA85: =IFERROR(SEARCH($A85,BA$3),"") | BB85: =SUM(C85:BA85) -> 19 | BC85: =IFERROR(SEARCH($A85,BC$3),"") | BD85: =IFERROR(SEARCH($A85,BD$3),"") | BE85: =SUM(BC85:BD85) -> 0 | BF85: =BB85+BE85 -> 19
A86: ПК-5 | B86: =VLOOKUP(A86,Лист1!B:C,2,0) -> Способен осуществлять организацию перевозочного процесса и улучшения качества оказания логистических услуг | C86: =IFERROR(IF(SEARCH($A86,C$3)<>0,1,""),"") | D86: =IFERROR(IF(SEARCH($A86,D$3)<>0,1,""),"") | E86: =IFERROR(IF(SEARCH($A86,E$3)<>0,1,""),"") | F86: =IFERROR(IF(SEARCH($A86,F$3)<>0,1,""),"") | G86: =IFERROR(IF(SEARCH($A86,G$3)<>0,1,""),"") | H86: =IFERROR(IF(SEARCH($A86,H$3)<>0,1,""),"") | I86: =IFERROR(IF(SEARCH($A86,I$3)<>0,1,""),"") | J86: =IFERROR(IF(SEARCH($A86,J$3)<>0,1,""),"") | ... O86: =IFERROR(IF(SEARCH($A86,O$3)<>0,1,""),"") | Q86: =IFERROR(IF(SEARCH($A86,Q$3)<>0,1,""),"") | R86: =IFERROR(IF(SEARCH($A86,R$3)<>0,1,""),"") | S86: =IFERROR(IF(SEARCH($A86,S$3)<>0,1,""),"") | T86: =IFERROR(IF(SEARCH($A86,T$3)<>0,1,""),"") | U86: =IFERROR(IF(SEARCH($A86,U$3)<>0,1,""),"") | V86: =IFERROR(IF(SEARCH($A86,V$3)<>0,1,""),"") | W86: =IFERROR(IF(SEARCH($A86,W$3)<>0,1,""),"") | Y86: =IFERROR(IF(SEARCH($A86,Y$3)<>0,1,""),"") | Z86: =IFERROR(IF(SEARCH($A86,Z$3)<>0,1,""),"") | AA86: 9 | AB86: 6 | AC86: =IFERROR(IF(SEARCH($A86,AC$3)<>0,1,""),"") | AD86: =IFERROR(IF(SEARCH($A86,AD$3)<>0,1,""),"") | AE86: 18 | AF86: =IFERROR(IF(SEARCH($A86,AF$3)<>0,1,""),"") | AG86: 18 | AH86: =IFERROR(IF(SEARCH($A86,AH$3)<>0,1,""),"") | AI86: =IFERROR(IF(SEARCH($A86,AI$3)<>0,1,""),"") | AJ86: =IFERROR(IF(SEARCH($A86,AJ$3)<>0,1,""),"") | AK86: =IFERROR(IF(SEARCH($A86,AK$3)<>0,1,""),"") | AL86: =IFERROR(IF(SEARCH($A86,AL$3)<>0,1,""),"") | AM86: =IFERROR(IF(SEARCH($A86,AM$3)<>0,1,""),"") | AN86: =IFERROR(IF(SEARCH($A86,AN$3)<>0,1,""),"") | AO86: =IFERROR(IF(SEARCH($A86,AO$3)<>0,1,""),"") | ... AQ86: =IFERROR(IF(SEARCH($A86,AQ$3)<>0,1,""),"") | AR86: 18 | AS86: 18 | AT86: =IFERROR(IF(SEARCH($A86,AT$3)<>0,1,""),"") | AU86: =IFERROR(IF(SEARCH($A86,AU$3)<>0,1,""),"") | AV86: =IFERROR(IF(SEARCH($A86,AV$3)<>0,1,""),"") | AW86: =IFERROR(IF(SEARCH($A86,AW$3)<>0,1,""),"") | AX86: 2 | AY86: 2 | AZ86: 2 | BA86: 2 | BB86: =SUM(C86:BA86) -> 95 | BE86: =SUM(BC86:BD86) -> 0 | BF86: =BB86+BE86 -> 95
A87: ПК-5.1 | B87: =VLOOKUP(A87,Лист1!B:C,2,0) -> Разрабатывает математические модели для решения транспортных задач и улучшения качества оказания логистических услуг | C87: =IFERROR(SEARCH($A87,C$3),"") | D87: =IFERROR(SEARCH($A87,D$3),"") | E87: =IFERROR(SEARCH($A87,E$3),"") | F87: =IFERROR(SEARCH($A87,F$3),"") | G87: =IFERROR(SEARCH($A87,G$3),"") | H87: =IFERROR(SEARCH($A87,H$3),"") | I87: =IFERROR(SEARCH($A87,I$3),"") | J87: =IFERROR(SEARCH($A87,J$3),"") | ... Z87: =IFERROR(SEARCH($A87,Z$3),"") | AA87: 9 | AB87: 3 | AC87: =IFERROR(SEARCH($A87,AC$3),"") | AD87: =IFERROR(SEARCH($A87,AD$3),"") | AE87: =IFERROR(SEARCH($A87,AE$3),"") | AF87: =IFERROR(SEARCH($A87,AF$3),"") | AG87: =IFERROR(SEARCH($A87,AG$3),"") | AH87: =IFERROR(SEARCH($A87,AH$3),"") | AI87: =IFERROR(SEARCH($A87,AI$3),"") | AJ87: =IFERROR(SEARCH($A87,AJ$3),"") | ... AZ87: =IFERROR(SEARCH($A87,AZ$3),"") | BA87: 1 | BB87: =SUM(C87:BA87) -> 13 | BC87: =IFERROR(SEARCH($A87,BC$3),"") | BD87: =IFERROR(SEARCH($A87,BD$3),"") | BE87: =SUM(BC87:BD87) -> 0 | BF87: =BB87+BE87 -> 13
A88: ПК-5.2 | B88: =VLOOKUP(A88,Лист1!B:C,2,0) -> Планирует деятельность по продвижению транспортно-логистических услуг и выбору оптимальных схем доставки грузов в цепи поставок | C88: =IFERROR(SEARCH($A88,C$3),"") | D88: =IFERROR(SEARCH($A88,D$3),"") | E88: =IFERROR(SEARCH($A88,E$3),"") | F88: =IFERROR(SEARCH($A88,F$3),"") | G88: =IFERROR(SEARCH($A88,G$3),"") | H88: =IFERROR(SEARCH($A88,H$3),"") | I88: =IFERROR(SEARCH($A88,I$3),"") | J88: =IFERROR(SEARCH($A88,J$3),"") | ... W88: =IFERROR(SEARCH($A88,W$3),"") | Y88: =IFERROR(SEARCH($A88,Y$3),"") | Z88: =IFERROR(SEARCH($A88,Z$3),"") | AA88: =IFERROR(SEARCH($A88,AA$3),"") | AB88: =IFERROR(SEARCH($A88,AB$3),"") | AC88: =IFERROR(SEARCH($A88,AC$3),"") | AD88: =IFERROR(SEARCH($A88,AD$3),"") | AE88: =IFERROR(SEARCH($A88,AE$3),"") | AF88: =IFERROR(SEARCH($A88,AF$3),"") | AG88: 18 | AH88: =IFERROR(SEARCH($A88,AH$3),"") | AI88: =IFERROR(SEARCH($A88,AI$3),"") | AJ88: =IFERROR(SEARCH($A88,AJ$3),"") | AK88: =IFERROR(SEARCH($A88,AK$3),"") | AL88: =IFERROR(SEARCH($A88,AL$3),"") | AM88: =IFERROR(SEARCH($A88,AM$3),"") | AN88: =IFERROR(SEARCH($A88,AN$3),"") | AO88: =IFERROR(SEARCH($A88,AO$3),"") | ... AX88: =IFERROR(SEARCH($A88,AX$3),"") | AY88: 2 | AZ88: =IFERROR(SEARCH($A88,AZ$3),"") | BA88: =IFERROR(SEARCH($A88,BA$3),"") | BB88: =SUM(C88:BA88) -> 20 | BC88: =IFERROR(SEARCH($A88,BC$3),"") | BD88: =IFERROR(SEARCH($A88,BD$3),"") | BE88: =SUM(BC88:BD88) -> 0 | BF88: =BB88+BE88 -> 20
A89: ПК-5.3 | B89: =VLOOKUP(A89,Лист1!B:C,2,0) -> Решает задачи по повышению эффективности технических и технологических мероприятий при организации перевозочного процесса и оказании логистических услуг | C89: =IFERROR(SEARCH($A89,C$3),"") | D89: =IFERROR(SEARCH($A89,D$3),"") | E89: =IFERROR(SEARCH($A89,E$3),"") | F89: =IFERROR(SEARCH($A89,F$3),"") | G89: =IFERROR(SEARCH($A89,G$3),"") | H89: =IFERROR(SEARCH($A89,H$3),"") | I89: =IFERROR(SEARCH($A89,I$3),"") | J89: =IFERROR(SEARCH($A89,J$3),"") | ... O89: =IFERROR(SEARCH($A89,O$3),"") | Q89: =IFERROR(SEARCH($A89,Q$3),"") | R89: =IFERROR(SEARCH($A89,R$3),"") | S89: =IFERROR(SEARCH($A89,S$3),"") | T89: =IFERROR(SEARCH($A89,T$3),"") | U89: =IFERROR(SEARCH($A89,U$3),"") | V89: =IFERROR(SEARCH($A89,V$3),"") | W89: =IFERROR(SEARCH($A89,W$3),"") | X89: =IFERROR(SEARCH($A89,X$3),"") | ... AA89: =IFERROR(SEARCH($A89,AA$3),"") | AB89: 3 | AC89: =IFERROR(SEARCH($A89,AC$3),"") | AD89: =IFERROR(SEARCH($A89,AD$3),"") | AE89: =IFERROR(SEARCH($A89,AE$3),"") | AF89: =IFERROR(SEARCH($A89,AF$3),"") | AG89: =IFERROR(SEARCH($A89,AG$3),"") | AH89: =IFERROR(SEARCH($A89,AH$3),"") | AI89: =IFERROR(SEARCH($A89,AI$3),"") | AJ89: =IFERROR(SEARCH($A89,AJ$3),"") | ... AW89: =IFERROR(SEARCH($A89,AW$3),"") | AX89: 1 | AY89: =IFERROR(SEARCH($A89,AY$3),"") | AZ89: =IFERROR(SEARCH($A89,AZ$3),"") | BA89: 1 | BB89: =SUM(C89:BA89) -> 5 | BC89: =IFERROR(SEARCH($A89,BC$3),"") | BD89: =IFERROR(SEARCH($A89,BD$3),"") | BE89: =SUM(BC89:BD89) -> 0 | BF89: =BB89+BE89 -> 5
A90: ПК-5.4 | B90: =VLOOKUP(A90,Лист1!B:C,2,0) -> Планирует логистические мероприятия по организации контейнерных и пакетных перевозок в технологии работы терминальных систем транспорта | C90: =IFERROR(SEARCH($A90,C$3),"") | D90: =IFERROR(SEARCH($A90,D$3),"") | E90: =IFERROR(SEARCH($A90,E$3),"") | F90: =IFERROR(SEARCH($A90,F$3),"") | G90: =IFERROR(SEARCH($A90,G$3),"") | H90: =IFERROR(SEARCH($A90,H$3),"") | I90: =IFERROR(SEARCH($A90,I$3),"") | J90: =IFERROR(SEARCH($A90,J$3),"") | ... AQ90: =IFERROR(SEARCH($A90,AQ$3),"") | AR90: 18 | AS90: 18 | AT90: =IFERROR(SEARCH($A90,AT$3),"") | AU90: =IFERROR(SEARCH($A90,AU$3),"") | AV90: =IFERROR(SEARCH($A90,AV$3),"") | AW90: =IFERROR(SEARCH($A90,AW$3),"") | AY90: =IFERROR(SEARCH($A90,AY$3),"") | AZ90: 1 | BA90: =IFERROR(SEARCH($A90,BA$3),"") | BB90: =SUM(C90:BA90) -> 37 | BC90: =IFERROR(SEARCH($A90,BC$3),"") | BD90: =IFERROR(SEARCH($A90,BD$3),"") | BE90: =SUM(BC90:BD90) -> 0 | BF90: =BB90+BE90 -> 37
A91: ПК-5.5 | B91: =VLOOKUP(A91,Лист1!B:C,2,0) -> Планирует логистические операции, распределяет задачи в процессе реализации ключевых и поддерживающих функций логистики | C91: =IFERROR(SEARCH($A91,C$3),"") | D91: =IFERROR(SEARCH($A91,D$3),"") | E91: =IFERROR(SEARCH($A91,E$3),"") | F91: =IFERROR(SEARCH($A91,F$3),"") | G91: =IFERROR(SEARCH($A91,G$3),"") | H91: =IFERROR(SEARCH($A91,H$3),"") | I91: =IFERROR(SEARCH($A91,I$3),"") | J91: =IFERROR(SEARCH($A91,J$3),"") | ... AD91: =IFERROR(SEARCH($A91,AD$3),"") | AE91: 18 | AF91: =IFERROR(SEARCH($A91,AF$3),"") | AG91: =IFERROR(SEARCH($A91,AG$3),"") | AH91: =IFERROR(SEARCH($A91,AH$3),"") | AI91: =IFERROR(SEARCH($A91,AI$3),"") | AJ91: =IFERROR(SEARCH($A91,AJ$3),"") | AK91: =IFERROR(SEARCH($A91,AK$3),"") | AL91: =IFERROR(SEARCH($A91,AL$3),"") | AM91: =IFERROR(SEARCH($A91,AM$3),"") | ... AW91: =IFERROR(SEARCH($A91,AW$3),"") | AX91: 1 | AY91: =IFERROR(SEARCH($A91,AY$3),"") | AZ91: 1 | BA91: =IFERROR(SEARCH($A91,BA$3),"") | BB91: =SUM(C91:BA91) -> 20 | BC91: =IFERROR(SEARCH($A91,BC$3),"") | BD91: =IFERROR(SEARCH($A91,BD$3),"") | BE91: =SUM(BC91:BD91) -> 0 | BF91: =BB91+BE91 -> 20
A92: ПК-6 | B92: =VLOOKUP(A92,Лист1!B:C,2,0) -> Способен осуществлять контроль и управление системой организации пассажирских перевозок на железнодорожном транспорте | C92: =IFERROR(IF(SEARCH($A92,C$3)<>0,1,""),"") | D92: =IFERROR(IF(SEARCH($A92,D$3)<>0,1,""),"") | E92: =IFERROR(IF(SEARCH($A92,E$3)<>0,1,""),"") | F92: =IFERROR(IF(SEARCH($A92,F$3)<>0,1,""),"") | G92: =IFERROR(IF(SEARCH($A92,G$3)<>0,1,""),"") | H92: =IFERROR(IF(SEARCH($A92,H$3)<>0,1,""),"") | I92: =IFERROR(IF(SEARCH($A92,I$3)<>0,1,""),"") | J92: =IFERROR(IF(SEARCH($A92,J$3)<>0,1,""),"") | ... V92: =IFERROR(IF(SEARCH($A92,V$3)<>0,1,""),"") | X92: =IFERROR(IF(SEARCH($A92,X$3)<>0,1,""),"") | Y92: =IFERROR(IF(SEARCH($A92,Y$3)<>0,1,""),"") | Z92: =IFERROR(IF(SEARCH($A92,Z$3)<>0,1,""),"") | AA92: =IFERROR(IF(SEARCH($A92,AA$3)<>0,1,""),"") | AC92: =IFERROR(IF(SEARCH($A92,AC$3)<>0,1,""),"") | AD92: =IFERROR(IF(SEARCH($A92,AD$3)<>0,1,""),"") | AE92: =IFERROR(IF(SEARCH($A92,AE$3)<>0,1,""),"") | AF92: =IFERROR(IF(SEARCH($A92,AF$3)<>0,1,""),"") | AG92: =IFERROR(IF(SEARCH($A92,AG$3)<>0,1,""),"") | AH92: =IFERROR(IF(SEARCH($A92,AH$3)<>0,1,""),"") | AI92: =IFERROR(IF(SEARCH($A92,AI$3)<>0,1,""),"") | AJ92: =IFERROR(IF(SEARCH($A92,AJ$3)<>0,1,""),"") | AK92: =IFERROR(IF(SEARCH($A92,AK$3)<>0,1,""),"") | AL92: 18 | AM92: =IFERROR(IF(SEARCH($A92,AM$3)<>0,1,""),"") | AN92: =IFERROR(IF(SEARCH($A92,AN$3)<>0,1,""),"") | AO92: =IFERROR(IF(SEARCH($A92,AO$3)<>0,1,""),"") | AP92: =IFERROR(IF(SEARCH($A92,AP$3)<>0,1,""),"") | AQ92: =IFERROR(IF(SEARCH($A92,AQ$3)<>0,1,""),"") | AR92: =IFERROR(IF(SEARCH($A92,AR$3)<>0,1,""),"") | AS92: =IFERROR(IF(SEARCH($A92,AS$3)<>0,1,""),"") | AT92: =IFERROR(IF(SEARCH($A92,AT$3)<>0,1,""),"") | ... AZ92: =IFERROR(IF(SEARCH($A92,AZ$3)<>0,1,""),"") | BA92: 2 | BB92: =SUM(C92:BA92) -> 20 | BC92: =IFERROR(SEARCH(_xlfn.CONCAT(" ",$A92),#REF!),"") | BD92: =IFERROR(SEARCH(_xlfn.CONCAT(" ",$A92),#REF!),"") | BE92: =SUM(BC92:BD92) -> 0 | BF92: =BB92+BE92 -> 20
A93: ПК-6.1 | B93: =VLOOKUP(A93,Лист1!B:C,2,0) -> Решает задачи, направленные на организацию пассажирских перевозок на железнодорожном транспорте | C93: =IFERROR(SEARCH($A93,C$3),"") | D93: =IFERROR(SEARCH($A93,D$3),"") | E93: =IFERROR(SEARCH($A93,E$3),"") | F93: =IFERROR(SEARCH($A93,F$3),"") | G93: =IFERROR(SEARCH($A93,G$3),"") | H93: =IFERROR(SEARCH($A93,H$3),"") | I93: =IFERROR(SEARCH($A93,I$3),"") | J93: =IFERROR(SEARCH($A93,J$3),"") | ... AA93: =IFERROR(SEARCH($A93,AA$3),"") | AC93: =IFERROR(SEARCH($A93,AC$3),"") | AD93: =IFERROR(SEARCH($A93,AD$3),"") | AE93: =IFERROR(SEARCH($A93,AE$3),"") | AF93: =IFERROR(SEARCH($A93,AF$3),"") | AG93: =IFERROR(SEARCH($A93,AG$3),"") | AH93: =IFERROR(SEARCH($A93,AH$3),"") | AI93: =IFERROR(SEARCH($A93,AI$3),"") | AJ93: =IFERROR(SEARCH($A93,AJ$3),"") | AK93: =IFERROR(SEARCH($A93,AK$3),"") | AL93: 9 | AM93: =IFERROR(SEARCH($A93,AM$3),"") | AN93: =IFERROR(SEARCH($A93,AN$3),"") | AO93: =IFERROR(SEARCH($A93,AO$3),"") | AP93: =IFERROR(SEARCH($A93,AP$3),"") | AQ93: =IFERROR(SEARCH($A93,AQ$3),"") | AR93: =IFERROR(SEARCH($A93,AR$3),"") | AS93: =IFERROR(SEARCH($A93,AS$3),"") | AT93: =IFERROR(SEARCH($A93,AT$3),"") | ... AZ93: =IFERROR(SEARCH($A93,AZ$3),"") | BA93: 1 | BB93: =SUM(C93:BA93) -> 10 | BC93: =IFERROR(SEARCH($A93,BC$3),"") | BD93: =IFERROR(SEARCH($A93,BD$3),"") | BE93: =SUM(BC93:BD93) -> 0 | BF93: =BB93+BE93 -> 10
A94: ПК-6.2 | B94: =VLOOKUP(A94,Лист1!B:C,2,0) -> Решает задачи, направленные на организацию работы и эксплуатацию вокзальных комплексов, транспортно-пересадочных узлов | C94: =IFERROR(SEARCH($A94,C$3),"") | D94: =IFERROR(SEARCH($A94,D$3),"") | E94: =IFERROR(SEARCH($A94,E$3),"") | F94: =IFERROR(SEARCH($A94,F$3),"") | G94: =IFERROR(SEARCH($A94,G$3),"") | H94: =IFERROR(SEARCH($A94,H$3),"") | I94: =IFERROR(SEARCH($A94,I$3),"") | J94: =IFERROR(SEARCH($A94,J$3),"") | ... V94: =IFERROR(SEARCH($A94,V$3),"") | X94: =IFERROR(SEARCH($A94,X$3),"") | Y94: =IFERROR(SEARCH($A94,Y$3),"") | Z94: =IFERROR(SEARCH($A94,Z$3),"") | AA94: =IFERROR(SEARCH($A94,AA$3),"") | AB94: =IFERROR(SEARCH($A94,AB$3),"") | AC94: =IFERROR(SEARCH($A94,AC$3),"") | AD94: =IFERROR(SEARCH($A94,AD$3),"") | AE94: =IFERROR(SEARCH($A94,AE$3),"") | ... AZ94: =IFERROR(SEARCH($A94,AZ$3),"") | BA94: 1 | BB94: =SUM(C94:BA94) -> 10 | BC94: =IFERROR(SEARCH($A94,BC$3),"") | BD94: =IFERROR(SEARCH($A94,BD$3),"") | BE94: =SUM(BC94:BD94) -> 0 | BF94: =BB94+BE94 -> 10
A95: Итого по дисциплине | C95: =SUM(C4,C7,C10,C13,C18,C22,C25,C29,C33,C36,C39,C42,C48,C53,C56,C61,C65,C68,C73,C78,C81,C86,C92) -> 18 | D95: =SUM(D4,D7,D10,D13,D18,D22,D25,D29,D33,D36,D39,D42,D48,D53,D56,D61,D65,D68,D73,D78,D81,D86,D92) -> 18 | E95: =SUM(E4,E7,E10,E13,E18,E22,E25,E29,E33,E36,E39,E42,E48,E53,E56,E61,E65,E68,E73,E78,E81,E86,E92) -> 18 | F95: =SUM(F4,F7,F10,F13,F18,F22,F25,F29,F33,F36,F39,F42,F48,F53,F56,F61,F65,F68,F73,F78,F81,F86,F92) -> 18 | G95: =SUM(G4,G7,G10,G13,G18,G22,G25,G29,G33,G36,G39,G42,G48,G53,G56,G61,G65,G68,G73,G78,G81,G86,G92) -> 18 | H95: =SUM(H4,H7,H10,H13,H18,H22,H25,H29,H33,H36,H39,H42,H48,H53,H56,H61,H65,H68,H73,H78,H81,H86,H92) -> 18 | I95: =SUM(I4,I7,I10,I13,I18,I22,I25,I29,I33,I36,I39,I42,I48,I53,I56,I61,I65,I68,I73,I78,I81,I86,I92) -> 18 | J95: =SUM(J4,J7,J10,J13,J18,J22,J25,J29,J33,J36,J39,J42,J48,J53,J56,J61,J65,J68,J73,J78,J81,J86,J92) -> 18 | ... BF95: =SUM(BF4,BF7,BF10,BF13,BF18,BF22,BF25,BF29,BF33,BF36,BF39,BF42,BF48,BF53,BF56,BF61,BF65,BF68,BF73,BF78,BF81,BF86,BF92) -> 934

Sheet Лист1
A1: УК-1 | B1: УК-1 | C1: =VLOOKUP(B1,F:G,2,0) -> Способен осуществлять поиск, критический анализ и синтез информации, применять системный подход для решения поставленных задач | D1: Индекс | G1: Содержание
B2: УК-1.1 | C2: =VLOOKUP(B2,F:G,2,0) -> Осуществляет поиск информации, критически оценивает надежность источников информации, работает с противоречивой информацией из разных источников | D2: УК-1 | F2: =_xlfn.CONCAT(D2,E2) -> УК-1 | G2: Способен осуществлять поиск, критический анализ и синтез информации, применять системный подход для решения поставленных задач
B3: УК-1.2 | C3: =VLOOKUP(B3,F:G,2,0) -> Анализирует проблемную ситуацию, выявляет ее составляющие и связи между ними, формулирует и аргументирует выводы и суждения | E3: УК-1.1 | F3: =_xlfn.CONCAT(D3,E3) -> УК-1.1 | G3: Осуществляет поиск информации, критически оценивает надежность источников информации, работает с противоречивой информацией из разных источников
A4: УК-2 | B4: УК-2 | C4: =VLOOKUP(B4,F:G,2,0) -> Способен определять круг задач в рамках поставленной цели и выбирать оптимальные способы их решения, исходя из действующих правовых норм, имеющихся ресурсов и ограничений | F4: =_xlfn.CONCAT(D4,E4) | G4: Философия
B5: УК-2.1 | C5: =VLOOKUP(B5,F:G,2,0) -> Решает ситуационные задачи с учетом трудовых и социальных факторов в рамках нормативно-правового регулирования | F5: =_xlfn.CONCAT(D5,E5) | G5: Выполнение, подготовка к процедуре защиты и защита выпускной квалификационной работы
B6: УК-2.2 | C6: =VLOOKUP(B6,F:G,2,0) -> Формулирует проектную задачу, определяет способы ее решения средствами проектного управления | E6: УК-1.2 | F6: =_xlfn.CONCAT(D6,E6) -> УК-1.2 | G6: Анализирует проблемную ситуацию, выявляет ее составляющие и связи между ними, формулирует и аргументирует выводы и суждения
A7: УК-3 | B7: УК-3 | C7: =VLOOKUP(B7,F:G,2,0) -> Способен осуществлять социальное взаимодействие и реализовывать свою роль в команде | F7: =_xlfn.CONCAT(D7,E7) | G7: Философия
B8: УК-3.1 | C8: =VLOOKUP(B8,F:G,2,0) -> Организует и координирует работу команды с учетом интересов, особенностей поведения и мнения её членов | F8: =_xlfn.CONCAT(D8,E8) | G8: Выполнение, подготовка к процедуре защиты и защита выпускной квалификационной работы
B9: УК-3.2 | C9: =VLOOKUP(B9,F:G,2,0) -> Вырабатывает командную стратегию для достижения поставленной цели | D9: УК-2 | F9: =_xlfn.CONCAT(D9,E9) -> УК-2 | G9: Способен определять круг задач в рамках поставленной цели и выбирать оптимальные способы их решения, исходя из действующих правовых норм, имеющихся ресурсов и ограничений
A10: УК-4 | B10: УК-4 | C10: =VLOOKUP(B10,F:G,2,0) -> Способен осуществлять деловую коммуникацию в устной и письменной формах на государственном языке Российской Федерации и иностранном(ых) языке(ах) | E10: УК-2.1 | F10: =_xlfn.CONCAT(D10,E10) -> УК-2.1 | G10: Решает ситуационные задачи с учетом трудовых и социальных факторов в рамках нормативно-правового регулирования
B11: УК-4.1 | C11: =VLOOKUP(B11,F:G,2,0) -> Отбирает и использует средства русского языка в соответствии с языковыми нормами в целях построения эффективной академической и профессиональной коммуникации | F11: =_xlfn.CONCAT(D11,E11) | G11: Правовое обеспечение профессиональной деятельности
B12: УК-4.2 | C12: =VLOOKUP(B12,F:G,2,0) -> Осуществляет академическое и деловое взаимодействие в различных жанрах и формах с использованием современных коммуникативных технологий | F12: =_xlfn.CONCAT(D12,E12) | G12: История России
B13: УК-4.3 | C13: =VLOOKUP(B13,F:G,2,0) -> Применяет современные коммуникативные технологии для академического взаимодействия на иностранном(ых) языке(ах) | F13: =_xlfn.CONCAT(D13,E13) | G13: Выполнение, подготовка к процедуре защиты и защита выпускной квалификационной работы
B14: УК-4.4 | C14: =VLOOKUP(B14,F:G,2,0) -> Применяет современные коммуникативные технологии для профессионального взаимодействия на иностранном(ых) языке(ах) | E14: УК-2.2 | F14: =_xlfn.CONCAT(D14,E14) -> УК-2.2 | G14: Формулирует проектную задачу, определяет способы ее решения средствами проектного управления
A15: УК-5 | B15: УК-5 | C15: =VLOOKUP(B15,F:G,2,0) -> Способен воспринимать межкультурное разнообразие общества в социально-историческом, этическом и философском контекстах | F15: =_xlfn.CONCAT(D15,E15) | G15: Менеджмент
B16: УК-5.1 | C16: =VLOOKUP(B16,F:G,2,0) -> Анализирует идеологические и ценностные системы в контексте исторического развития общества, обосновывает актуальность их использования при социальном и профессиональном взаимодействии | F16: =_xlfn.CONCAT(D16,E16) | G16: Выполнение, подготовка к процедуре защиты и защита выпускной квалификационной работы
B17: УК-5.2 | C17: =VLOOKUP(B17,F:G,2,0) -> Выявляет современные тенденции исторического развития России с учетом геополитической обстановки | F17: =_xlfn.CONCAT(D17,E17) | G17: Построение бизнес-модели
B18: УК-5.3 | C18: =VLOOKUP(B18,F:G,2,0) -> Выстраивает социальное и профессиональное взаимодействие с учетом особенностей основных форм научного и религиозного сознания, деловой и общей культуры представителей различных социальных групп, этносов и конфессий | D18: УК-3 | F18: =_xlfn.CONCAT(D18,E18) -> УК-3 | G18: Способен осуществлять социальное взаимодействие и реализовывать свою роль в команде
A19: УК-6 | B19: УК-6 | C19: =VLOOKUP(B19,F:G,2,0) -> Способен управлять своим временем, выстраивать и реализовывать траекторию саморазвития на основе принципов образования в течение всей жизни | E19: УК-3.1 | F19: =_xlfn.CONCAT(D19,E19) -> УК-3.1 | G19: Организует и координирует работу команды с учетом интересов, особенностей поведения и мнения её членов
B20: УК-6.1 | C20: =VLOOKUP(B20,F:G,2,0) -> Определяет цели и задачи саморазвития и профессионального роста на основе оценки временных и личностных ресурсов | F20: =_xlfn.CONCAT(D20,E20) | G20: Менеджмент
B21: УК-6.2 | C21: =VLOOKUP(B21,F:G,2,0) -> Использует основные возможности и инструменты непрерывного образования (образования в течение всей жизни) для реализации траектории саморазвития | F21: =_xlfn.CONCAT(D21,E21) | G21: Выполнение, подготовка к процедуре защиты и защита выпускной квалификационной работы
A22: УК-7 | B22: УК-7 | C22: =VLOOKUP(B22,F:G,2,0) -> Способен поддерживать должный уровень физической подготовленности для обеспечения полноценной социальной и профессиональной деятельности | E22: УК-3.2 | F22: =_xlfn.CONCAT(D22,E22) -> УК-3.2 | G22: Вырабатывает командную стратегию для достижения поставленной цели
B23: УК-7.1 | C23: =VLOOKUP(B23,F:G,2,0) -> Идентифицирует и анализирует социально-биологические и методические основы физического воспитания, здорового образа жизни, профессионально-прикладной физической подготовки | F23: =_xlfn.CONCAT(D23,E23) | G23: Менеджмент
B24: УК-7.2 | C24: =VLOOKUP(B24,F:G,2,0) -> Выбирает способы оценки и контроля уровня физического развития, физической и профессионально-прикладной подготовленности, показателей работоспособности и здоровья, с учетом физиологических особенностей организма | F24: =_xlfn.CONCAT(D24,E24) | G24: Выполнение, подготовка к процедуре защиты и защита выпускной квалификационной работы
B25: УК-7.3 | C25: =VLOOKUP(B25,F:G,2,0) -> Соблюдает нормы здорового образа жизни, поддерживает должный уровень физической подготовленности для обеспечения полноценной социальной и профессиональной деятельности | D25: УК-4 | F25: =_xlfn.CONCAT(D25,E25) -> УК-4 | G25: Способен осуществлять деловую коммуникацию в устной и письменной формах на государственном языке Российской Федерации и иностранном(ых) языке(ах)
A26: УК-8 | B26: УК-8 | C26: =VLOOKUP(B26,F:G,2,0) -> Способен создавать и поддерживать в повседневной жизни и в профессиональной деятельности безопасные условия жизнедеятельности для сохранения природной среды, обеспечения устойчивого развития общества, в том числе при угрозе и возникновении чрезвычайных ситуаций и военных конфликтов | E26: УК-4.1 | F26: =_xlfn.CONCAT(D26,E26) -> УК-4.1 | G26: Отбирает и использует средства русского языка в соответствии с языковыми нормами в целях построения эффективной академической и профессиональной коммуникации
B27: УК-8.1 | C27: =VLOOKUP(B27,F:G,2,0) -> Идентифицирует и анализирует факторы вредного влияния элементов среды обитания (технических средств, технологических процессов, материалов, зданий и сооружений, природных и социальных явлений) | F27: =_xlfn.CONCAT(D27,E27) | G27: Русский язык и деловые коммуникации
B28: УК-8.2 | C28: =VLOOKUP(B28,F:G,2,0) -> Определяет алгоритм действий по обеспечению безопасных условий жизнедеятельности при угрозе и возникновении чрезвычайных ситуаций и военных конфликтов | F28: =_xlfn.CONCAT(D28,E28) | G28: Выполнение, подготовка к процедуре защиты и защита выпускной квалификационной работы
B29: УК-8.3 | C29: =VLOOKUP(B29,F:G,2,0) -> Планирует мероприятия по организации безопасных условий труда на предприятии | E29: УК-4.2 | F29: =_xlfn.CONCAT(D29,E29) -> УК-4.2 | G29: Осуществляет академическое и деловое взаимодействие в различных жанрах и формах с использованием современных коммуникативных технологий
A30: УК-9 | B30: УК-9 | C30: =VLOOKUP(B30,F:G,2,0) -> Способен использовать базовые дефектологические знания в социальной и профессиональной сферах | F30: =_xlfn.CONCAT(D30,E30) | G30: Русский язык и деловые коммуникации
B31: УК-9.1 | C31: =VLOOKUP(B31,F:G,2,0) -> Осуществляет взаимодействие в социальной и профессиональной сферах с лицами с ограниченными возможностями здоровья и инвалидами | F31: =_xlfn.CONCAT(D31,E31) | G31: Выполнение, подготовка к процедуре защиты и защита выпускной квалификационной работы
B32: УК-9.2 | C32: =VLOOKUP(B32,F:G,2,0) -> Планирует мероприятия по организации доступной среды на объектах транспорта для безбарьерного обслуживания пассажиров из числа инвалидов и лиц с ограниченными возможностями здоровья | E32: УК-4.3 | F32: =_xlfn.CONCAT(D32,E32) -> УК-4.3 | G32: Применяет современные коммуникативные технологии для академического взаимодействия на иностранном(ых) языке(ах)
A33: УК-10 | B33: УК-10 | C33: =VLOOKUP(B33,F:G,2,0) -> Способен принимать обоснованные экономические решения в различных областях жизнедеятельности | F33: =_xlfn.CONCAT(D33,E33) | G33: Иностранный язык
B34: УК-10.1 | C34: =VLOOKUP(B34,F:G,2,0) -> Анализирует и критически оценивает информацию, необходимую для принятия обоснованных экономических решений | F34: =_xlfn.CONCAT(D34,E34) | G34: Выполнение, подготовка к процедуре защиты и защита выпускной квалификационной работы
B35: УК-10.2 | C35: =VLOOKUP(B35,F:G,2,0) -> Применяет методы личного экономического и финансового планирования для достижения текущих и долгосрочных финансовых целей, использует финансовые инструменты для управления личными финансами (личным бюджетом), контролирует собственные экономические и финансовые риски | E35: УК-4.4 | F35: =_xlfn.CONCAT(D35,E35) -> УК-4.4 | G35: Применяет современные коммуникативные технологии для профессионального взаимодействия на иностранном(ых) языке(ах)
A36: УК-11 | B36: УК-11 | C36: =VLOOKUP(B36,F:G,2,0) -> Способен формировать нетерпимое отношение к проявлениям экстремизма, терроризма, коррупционному поведению и противодействовать им в профессиональной деятельности | F36: =_xlfn.CONCAT(D36,E36) | G36: Иностранный язык
B37: УК-11.1 | C37: =VLOOKUP(B37,F:G,2,0) -> Раскрывает механизм проявления коррупционного поведения и определяет способы противодействия ему в профессиональной деятельности | F37: =_xlfn.CONCAT(D37,E37) | G37: Выполнение, подготовка к процедуре защиты и защита выпускной квалификационной работы
B38: УК-11.2 | C38: =VLOOKUP(B38,F:G,2,0) -> Обосновывает правовыми средствами свою гражданскую позицию в отношении терроризма и экстремизма и применяет способы противодействия им в профессиональной сфере | D38: УК-5 | F38: =_xlfn.CONCAT(D38,E38) -> УК-5 | G38: Способен воспринимать межкультурное разнообразие общества в социально-историческом, этическом и философском контекстах
B39: ОПК-1 | C39: =VLOOKUP(B39,F:G,2,0) -> Способен применять естественнонаучные и общеинженерные знания, методы математического анализа и моделирования в профессиональной деятельности | E39: УК-5.1 | F39: =_xlfn.CONCAT(D39,E39) -> УК-5.1 | G39: Анализирует идеологические и ценностные системы в контексте исторического развития общества, обосновывает актуальность их использования при социальном и профессиональном взаимодействии
B40: ОПК-1.1 | C40: =VLOOKUP(B40,F:G,2,0) -> Применяет методы высшей математики для решения задач профессиональной деятельности | F40: =_xlfn.CONCAT(D40,E40) | G40: История (история России, всеобщая история)
B41: ОПК-1.2 | C41: =VLOOKUP(B41,F:G,2,0) -> Применяет основные понятия и законы естественных наук для решения предметно-профильных задач | F41: =_xlfn.CONCAT(D41,E41) | G41: История России
B42: ОПК-1.3 | C42: =VLOOKUP(B42,F:G,2,0) -> Применяет естественнонаучные методы теоретического и экспериментального исследования объектов, процессов, явлений, проводит эксперименты по заданной методике и анализирует результаты | F42: =_xlfn.CONCAT(D42,E42) | G42: Выполнение, подготовка к процедуре защиты и защита выпускной квалификационной работы
A43: ОПК-1 | B43: ОПК-1.4 | C43: =VLOOKUP(B43,F:G,2,0) -> Разрабатывает графическую техническую документацию в соответствии с требованиями ЕСКД, в том числе с использованием пакетов прикладных программ для автоматизированного построения модели деталей техники | E43: УК-5.2 | F43: =_xlfn.CONCAT(D43,E43) -> УК-5.2 | G43: Выявляет современные тенденции исторического развития России с учетом геополитической обстановки
B44: ОПК-1.5 | C44: =VLOOKUP(B44,F:G,2,0) -> Применяет методы математического анализа и моделирования для решения прикладных задач | F44: =_xlfn.CONCAT(D44,E44) | G44: История (история России, всеобщая история)
B45: ОПК-2 | C45: =VLOOKUP(B45,F:G,2,0) -> Способен осуществлять профессиональную деятельность с учетом экономических, экологических и социальных ограничений на всех этапах жизненного цикла транспортно-технологических машин и комплексов | F45: =_xlfn.CONCAT(D45,E45) | G45: История России
B46: ОПК-2.1 | C46: =VLOOKUP(B46,F:G,2,0) -> Осуществляет мониторинг, прогнозирование и оценку экологической безопасности действующих, вновь строящихся и реконструируемых объектов | F46: =_xlfn.CONCAT(D46,E46) | G46: Выполнение, подготовка к процедуре защиты и защита выпускной квалификационной работы
B47: ОПК-2.2 | C47: =VLOOKUP(B47,F:G,2,0) -> Решает задачи профессиональной деятельности с учетом экономических ограничений на всех этапах жизненного цикла транспортно-технологических машин и комплексов | E47: УК-5.3 | F47: =_xlfn.CONCAT(D47,E47) -> УК-5.3 | G47: Выстраивает социальное и профессиональное взаимодействие с учетом особенностей основных форм научного и религиозного сознания, деловой и общей культуры представителей различных социальных групп, этносов и конфессий
B48: ОПК-2.3 | C48: =VLOOKUP(B48,F:G,2,0) -> Применяет теоретические основы менеджмента при решении профессиональных задач | F48: =_xlfn.CONCAT(D48,E48) | G48: Религии мира
B49: ОПК-2.4 | C49: =VLOOKUP(B49,F:G,2,0) -> Предлагает решение проблем, связанных с формированием или развитием транспортно-технологических систем (в том числе машин и комплексов) | F49: =_xlfn.CONCAT(D49,E49) | G49: Выполнение, подготовка к процедуре защиты и защита выпускной квалификационной работы
B50: ОПК-3 | C50: =VLOOKUP(B50,F:G,2,0) -> Способен в сфере своей профессиональной деятельности проводить измерения и наблюдения, обрабатывать и представлять экспериментальные данные и результаты испытаний | F50: =_xlfn.CONCAT(D50,E50) | G50: История религиозной культуры
B51: ОПК-3.1 | C51: =VLOOKUP(B51,F:G,2,0) -> Проводит измерения и наблюдения с использованием технических средств с учетом правовых норм метрологии | D51: УК-6 | F51: =_xlfn.CONCAT(D51,E51) -> УК-6 | G51: Способен управлять своим временем, выстраивать и реализовывать траекторию саморазвития на основе принципов образования в течение всей жизни
B52: ОПК-3.2 | C52: =VLOOKUP(B52,F:G,2,0) -> Обрабатывает и представляет результаты измерений в ходе выполнения экспериментальных испытаний в соответствии с требованиями действующих стандартов | E52: УК-6.1 | F52: =_xlfn.CONCAT(D52,E52) -> УК-6.1 | G52: Определяет цели и задачи саморазвития и профессионального роста на основе оценки временных и личностных ресурсов
B53: ОПК-4 | C53: =VLOOKUP(B53,F:G,2,0) -> Способен понимать принципы работы современных информационных технологий и использовать их для решения задач профессиональной деятельности | F53: =_xlfn.CONCAT(D53,E53) | G53: Тренинг-практикум по самоорганизации и саморазвитию
B54: ОПК-4.1 | C54: =VLOOKUP(B54,F:G,2,0) -> Применяет основные методы представления информации и алгоритмы обработки данных в профессиональной деятельности | F54: =_xlfn.CONCAT(D54,E54) | G54: Выполнение, подготовка к процедуре защиты и защита выпускной квалификационной работы
B55: ОПК-4.2 | C55: =VLOOKUP(B55,F:G,2,0) -> Использует ресурсы электронной образовательной среды в рамках своей образовательной деятельности | E55: УК-6.2 | F55: =_xlfn.CONCAT(D55,E55) -> УК-6.2 | G55: Использует основные возможности и инструменты непрерывного образования (образования в течение всей жизни) для реализации траектории саморазвития
B56: ОПК-4.3 | C56: =VLOOKUP(B56,F:G,2,0) -> Использует в своей профессиональной деятельности автоматизированные информационно-управляющие и аналитические системы, применяемые на транспорте | F56: =_xlfn.CONCAT(D56,E56) | G56: Тренинг-практикум по самоорганизации и саморазвитию
B57: ОПК-4.4 | C57: =VLOOKUP(B57,F:G,2,0) -> Использует методы искусственного интеллекта (машинного обучения) и анализа больших данных для решения прикладных задач | F57: =_xlfn.CONCAT(D57,E57) | G57: Выполнение, подготовка к процедуре защиты и защита выпускной квалификационной работы
B58: ОПК-5 | C58: =VLOOKUP(B58,F:G,2,0) -> Способен принимать обоснованные технические решения, выбирать эффективные и безопасные технические средства и технологии при решении задач профессиональной деятельности | D58: УК-7 | F58: =_xlfn.CONCAT(D58,E58) -> УК-7 | G58: Способен поддерживать должный уровень физической подготовленности для обеспечения полноценной социальной и профессиональной деятельности
B59: ОПК-5.1 | C59: =VLOOKUP(B59,F:G,2,0) -> Обосновывает технические решения, выбирает эффективные и безопасные технические средства и технологии при решении задач профессиональной деятельности | E59: УК-7.1 | F59: =_xlfn.CONCAT(D59,E59) -> УК-7.1 | G59: Идентифицирует и анализирует социально-биологические и методические основы физического воспитания, здорового образа жизни, профессионально-прикладной физической подготовки
B60: ОПК-5.2 | C60: =VLOOKUP(B60,F:G,2,0) -> Выбирает эффективные и безопасные технические средства и технологии погрузочно-разгрузочных работ | F60: =_xlfn.CONCAT(D60,E60) | G60: Физическая культура и спорт
A61: ОПК-2 | B61: ОПК-5.3 | C61: =VLOOKUP(B61,F:G,2,0) -> Обосновывает выбор эффективных и безопасных технических средств и технологий при решении задач профессиональной деятельности | F61: =_xlfn.CONCAT(D61,E61) | G61: Выполнение, подготовка к процедуре защиты и защита выпускной квалификационной работы
B62: ОПК-6 | C62: =VLOOKUP(B62,F:G,2,0) -> Способен участвовать в разработке технической документации с использованием стандартов, норм и правил, связанных с профессиональной деятельностью | E62: УК-7.2 | F62: =_xlfn.CONCAT(D62,E62) -> УК-7.2 | G62: Выбирает способы оценки и контроля уровня физического развития, физической и профессионально-прикладной подготовленности, показателей работоспособности и здоровья, с учетом физиологических особенностей организма
B63: ОПК-6.1 | C63: =VLOOKUP(B63,F:G,2,0) -> Использует стандарты, нормы и правила, связанные с профессиональной деятельностью, при разработке технических и технологических мероприятий в организации перевозочного процесса и оказании логистических услуг | F63: =_xlfn.CONCAT(D63,E63) | G63: Физическая культура и спорт
B64: ОПК-6.2 | C64: =VLOOKUP(B64,F:G,2,0) -> Разрабатывает технические и технологические мероприятия производственной деятельности с учетом действующих международных, российских, отраслевых стандартов, норм и правил | F64: =_xlfn.CONCAT(D64,E64) | G64: Выполнение, подготовка к процедуре защиты и защита выпускной квалификационной работы
B65: ПК-1 | C65: =VLOOKUP(B65,F:G,2,0) -> Способен выполнять комплекс услуг по транспортному обслуживанию грузоотправителей и грузополучателей при перевозке грузов, в том числе скоропортящихся, на основе принципов логистики с учетом эффективного и рационального взаимодействия видов транспорта, составляющих единую транспортную систему | E65: УК-7.3 | F65: =_xlfn.CONCAT(D65,E65) -> УК-7.3 | G65: Соблюдает нормы здорового образа жизни, поддерживает должный уровень физической подготовленности для обеспечения полноценной социальной и профессиональной деятельности
B66: ПК-1.1 | C66: =VLOOKUP(B66,F:G,2,0) -> Планирует работу предприятия транспортной отрасли по оказанию комплекса услуг грузовладельцам | F66: =_xlfn.CONCAT(D66,E66) | G66: Элективные курсы по физической культуре и спорту
B67: ПК-1.2 | C67: =VLOOKUP(B67,F:G,2,0) -> Идентифицирует и анализирует свойства грузов, характеристики подвижного состава, требования к размещению и креплению грузов в вагонах и контейнерах | F67: =_xlfn.CONCAT(D67,E67) | G67: Выполнение, подготовка к процедуре защиты и защита выпускной квалификационной работы
B68: ПК-1.3 | C68: =VLOOKUP(B68,F:G,2,0) -> Определяет перечень транспортных услуг, связанных с перевозкой скоропортящихся грузов | D68: УК-8 | F68: =_xlfn.CONCAT(D68,E68) -> УК-8 | G68: Способен создавать и поддерживать в повседневной жизни и в профессиональной деятельности безопасные условия жизнедеятельности для сохранения природной среды, обеспечения устойчивого развития общества, в том числе при угрозе и возникновении чрезвычайных ситуаций и военных конфликтов
B69: ПК-1.4 | C69: =VLOOKUP(B69,F:G,2,0) -> Разрабатывает комплекс услуг по транспортно-логистическому обслуживанию для эффективной мультимодальной перевозки грузов | E69: УК-8.1 | F69: =_xlfn.CONCAT(D69,E69) -> УК-8.1 | G69: Идентифицирует и анализирует факторы вредного влияния элементов среды обитания (технических средств, технологических процессов, материалов, зданий и сооружений, природных и социальных явлений)
B70: ПК-2 | C70: =VLOOKUP(B70,F:G,2,0) -> Способен осуществлять контроль и управление перевозочным процессом, оперативное планирование и управление эксплуатационной работой с учетом технического состояния, контроль безопасности движения и эксплуатации на железнодорожном транспорте | F70: =_xlfn.CONCAT(D70,E70) | G70: Безопасность жизнедеятельности
B71: ПК-2.1 | C71: =VLOOKUP(B71,F:G,2,0) -> Осуществляет оперативное планирование, управление, контроль перевозочного процесса с учетом технического состояния и безопасности | F71: =_xlfn.CONCAT(D71,E71) | G71: Выполнение, подготовка к процедуре защиты и защита выпускной квалификационной работы
B72: ПК-2.2 | C72: =VLOOKUP(B72,F:G,2,0) -> Использует технические средства для обеспечения безопасности на железнодорожном транспорте | E72: УК-8.2 | F72: =_xlfn.CONCAT(D72,E72) -> УК-8.2 | G72: Определяет алгоритм действий по обеспечению безопасных условий жизнедеятельности при угрозе и возникновении чрезвычайных ситуаций и военных конфликтов
B73: ПК-2.3 | C73: =VLOOKUP(B73,F:G,2,0) -> Определяет последовательность действий в соответствии с правилами технической эксплуатации и требованиями техники безопасности при организации и проведении работ | F73: =_xlfn.CONCAT(D73,E73) | G73: Безопасность жизнедеятельности
A74: ОПК-3 | B74: ПК-2.4 | C74: =VLOOKUP(B74,F:G,2,0) -> Осуществляет контроль и управление движением поездов, принимает решения по организации движения поездов по участку в изменяющейся поездной обстановке | F74: =_xlfn.CONCAT(D74,E74) | G74: Выполнение, подготовка к процедуре защиты и защита выпускной квалификационной работы
B75: ПК-3 | C75: =VLOOKUP(B75,F:G,2,0) -> Способен проектировать железнодорожные линии, станции и узлы, разрабатывать и корректировать нормативную технологическую документацию с учетом технического оснащения и перспективного развития объектов железнодорожной инфраструктуры | E75: УК-8.3 | F75: =_xlfn.CONCAT(D75,E75) -> УК-8.3 | G75: Планирует мероприятия по организации безопасных условий труда на предприятии
B76: ПК-3.1 | C76: =VLOOKUP(B76,F:G,2,0) -> Использует техническую и нормативную документацию по проектированию объектов транспортной инфраструктуры, устройств и технического оснащения раздельных пунктов и транспортных узлов; методы расчета основных элементов; способы увязки проектных решений с передовой технологией работы станций и железнодорожных узлов; методы выполнения технико-экономических расчетов по выбору наиболее эффективных решений | F76: =_xlfn.CONCAT(D76,E76) | G76: Безопасность жизнедеятельности
B77: ПК-3.2 | C77: =VLOOKUP(B77,F:G,2,0) -> Использует методы технико-экономического обоснования при принятии решения о необходимости развития железнодорожной станции и узла; проектирования и расчетов, включая применение автоматизированного проектирования | F77: =_xlfn.CONCAT(D77,E77) | G77: Выполнение, подготовка к процедуре защиты и защита выпускной квалификационной работы
B78: ПК-4 | C78: =VLOOKUP(B78,F:G,2,0) -> Способен осуществлять организацию работы с подрядчиками на рынке транспортных услуг | D78: УК-9 | F78: =_xlfn.CONCAT(D78,E78) -> УК-9 | G78: Способен использовать базовые дефектологические знания в социальной и профессиональной сферах
B79: ПК-4.1 | C79: =VLOOKUP(B79,F:G,2,0) -> Решает задачи по организации работы экспедиторских фирм, оформляет необходимые документы для заключения договоров с юридическими и физическими лицами на транспортно-экспедиционное обслуживание грузовладельцев | E79: УК-9.1 | F79: =_xlfn.CONCAT(D79,E79) -> УК-9.1 | G79: Осуществляет взаимодействие в социальной и профессиональной сферах с лицами с ограниченными возможностями здоровья и инвалидами
B80: ПК-4.2 | C80: =VLOOKUP(B80,F:G,2,0) -> Разрабатывает эффективные схемы взаимоотношения промышленного и магистрального транспорта в процессе оказания логистической услуги перевозки груза в цепи поставок | F80: =_xlfn.CONCAT(D80,E80) | G80: Организация доступной среды
A81: ОПК-4 | B81: ПК-4.3 | C81: =VLOOKUP(B81,F:G,2,0) -> Анализирует информацию о планируемых мероприятиях, разрабатывает эффективные схемы взаимоотношений в процессе оказания логистической услуги перевозки груза, организует планирование услуг, этапов, сроков доставки | F81: =_xlfn.CONCAT(D81,E81) | G81: Выполнение, подготовка к процедуре защиты и защита выпускной квалификационной работы
B82: ПК-4.4 | C82: =VLOOKUP(B82,F:G,2,0) -> Определяет перечень необходимых услуг на транспортном рынке, выбирает подрядчика на основе критериального анализа, проверяет договор на содержание, полноту и соответствие услуг, организует работу с подрядчиками на рынке транспортных услуг | E82: УК-9.2 | F82: =_xlfn.CONCAT(D82,E82) -> УК-9.2 | G82: Планирует мероприятия по организации доступной среды на объектах транспорта для безбарьерного обслуживания пассажиров из числа инвалидов и лиц с ограниченными возможностями здоровья
B83: ПК-5 | C83: =VLOOKUP(B83,F:G,2,0) -> Способен осуществлять организацию перевозочного процесса и улучшения качества оказания логистических услуг | F83: =_xlfn.CONCAT(D83,E83) | G83: Организация доступной среды
B84: ПК-5.1 | C84: =VLOOKUP(B84,F:G,2,0) -> Разрабатывает математические модели для решения транспортных задач и улучшения качества оказания логистических услуг | F84: =_xlfn.CONCAT(D84,E84) | G84: Выполнение, подготовка к процедуре защиты и защита выпускной квалификационной работы
B85: ПК-5.2 | C85: =VLOOKUP(B85,F:G,2,0) -> Планирует деятельность по продвижению транспортно-логистических услуг и выбору оптимальных схем доставки грузов в цепи поставок | D85: УК-10 | F85: =_xlfn.CONCAT(D85,E85) -> УК-10 | G85: Способен принимать обоснованные экономические решения в различных областях жизнедеятельности
B86: ПК-5.3 | C86: =VLOOKUP(B86,F:G,2,0) -> Решает задачи по повышению эффективности технических и технологических мероприятий при организации перевозочного процесса и оказании логистических услуг | E86: УК-10.1 | F86: =_xlfn.CONCAT(D86,E86) -> УК-10.1 | G86: Анализирует и критически оценивает информацию, необходимую для принятия обоснованных экономических решений
B87: ПК-5.4 | C87: =VLOOKUP(B87,F:G,2,0) -> Планирует логистические мероприятия по организации контейнерных и пакетных перевозок в технологии работы терминальных систем транспорта | F87: =_xlfn.CONCAT(D87,E87) | G87: Экономика
B88: ПК-5.5 | C88: =VLOOKUP(B88,F:G,2,0) -> Планирует логистические операции, распределяет задачи в процессе реализации ключевых и поддерживающих функций логистики | F88: =_xlfn.CONCAT(D88,E88) | G88: Выполнение, подготовка к процедуре защиты и защита выпускной квалификационной работы
B89: ПК-6 | C89: =VLOOKUP(B89,F:G,2,0) -> Способен осуществлять контроль и управление системой организации пассажирских перевозок на железнодорожном транспорте | E89: УК-10.2 | F89: =_xlfn.CONCAT(D89,E89) -> УК-10.2 | G89: Применяет методы личного экономического и финансового планирования для достижения текущих и долгосрочных финансовых целей, использует финансовые инструменты для управления личными финансами (личным бюджетом), контролирует собственные экономические и финансовые риски
B90: ПК-6.1 | C90: =VLOOKUP(B90,F:G,2,0) -> Решает задачи, направленные на организацию пассажирских перевозок на железнодорожном транспорте | F90: =_xlfn.CONCAT(D90,E90) | G90: Экономика
B91: ПК-6.2 | C91: =VLOOKUP(B91,F:G,2,0) -> Решает задачи, направленные на организацию работы и эксплуатацию вокзальных комплексов, транспортно-пересадочных узлов | F91: =_xlfn.CONCAT(D91,E91) | G91: Выполнение, подготовка к процедуре защиты и защита выпускной квалификационной работы
C92: =VLOOKUP(B92,F:G,2,0) -> #N/A | D92: УК-11 | F92: =_xlfn.CONCAT(D92,E92) -> УК-11 | G92: Способен формировать нетерпимое отношение к проявлениям экстремизма, терроризма, коррупционному поведению и противодействовать им в профессиональной деятельности
C93: =VLOOKUP(B93,F:G,2,0) -> #N/A | E93: УК-11.1 | F93: =_xlfn.CONCAT(D93,E93) -> УК-11.1 | G93: Раскрывает механизм проявления коррупционного поведения и определяет способы противодействия ему в профессиональной деятельности
C94: =VLOOKUP(B94,F:G,2,0) -> #N/A | F94: =_xlfn.CONCAT(D94,E94) | G94: Правовое обеспечение профессиональной деятельности
C95: =VLOOKUP(B95,F:G,2,0) -> #N/A | F95: =_xlfn.CONCAT(D95,E95) | G95: Выполнение, подготовка к процедуре защиты и защита выпускной квалификационной работы
C96: =VLOOKUP(B96,F:G,2,0) -> #N/A | E96: УК-11.2 | F96: =_xlfn.CONCAT(D96,E96) -> УК-11.2 | G96: Обосновывает правовыми средствами свою гражданскую позицию в отношении терроризма и экстремизма и применяет способы противодействия им в профессиональной сфере
C97: =VLOOKUP(B97,F:G,2,0) -> #N/A | F97: =_xlfn.CONCAT(D97,E97) | G97: Правовое обеспечение профессиональной деятельности
C98: =VLOOKUP(B98,F:G,2,0) -> #N/A | F98: =_xlfn.CONCAT(D98,E98) | G98: Выполнение, подготовка к процедуре защиты и защита выпускной квалификационной работы
A99: ОПК-5 | C99: =VLOOKUP(B99,F:G,2,0) -> #N/A | D99: ОПК-1 | F99: =_xlfn.CONCAT(D99,E99) -> ОПК-1 | G99: Способен применять естественнонаучные и общеинженерные знания, методы математического анализа и моделирования в профессиональной деятельности
C100: =VLOOKUP(B100,F:G,2,0) -> #N/A | E100: ОПК-1.1 | F100: =_xlfn.CONCAT(D100,E100) -> ОПК-1.1 | G100: Применяет методы высшей математики для решения задач профессиональной деятельности
...

Sheet Матрица
C1: Все индикаторы дисциплины | G1: 7 | K1: 1 | L1: 2 | M1: 3 | N1: 4 | O1: 5 | P1: 6 | Q1: 7 | R1: 8 | S1: 9 | T1: 10 | U1: 11 | V1: 12 | W1: 13 | X1: 14 | Y1: 15 | Z1: 16 | AA1: 17 | AB1: 18 | AC1: 19 | AD1: 20 | AE1: 21 | AF1: 22 | AG1: 23 | AH1: 24 | AI1: 25
C2: =HLOOKUP($G$1,$K$1:$AI$4,4,0) -> ОПК-3.1; ПК-2.1; ПК-2.2 | G2: =_xlfn.CONCAT(HLOOKUP($G$1,$K$1:$AI$4,3,0)," ",HLOOKUP($G$1,$K$1:$AI$4,2,0)) -> Б1.О.07 Экономика транспортных систем | I2: Индекс | J2: Содержание | K2: Деловые коммуникации (билингвальный курс) | L2: Психологические основы интеллектуально-личностного развития | M2: Проектно-процессное управление | N2: Правовое обеспечение транспортных процессов | O2: Стратегические решения в функциональных областях организации | P2: Научно-техническое обеспечение технологических процессов на транспорте | Q2: Экономика транспортных систем | R2: Математическое моделирование в профессиональной деятельности | S2: Системы искусственного интеллекта | T2: Цифровые технологии в науке и на транспорте | U2: Коммерческая деятельность на транспорте | V2: Управление процессами перевозок | W2: Технология работы единой транспортной системы | X2: Организация мультимодальных и интермодальных перевозок | Y2: Транспортное и складское обеспечение логистики | Z2: Мультимодальные транспортно-логистические центры | AA2: Актово-претензионное дело | AB2: Стандартизация и сертификация транспортных услуг | AC2: Учебная практика (ознакомительная практика) | AD2: Производственная практика (научно-исследовательская работа) | AE2: Производственная практика (технологическая (производственно-технологическая) практика) | AF2: Производственная практика (эксплуатационная практика) | AG2: Итого без учета факультативов | AH2: Клиентоориентированность на транспорте | AI2: Развитие семейного сознания личности
A3: Компетенция (код) | B3: Компетенция (расшифровка) | C3: Индикатор (код) | D3: Индикатор (расшифровка) | E3: Компетенция (объединенная) | F3: Индикатор (объединенный) | G3: Название дисциплины | H3: Количество вопросов | K3: Б1.О.01 | L3: Б1.О.02 | M3: Б1.О.03 | N3: Б1.О.04 | O3: Б1.О.05 | P3: Б1.О.06 | Q3: Б1.О.07 | R3: Б1.О.08 | S3: Б1.О.09.01 | T3: Б1.О.09.02 | U3: Б1.В.01 | V3: Б1.В.02 | W3: Б1.В.ДВ.01.01 | X3: Б1.В.ДВ.01.02 | Y3: Б1.В.ДВ.02.01 | Z3: Б1.В.ДВ.02.02 | AA3: Б1.В.ДВ.03.01 | AB3: Б1.В.ДВ.03.02 | AC3: Б2.О.01(У) | AD3: Б2.О.02(Н) | AE3: Б2.В.01(П) | AF3: Б2.В.02(П) | AH3: ФТД.01 | AI3: ФТД.02
A4: =IFERROR(LEFT(C4,SEARCH(".",C4)-1),"") -> ОПК-3 | B4: =IFERROR(VLOOKUP(A4,$I$5:$J$54,2,0),"") -> Способен управлять жизненным циклом инженерных продуктов с учетом экономических, экологических и социальных ограничений | C4: {=_xlfn.TEXTSPLIT(C2,," ")} -> ОПК-3.1; | D4: =IFERROR(VLOOKUP(IF(RIGHT(C4,1)<>";",C4,LEFT(C4,LEN(C4)-1)),$I$5:$J$54,2,0),"") -> Анализирует стадии жизненного цикла инженерных продуктов и подходы к экономической оценке их стоимости | E4: =_xlfn.CONCAT(A4," ",B4) -> ОПК-3 Способен управлять жизненным циклом инженерных продуктов с учетом экономических, экологических и социальных ограничений | F4: =_xlfn.CONCAT(IF(RIGHT(C4,1)<>";",C4,LEFT(C4,LEN(C4)-1))," ",D4) -> ОПК-3.1 Анализирует стадии жизненного цикла инженерных продуктов и подходы к экономической оценке их стоимости | G4: =$G$2 -> Б1.О.07 Экономика транспортных систем | H4: =IFERROR(VLOOKUP(IF(RIGHT(C4,1)<>";",C4,LEFT(C4,LEN(C4)-1)),$I$5:$AI$54,$G$1+2,0),"") -> 10 | K4: УК-4.1; УК-4.2; УК-5.1; УК-5.2 | L4: УК-1.1; УК-1.2; УК-6.1; УК-6.2 | M4: УК-2.1; УК-2.2; УК-3.1; УК-3.2 | N4: ОПК-6.1 | O4: ОПК-2.1; ОПК-2.2; ОПК-3.2; ОПК-6.2 | P4: ОПК-1.1; ОПК-4.1; ОПК-4.2 | Q4: ОПК-3.1; ПК-2.1; ПК-2.2 | R4: ОПК-1.2 | S4: ОПК-5.3 | T4: ОПК-5.1; ОПК-5.2 | U4: ПК-3.1; ПК-3.2 | V4: ПК-1.1 | W4: ПК-1.3 | X4: ПК-1.3 | Y4: ПК-1.2 | Z4: ПК-1.2 | AA4: ПК-4.1; ПК-4.2 | AB4: ПК-4.1; ПК-4.2 | AC4: ОПК-3.1; ПК-1.1 | AD4: ОПК-4.1; ПК-2.1 | AE4: ПК-1.2; ПК-1.3; ПК-4.1; ПК-4.2 | AF4: ПК-2.2; ПК-3.1; ПК-3.2 | AH4: ПК-1.1 | AI4: УК-5.1
A5: =IFERROR(LEFT(C5,SEARCH(".",C5)-1),"") -> ПК-2 | B5: =IFERROR(VLOOKUP(A5,$I$5:$J$54,2,0),"") -> Способен осуществлять контроль ключевых финансовых показателей логистической деятельности по перевозке груза в цепи поставок | C5: ПК-2.1; | D5: =IFERROR(VLOOKUP(IF(RIGHT(C5,1)<>";",C5,LEFT(C5,LEN(C5)-1)),$I$5:$J$54,2,0),"") -> Анализирует финансовую информацию и разрабатывает план мероприятий по достижению финансовых показателей деятельности по перевозке грузов в рамках цепей поставок | E5: =_xlfn.CONCAT(A5," ",B5) -> ПК-2 Способен осуществлять контроль ключевых финансовых показателей логистической деятельности по перевозке груза в цепи поставок | F5: =_xlfn.CONCAT(IF(RIGHT(C5,1)<>";",C5,LEFT(C5,LEN(C5)-1))," ",D5) -> ПК-2.1 Анализирует финансовую информацию и разрабатывает план мероприятий по достижению финансовых показателей деятельности по перевозке грузов в рамках цепей поставок | G5: =IF(F5<>" ",$G$2,"") -> Б1.О.07 Экономика транспортных систем | H5: =IFERROR(VLOOKUP(IF(RIGHT(C5,1)<>";",C5,LEFT(C5,LEN(C5)-1)),$I$5:$AI$54,$G$1+2,0),"") -> 6 | I5: УК-1 | J5: Способен осуществлять критический анализ проблемных ситуаций на основе системного подхода, вырабатывать стратегию действий | L5: 16 | AG5: =SUM(S5:AF5) -> 0
A6: =IFERROR(LEFT(C6,SEARCH(".",C6)-1),"") -> ПК-2 | B6: =IFERROR(VLOOKUP(A6,$I$5:$J$54,2,0),"") -> Способен осуществлять контроль ключевых финансовых показателей логистической деятельности по перевозке груза в цепи поставок | C6: ПК-2.2 | D6: =IFERROR(VLOOKUP(IF(RIGHT(C6,1)<>";",C6,LEFT(C6,LEN(C6)-1)),$I$5:$J$54,2,0),"") -> Контролирует финансовые показатели логистической деятельности | E6: =_xlfn.CONCAT(A6," ",B6) -> ПК-2 Способен осуществлять контроль ключевых финансовых показателей логистической деятельности по перевозке груза в цепи поставок | F6: =_xlfn.CONCAT(IF(RIGHT(C6,1)<>";",C6,LEFT(C6,LEN(C6)-1))," ",D6) -> ПК-2.2 Контролирует финансовые показатели логистической деятельности | G6: =IF(F6<>" ",$G$2,"") -> Б1.О.07 Экономика транспортных систем | H6: =IFERROR(VLOOKUP(IF(RIGHT(C6,1)<>";",C6,LEFT(C6,LEN(C6)-1)),$I$5:$AI$54,$G$1+2,0),"") -> 6 | I6: УК-1.1 | J6: Анализирует проблемную ситуацию, выявляя ее составляющие и связи между ними. Критические оценивает имеющиеся факты проблемных ситуаций, проверяет их логическую непротиворечивость, подтверждаемость и воспроизводимость | L6: 8 | AG6: =SUM(S6:AF6) -> 0 | AH6: =IFERROR(SEARCH(_xlfn.CONCAT(" ",$I6),AH$4),"") | AI6: =IFERROR(SEARCH(_xlfn.CONCAT(" ",$I6),AI$4),"")
A7: =IFERROR(LEFT(C7,SEARCH(".",C7)-1),"") | B7: =IFERROR(VLOOKUP(A7,$I$5:$J$54,2,0),"") | D7: =IFERROR(VLOOKUP(IF(RIGHT(C7,1)<>";",C7,LEFT(C7,LEN(C7)-1)),$I$5:$J$54,2,0),"") | E7: =_xlfn.CONCAT(A7," ",B7) | F7: =_xlfn.CONCAT(IF(RIGHT(C7,1)<>";",C7,LEFT(C7,LEN(C7)-1))," ",D7) | G7: =IF(F7<>" ",$G$2,"") | H7: =IFERROR(VLOOKUP(IF(RIGHT(C7,1)<>";",C7,LEFT(C7,LEN(C7)-1)),$I$5:$AI$54,$G$1+2,0),"") | I7: УК-1.2 | J7: Разрабатывает стратегию решения проблемной ситуации на основе системного подхода, сценарных условий, оценки рисков | L7: 8 | AG7: =SUM(S7:AF7) -> 0 | AH7: =IFERROR(SEARCH(_xlfn.CONCAT(" ",$I7),AH$4),"") | AI7: =IFERROR(SEARCH(_xlfn.CONCAT(" ",$I7),AI$4),"")
A8: =IFERROR(LEFT(C8,SEARCH(".",C8)-1),"") | B8: =IFERROR(VLOOKUP(A8,$I$5:$J$54,2,0),"") | D8: =IFERROR(VLOOKUP(IF(RIGHT(C8,1)<>";",C8,LEFT(C8,LEN(C8)-1)),$I$5:$J$54,2,0),"") | E8: =_xlfn.CONCAT(A8," ",B8) | F8: =_xlfn.CONCAT(IF(RIGHT(C8,1)<>";",C8,LEFT(C8,LEN(C8)-1))," ",D8) | G8: =IF(F8<>" ",$G$2,"") | H8: =IFERROR(VLOOKUP(IF(RIGHT(C8,1)<>";",C8,LEFT(C8,LEN(C8)-1)),$I$5:$AI$54,$G$1+2,0),"") | I8: УК-2 | J8: Способен управлять проектом на всех этапах его жизненного цикла | M8: 16 | AG8: =SUM(S8:AF8) -> 0
A9: =IFERROR(LEFT(C9,SEARCH(".",C9)-1),"") | B9: =IFERROR(VLOOKUP(A9,$I$5:$J$54,2,0),"") | D9: =IFERROR(VLOOKUP(IF(RIGHT(C9,1)<>";",C9,LEFT(C9,LEN(C9)-1)),$I$5:$J$54,2,0),"") | E9: =_xlfn.CONCAT(A9," ",B9) | F9: =_xlfn.CONCAT(IF(RIGHT(C9,1)<>";",C9,LEFT(C9,LEN(C9)-1))," ",D9) | G9: =IF(F9<>" ",$G$2,"") | H9: =IFERROR(VLOOKUP(IF(RIGHT(C9,1)<>";",C9,LEFT(C9,LEN(C9)-1)),$I$5:$AI$54,$G$1+2,0),"") | I9: УК-2.1 | J9: Инициирует, разрабатывает концепцию, формулирует цель, задачи, ожидаемые результаты в стратегическом управлении проектом | M9: 8 | AG9: =SUM(S9:AF9) -> 0 | AH9: =IFERROR(SEARCH(_xlfn.CONCAT(" ",$I9),AH$4),"") | AI9: =IFERROR(SEARCH(_xlfn.CONCAT(" ",$I9),AI$4),"")
A10: =IFERROR(LEFT(C10,SEARCH(".",C10)-1),"") | B10: =IFERROR(VLOOKUP(A10,$I$5:$J$54,2,0),"") | D10: =IFERROR(VLOOKUP(IF(RIGHT(C10,1)<>";",C10,LEFT(C10,LEN(C10)-1)),$I$5:$J$54,2,0),"") | E10: =_xlfn.CONCAT(A10," ",B10) | F10: =_xlfn.CONCAT(IF(RIGHT(C10,1)<>";",C10,LEFT(C10,LEN(C10)-1))," ",D10) | G10: =IF(F10<>" ",$G$2,"") | H10: =IFERROR(VLOOKUP(IF(RIGHT(C10,1)<>";",C10,LEFT(C10,LEN(C10)-1)),$I$5:$AI$54,$G$1+2,0),"") | I10: УК-2.2 | J10: Осуществляет организационное, финансовое, инвестиционное, экспертное сопровождение проектов, решает оперативные задачи на всех этапах жизненного цикла проекта | M10: 8 | AG10: =SUM(S10:AF10) -> 0 | AH10: =IFERROR(SEARCH(_xlfn.CONCAT(" ",$I10),AH$4),"") | AI10: =IFERROR(SEARCH(_xlfn.CONCAT(" ",$I10),AI$4),"")
A11: =IFERROR(LEFT(C11,SEARCH(".",C11)-1),"") | B11: =IFERROR(VLOOKUP(A11,$I$5:$J$54,2,0),"") | D11: =IFERROR(VLOOKUP(IF(RIGHT(C11,1)<>";",C11,LEFT(C11,LEN(C11)-1)),$I$5:$J$54,2,0),"") | E11: =_xlfn.CONCAT(A11," ",B11) | F11: =_xlfn.CONCAT(IF(RIGHT(C11,1)<>";",C11,LEFT(C11,LEN(C11)-1))," ",D11) | G11: =IF(F11<>" ",$G$2,"") | H11: =IFERROR(VLOOKUP(IF(RIGHT(C11,1)<>";",C11,LEFT(C11,LEN(C11)-1)),$I$5:$AI$54,$G$1+2,0),"") | I11: УК-3 | J11: Способен организовывать и руководить работой команды, вырабатывая командную стратегию для достижения поставленной цели | M11: 16 | AG11: =SUM(S11:AF11) -> 0
A12: =IFERROR(LEFT(C12,SEARCH(".",C12)-1),"") | B12: =IFERROR(VLOOKUP(A12,$I$5:$J$54,2,0),"") | D12: =IFERROR(VLOOKUP(IF(RIGHT(C12,1)<>";",C12,LEFT(C12,LEN(C12)-1)),$I$5:$J$54,2,0),"") | E12: =_xlfn.CONCAT(A12," ",B12) | F12: =_xlfn.CONCAT(IF(RIGHT(C12,1)<>";",C12,LEFT(C12,LEN(C12)-1))," ",D12) | G12: =IF(F12<>" ",$G$2,"") | H12: =IFERROR(VLOOKUP(IF(RIGHT(C12,1)<>";",C12,LEFT(C12,LEN(C12)-1)),$I$5:$AI$54,$G$1+2,0),"") | I12: =_xlfn.CONCAT(I11,".1") -> УК-3.1 | J12: Вырабатывает стратегию и тактику, мотивирует работу команды, выработку коллегиальных решений средствами технологий лидерства | M12: 8 | AG12: =SUM(S12:AF12) -> 0 | AH12: =IFERROR(SEARCH(_xlfn.CONCAT(" ",$I12),AH$4),"") | AI12: =IFERROR(SEARCH(_xlfn.CONCAT(" ",$I12),AI$4),"")
A13: =IFERROR(LEFT(C13,SEARCH(".",C13)-1),"") | B13: =IFERROR(VLOOKUP(A13,$I$5:$J$54,2,0),"") | D13: =IFERROR(VLOOKUP(IF(RIGHT(C13,1)<>";",C13,LEFT(C13,LEN(C13)-1)),$I$5:$J$54,2,0),"") | E13: =_xlfn.CONCAT(A13," ",B13) | F13: =_xlfn.CONCAT(IF(RIGHT(C13,1)<>";",C13,LEFT(C13,LEN(C13)-1))," ",D13) | G13: =IF(F13<>" ",$G$2,"") | H13: =IFERROR(VLOOKUP(IF(RIGHT(C13,1)<>";",C13,LEFT(C13,LEN(C13)-1)),$I$5:$AI$54,$G$1+2,0),"") | I13: =_xlfn.CONCAT(I11,".2") -> УК-3.2 | J13: Организует и корректирует рабочие процессы в соответствии с функциональными и проектными задачами команды | M13: 8 | AG13: =SUM(S13:AF13) -> 0 | AH13: =IFERROR(SEARCH(_xlfn.CONCAT(" ",$I13),AH$4),"") | AI13: =IFERROR(SEARCH(_xlfn.CONCAT(" ",$I13),AI$4),"")
A14: =IFERROR(LEFT(C14,SEARCH(".",C14)-1),"") | B14: =IFERROR(VLOOKUP(A14,$I$5:$J$54,2,0),"") | D14: =IFERROR(VLOOKUP(IF(RIGHT(C14,1)<>";",C14,LEFT(C14,LEN(C14)-1)),$I$5:$J$54,2,0),"") | E14: =_xlfn.CONCAT(A14," ",B14) | F14: =_xlfn.CONCAT(IF(RIGHT(C14,1)<>";",C14,LEFT(C14,LEN(C14)-1))," ",D14) | G14: =IF(F14<>" ",$G$2,"") | H14: =IFERROR(VLOOKUP(IF(RIGHT(C14,1)<>";",C14,LEFT(C14,LEN(C14)-1)),$I$5:$AI$54,$G$1+2,0),"") | I14: УК-4 | J14: Способен применять современные коммуникативные технологии, в том числе на иностранном(ых) языке(ах), для академического и профессионального взаимодействия | K14: 16 | AG14: =SUM(S14:AF14) -> 0
I15: =_xlfn.CONCAT(I14,".1") -> УК-4.1 | J15: Формирует в соответствии с фонетическими, графическими, лексическими, грамматическими, стилистическими нормами языка, в том числе иностранного (ых), деловую коммуникацию в устной и письменной формах | K15: 8 | AG15: =SUM(S15:AF15) -> 0 | AH15: =IFERROR(SEARCH(_xlfn.CONCAT(" ",$I15),AH$4),"") | AI15: =IFERROR(SEARCH(_xlfn.CONCAT(" ",$I15),AI$4),"")
I16: =_xlfn.CONCAT(I14,".2") -> УК-4.2 | J16: Обеспечивает обсуждение результатов профессионального взаимодействия на публичных мероприятиях, в деловой переписке, в дискуссии, в иных форматах коммуникации | K16: 8 | AG16: =SUM(S16:AF16) -> 0 | AH16: =IFERROR(SEARCH(_xlfn.CONCAT(" ",$I16),AH$4),"") | AI16: =IFERROR(SEARCH(_xlfn.CONCAT(" ",$I16),AI$4),"")
I17: УК-5 | J17: Способен анализировать и учитывать разнообразие культур в процессе межкультурного взаимодействия | K17: 16 | AG17: =SUM(S17:AF17) -> 0 | AI17: 18
I18: =_xlfn.CONCAT(I17,".1") -> УК-5.1 | J18: Осуществляет профессиональное взаимодействие с учетом разнообразия культур, принятых норм, правил, стандартов, личностных и профессиональных ценностей и убеждений | K18: 8 | AG18: =SUM(S18:AF18) -> 0 | AH18: =IFERROR(SEARCH(_xlfn.CONCAT(" ",$I18),AH$4),"") | AI18: 18
I19: =_xlfn.CONCAT(I17,".2") -> УК-5.2 | J19: Анализирует причины разногласий в межкультурной коммуникации, разрешает конфликты, устраняет условия их возникновения | K19: 8 | AG19: =SUM(S19:AF19) -> 0 | AH19: =IFERROR(SEARCH(_xlfn.CONCAT(" ",$I19),AH$4),"") | AI19: =IFERROR(SEARCH(_xlfn.CONCAT(" ",$I19),AI$4),"")
I20: УК-6 | J20: Способен определять и реализовывать приоритеты собственной деятельности и способы ее совершенствования на основе самооценки | L20: 16 | AG20: =SUM(S20:AF20) -> 0
I21: =_xlfn.CONCAT(I20,".1") -> УК-6.1 | J21: Определяет приоритеты профессионального роста и способы совершенствования собственной деятельности на основе самооценки | L21: 8 | AG21: =SUM(S21:AF21) -> 0 | AH21: =IFERROR(SEARCH(_xlfn.CONCAT(" ",$I21),AH$4),"") | AI21: =IFERROR(SEARCH(_xlfn.CONCAT(" ",$I21),AI$4),"")
I22: =_xlfn.CONCAT(I20,".2") -> УК-6.2 | J22: Выстраивает гибкую профессиональную траекторию, используя инструменты непрерывного образования. Целесообразно использует собственные интеллектуальные и физические ресурсы | L22: 8 | AG22: =SUM(S22:AF22) -> 0 | AH22: =IFERROR(SEARCH(_xlfn.CONCAT(" ",$I22),AH$4),"") | AI22: =IFERROR(SEARCH(_xlfn.CONCAT(" ",$I22),AI$4),"")
I23: ОПК-1 | J23: Способен ставить и решать научно-технические задачи в сфере своей профессиональной деятельности и новых междисциплинарных направлений с использованием естественно-научных и математических моделей с учетом последних достижений науки и техники | P23: 4 | R23: 18 | AG23: =SUM(S23:AF23) -> 0
I24: =_xlfn.CONCAT(I23,".1") -> ОПК-1.1 | J24: Решает научно-технические задачи в сфере транспорта с учетом последних достижений науки и техники | P24: 4 | AG24: =SUM(S24:AF24) -> 0 | AH24: =IFERROR(SEARCH(_xlfn.CONCAT(" ",$I24),AH$4),"") | AI24: =IFERROR(SEARCH(_xlfn.CONCAT(" ",$I24),AI$4),"")
I25: =_xlfn.CONCAT(I23,".2") -> ОПК-1.2 | J25: Использует естественно-научные и математические модели для решения научно-технических задач в сфере своей профессиональной деятельности | R25: 18 | AG25: =SUM(S25:AF25) -> 0 | AH25: =IFERROR(SEARCH(_xlfn.CONCAT(" ",$I25),AH$4),"") | AI25: =IFERROR(SEARCH(_xlfn.CONCAT(" ",$I25),AI$4),"")
I26: ОПК-2 | J26: Способен принимать обоснованные решения в области проектного и финансового менеджмента в сфере своей профессиональной деятельности | O26: 16 | AG26: =SUM(S26:AF26) -> 0
I27: =_xlfn.CONCAT(I26,".1") -> ОПК-2.1 | J27: Предлагает механизм приобретения конкурентных преимуществ в условиях высокой степени изменчивости и непредсказуемости среды | O27: 8 | AG27: =SUM(S27:AF27) -> 0 | AH27: =IFERROR(SEARCH(_xlfn.CONCAT(" ",$I27),AH$4),"") | AI27: =IFERROR(SEARCH(_xlfn.CONCAT(" ",$I27),AI$4),"")
I28: =_xlfn.CONCAT(I26,".2") -> ОПК-2.2 | J28: Использует инструментарий стратегического анализа и обосновывает принимаемые решения в рамках будущей профессиональной деятельности | O28: 8 | AG28: =SUM(S28:AF28) -> 0 | AH28: =IFERROR(SEARCH(_xlfn.CONCAT(" ",$I28),AH$4),"") | AI28: =IFERROR(SEARCH(_xlfn.CONCAT(" ",$I28),AI$4),"")
I29: ОПК-3 | J29: Способен управлять жизненным циклом инженерных продуктов с учетом экономических, экологических и социальных ограничений | O29: 4 | Q29: 10 | AC29: 2 | AG29: =SUM(S29:AF29) -> 2
I30: =_xlfn.CONCAT(I29,".1") -> ОПК-3.1 | J30: Анализирует стадии жизненного цикла инженерных продуктов и подходы к экономической оценке их стоимости | Q30: 10 | AC30: 2 | AG30: =SUM(S30:AF30) -> 2 | AH30: =IFERROR(SEARCH(_xlfn.CONCAT(" ",$I30),AH$4),"") | AI30: =IFERROR(SEARCH(_xlfn.CONCAT(" ",$I30),AI$4),"")
I31: =_xlfn.CONCAT(I29,".2") -> ОПК-3.2 | J31: Разрабатывает продуктовую стратегию развития организации с целью повышения конкурентоспособности на базе усовершенствования производимой продукции и действующей технологии производства, создания принципиально новых продуктов | O31: 4 | AG31: =SUM(S31:AF31) -> 0 | AH31: =IFERROR(SEARCH(_xlfn.CONCAT(" ",$I31),AH$4),"") | AI31: =IFERROR(SEARCH(_xlfn.CONCAT(" ",$I31),AI$4),"")
I32: ОПК-4 | J32: Способен проводить исследования, организовывать самостоятельную и коллективную научно-исследовательскую деятельность при решении инженерных и научно-технических задач, включающих планирование и постановку эксперимента, критическую оценку и интерпретацию результатов | P32: 14 | AD32: 2 | AG32: =SUM(S32:AF32) -> 2
I33: =_xlfn.CONCAT(I32,".1") -> ОПК-4.1 | J33: Планирует и организует научно-исследовательскую деятельность для решения инженерных и научно-технических задач | P33: 7 | AD33: 2 | AG33: =SUM(S33:AF33) -> 2 | AH33: =IFERROR(SEARCH(_xlfn.CONCAT(" ",$I33),AH$4),"") | AI33: =IFERROR(SEARCH(_xlfn.CONCAT(" ",$I33),AI$4),"")
I34: =_xlfn.CONCAT(I32,".2") -> ОПК-4.2 | J34: Осуществляет исследовательскую деятельность технологических процессов на транспорте | P34: 7 | AG34: =SUM(S34:AF34) -> 0 | AH34: =IFERROR(SEARCH(_xlfn.CONCAT(" ",$I34),AH$4),"") | AI34: =IFERROR(SEARCH(_xlfn.CONCAT(" ",$I34),AI$4),"")
I35: ОПК-5 | J35: Способен применять инструментарий формализации научно-технических задач, использовать прикладное программное обеспечение для моделирования и проектирования систем и процессов | S35: 18 | T35: 18 | AG35: =SUM(S35:AF35) -> 36
I36: =_xlfn.CONCAT(I35,".1") -> ОПК-5.1 | J36: Идентифицирует и анализирует методы и инструментарии для формализации научно-технических задач в сфере логистики и транспорта | T36: 9 | AG36: =SUM(S36:AF36) -> 9 | AH36: =IFERROR(SEARCH(_xlfn.CONCAT(" ",$I36),AH$4),"") | AI36: =IFERROR(SEARCH(_xlfn.CONCAT(" ",$I36),AI$4),"")
I37: =_xlfn.CONCAT(I35,".2") -> ОПК-5.2 | J37: Предлагает алгоритм оценки и выбора прикладного программного обеспечения для моделирования и проектирования систем и процессов на транспорте | T37: 9 | AG37: =SUM(S37:AF37) -> 9 | AH37: =IFERROR(SEARCH(_xlfn.CONCAT(" ",$I37),AH$4),"") | AI37: =IFERROR(SEARCH(_xlfn.CONCAT(" ",$I37),AI$4),"")
I38: =_xlfn.CONCAT(I35,".3") -> ОПК-5.3 | J38: Использует методы искусственного интеллекта (машинного обучения) и анализа больших данных для решения прикладных задач | S38: 18 | AG38: =SUM(S38:AF38) -> 18 | AH38: =IFERROR(SEARCH(_xlfn.CONCAT(" ",$I38),AH$4),"") | AI38: =IFERROR(SEARCH(_xlfn.CONCAT(" ",$I38),AI$4),"")
I39: ОПК-6 | J39: Способен оценивать социальные, правовые и общекультурные последствия принимаемых решений при осуществлении профессиональной деятельности | N39: 18 | O39: 2 | AG39: =SUM(S39:AF39) -> 0
I40: =_xlfn.CONCAT(I39,".1") -> ОПК-6.1 | J40: Проводит управленческие мероприятия по достижению запланированных результатов в своей профессиональной деятельности | N40: 18 | AG40: =SUM(S40:AF40) -> 0 | AH40: =IFERROR(SEARCH(_xlfn.CONCAT(" ",$I40),AH$4),"") | AI40: =IFERROR(SEARCH(_xlfn.CONCAT(" ",$I40),AI$4),"")
I41: =_xlfn.CONCAT(I39,".2") -> ОПК-6.2 | J41: Оценивает условия и последствия, принимаемых стратегических организационно-управленческих решений при осуществлении профессиональной деятельности | O41: 2 | AG41: =SUM(S41:AF41) -> 0 | AH41: =IFERROR(SEARCH(_xlfn.CONCAT(" ",$I41),AH$4),"") | AI41: =IFERROR(SEARCH(_xlfn.CONCAT(" ",$I41),AI$4),"")
I42: ПК-1 | J42: Способен осуществлять контроль ключевых операционных показателей эффективности логистической деятельности по перевозке груза в цепи поставок | V42: 18 | W42: 18 | X42: 18 | Y42: 18 | Z42: 18 | AC42: 2 | AE42: 4 | AG42: =SUM(S42:AF42) -> 96 | AH42: 18
I43: =_xlfn.CONCAT(I42,".1") -> ПК-1.1 | J43: Решает задачи по расчету показателей работы транспорта по перевозке груза в цепи поставок | V43: 18 | AC43: 2 | AG43: =SUM(S43:AF43) -> 20 | AH43: 18 | AI43: =IFERROR(SEARCH(_xlfn.CONCAT(" ",$I43),AI$4),"")
I44: =_xlfn.CONCAT(I42,".2") -> ПК-1.2 | J44: Идентифицирует и анализирует показатели проекта, направленные на снижение себестоимости операций, повышение производительности труда и эффективности операционной деятельности | Y44: 18 | Z44: 18 | AE44: 2 | AG44: =SUM(S44:AF44) -> 38 | AH44: =IFERROR(SEARCH(_xlfn.CONCAT(" ",$I44),AH$4),"") | AI44: =IFERROR(SEARCH(_xlfn.CONCAT(" ",$I44),AI$4),"")
I45: =_xlfn.CONCAT(I42,".3") -> ПК-1.3 | J45: Составляет графики грузопотоков, определяет способы доставки и вида транспорта по перевозке груза в цепи поставок | W45: 18 | X45: 18 | AE45: 2 | AG45: =SUM(S45:AF45) -> 38 | AH45: =IFERROR(SEARCH(_xlfn.CONCAT(" ",$I45),AH$4),"") | AI45: =IFERROR(SEARCH(_xlfn.CONCAT(" ",$I45),AI$4),"")
I46: ПК-2 | J46: Способен осуществлять контроль ключевых финансовых показателей логистической деятельности по перевозке груза в цепи поставок | Q46: 12 | AD46: 2 | AF46: 2 | AG46: =SUM(S46:AF46) -> 4
I47: =_xlfn.CONCAT(I46,".1") -> ПК-2.1 | J47: Анализирует финансовую информацию и разрабатывает план мероприятий по достижению финансовых показателей деятельности по перевозке грузов в рамках цепей поставок | Q47: 6 | AD47: 2 | AG47: =SUM(S47:AF47) -> 2 | AH47: =IFERROR(SEARCH(_xlfn.CONCAT(" ",$I47),AH$4),"") | AI47: =IFERROR(SEARCH(_xlfn.CONCAT(" ",$I47),AI$4),"")
I48: =_xlfn.CONCAT(I46,".2") -> ПК-2.2 | J48: Контролирует финансовые показатели логистической деятельности | Q48: 6 | AF48: 2 | AG48: =SUM(S48:AF48) -> 2 | AH48: =IFERROR(SEARCH(_xlfn.CONCAT(" ",$I48),AH$4),"") | AI48: =IFERROR(SEARCH(_xlfn.CONCAT(" ",$I48),AI$4),"")
I49: ПК-3 | J49: Способен осуществлять разработку коммерческой политики по оказанию логистической услуги перевозки груза в цепи поставок | U49: 18 | AF49: 4 | AG49: =SUM(S49:AF49) -> 22
I50: =_xlfn.CONCAT(I49,".1") -> ПК-3.1 | J50: Анализирует взаимосвязи между функциональными стратегиями компаний с целью подготовки сбалансированных управленческих решений по оказанию логистической услуги перевозки груза в цепи поставок | U50: 9 | AF50: 2 | AG50: =SUM(S50:AF50) -> 11 | AH50: =IFERROR(SEARCH(_xlfn.CONCAT(" ",$I50),AH$4),"") | AI50: =IFERROR(SEARCH(_xlfn.CONCAT(" ",$I50),AI$4),"")
I51: =_xlfn.CONCAT(I49,".2") -> ПК-3.2 | J51: Планирует мероприятия по управлению запасами грузовладельцев распределительной транспортной сети | U51: 9 | AF51: 2 | AG51: =SUM(S51:AF51) -> 11 | AH51: =IFERROR(SEARCH(_xlfn.CONCAT(" ",$I51),AH$4),"") | AI51: =IFERROR(SEARCH(_xlfn.CONCAT(" ",$I51),AI$4),"")
I52: ПК-4 | J52: Способен осуществлять разработку системы управления рисками при оказании логистических услуг по перевозке грузов в цепи поставок | AA52: 18 | AB52: 18 | AE52: 4 | AG52: =SUM(S52:AF52) -> 40
I53: =_xlfn.CONCAT(I52,".1") -> ПК-4.1 | J53: Идентифицирует и оценивает логистические риски, разрабатывает мероприятия по их управлению при оказании логистических услуг | AA53: 9 | AB53: 9 | AE53: 2 | AG53: =SUM(S53:AF53) -> 20 | AH53: =IFERROR(SEARCH(_xlfn.CONCAT(" ",$I53),AH$4),"") | AI53: =IFERROR(SEARCH(_xlfn.CONCAT(" ",$I53),AI$4),"")
I54: =_xlfn.CONCAT(I52,".2") -> ПК-4.2 | J54: Разрабатывает и проводит мероприятия по управлению рисками при оказании услуг по перевозке грузов | AA54: 9 | AB54: 9 | AE54: 2 | AG54: =SUM(S54:AF54) -> 20 | AH54: =IFERROR(SEARCH(_xlfn.CONCAT(" ",$I54),AH$4),"") | AI54: =IFERROR(SEARCH(_xlfn.CONCAT(" ",$I54),AI$4),"")
I55: Итого по дисциплине | K55: =SUM(K5,K8,K11,K14,K17,K20,K23,K26,K29,K32,K35,K39,K42,K46,K49,K52) -> 32 | L55: =SUM(L5,L8,L11,L14,L17,L20,L23,L26,L29,L32,L35,L39,L42,L46,L49,L52) -> 32 | M55: =SUM(M5,M8,M11,M14,M17,M20,M23,M26,M29,M32,M35,M39,M42,M46,M49,M52) -> 32 | N55: =SUM(N5,N8,N11,N14,N17,N20,N23,N26,N29,N32,N35,N39,N42,N46,N49,N52) -> 18 | O55: =SUM(O5,O8,O11,O14,O17,O20,O23,O26,O29,O32,O35,O39,O42,O46,O49,O52) -> 22 | P55: =SUM(P5,P8,P11,P14,P17,P20,P23,P26,P29,P32,P35,P39,P42,P46,P49,P52) -> 18 | Q55: =SUM(Q5,Q8,Q11,Q14,Q17,Q20,Q23,Q26,Q29,Q32,Q35,Q39,Q42,Q46,Q49,Q52) -> 22 | R55: =SUM(R5,R8,R11,R14,R17,R20,R23,R26,R29,R32,R35,R39,R42,R46,R49,R52) -> 18 | ... AI55: =SUM(AI5,AI8,AI11,AI14,AI17,AI20,AI23,AI26,AI29,AI32,AI35,AI39,AI42,AI46,AI49,AI52) -> 18
